Workbook

Sheet Base_Amostral
A1: codigo_municipio_completo | B1: codigo_uf | C1: nome_uf | D1: codigo_municipio | E1: nome_municipio | F1: regiao | G1: url | H1: site_encontrado | I1: url_confiavel | J1: status_validacao_url | K1: populacao_residente_2022 | L1: area_territorial_km2 | M1: densidade_demografica_hab_km2 | N1: chave_aleatoria | O1: observacao
A2: 5107909 | B2: 51 | C2: Mato Grosso | D2: 7909 | E2: Sinop | F2: Centro-Oeste | G2: https://www.sinop.mt.gov.br/ | H2: Sim | I2: Sim | J2: Apto | K2: 196312 | L2: 3990,87 | M2: 49,19 | N2: 0.002508886 | O2: 0
A3: 5108402 | B3: 51 | C3: Mato Grosso | D3: 8402 | E3: Várzea Grande | F3: Centro-Oeste | G3: https://www.varzeagrande.mt.gov.br/ | H3: Sim | I3: Sim | J3: Apto | K3: 300078 | L3: 724,279 | M3: 414,31 | N3: 0.004229534 | O3: 0
A4: 5206602 | B4: 52 | C4: Goiás | D4: 6602 | E4: Cumari | F4: Centro-Oeste | G4: https://cumari.go.gov.br/ | H4: Sim | I4: Sim | J4: Apto | K4: 2927 | L4: 568,365 | M4: 5,15 | N4: 0.005838812 | O4: 0
A5: 5220454 | B5: 52 | C5: Goiás | D5: 20454 | E5: Senador Canedo | F5: Centro-Oeste | G5: https://senadorcanedo.go.gov.br/ | H5: Sim | I5: Sim | J5: Apto | K5: 155635 | L5: 247,005 | M5: 630,09 | N5: 0.006292154 | O5: 0
A6: 5207253 | B6: 52 | C6: Goiás | D6: 7253 | E6: Doverlândia | F6: Centro-Oeste | G6: https://doverlandia.go.gov.br/ | H6: Sim | I6: Sim | J6: Apto | K6: 6956 | L6: 3227,558 | M6: 2,16 | N6: 0.006417589 | O6: 0
A7: 5103437 | B7: 51 | C7: Mato Grosso | D7: 3437 | E7: Curvelândia | F7: Centro-Oeste | G7: https://www.curvelandia.mt.gov.br/ | H7: Sim | I7: Sim | J7: Apto | K7: 4903 | L7: 357,128 | M7: 13,73 | N7: 0.006579241 | O7: 0
A8: 5204656 | B8: 52 | C8: Goiás | D8: 4656 | E8: Campinaçu | F8: Centro-Oeste | G8: https://www.campinacu.go.gov.br/ | H8: Sim | I8: Sim | J8: Apto | K8: 3708 | L8: 1978,386 | M8: 1,87 | N8: 0.008315084 | O8: 0
A9: 5213905 | B9: 52 | C9: Goiás | D9: 13905 | E9: Mossâmedes | F9: Centro-Oeste | G9: http://mossamedes.go.gov.br/ | H9: Sim | I9: Sim | J9: Apto | K9: 4654 | L9: 684,882 | M9: 6,8 | N9: 0.010133321 | O9: 0
A10: 5002704 | B10: 50 | C10: Mato Grosso do Sul | D10: 2704 | E10: Campo Grande | F10: Centro-Oeste | G10: https://www.campogrande.ms.gov.br/ | H10: Sim | I10: Sim | J10: Apto | K10: 898100 | L10: 8082,978 | M10: 111,11 | N10: 0.011278 | O10: 0
A11: 5210802 | B11: 52 | C11: Goiás | D11: 10802 | E11: Itajá | F11: Centro-Oeste | G11: https://itaja.go.gov.br/ | H11: Sim | I11: Sim | J11: Apto | K11: 4380 | L11: 2082,736 | M11: 2,1 | N11: 0.012106377 | O11: 0
A12: 5007208 | B12: 50 | C12: Mato Grosso do Sul | D12: 7208 | E12: Rio Brilhante | F12: Centro-Oeste | G12: https://riobrilhante.ms.gov.br/ | H12: Sim | I12: Sim | J12: Apto | K12: 37601 | L12: 3983,562 | M12: 9,44 | N12: 0.015918488 | O12: 0
A13: 5214838 | B13: 52 | C13: Goiás | D13: 14838 | E13: Nova Crixás | F13: Centro-Oeste | G13: https://novacrixas.go.gov.br/ | H13: Sim | I13: Sim | J13: Apto | K13: 12815 | L13: 7308,681 | M13: 1,75 | N13: 0.016464116 | O13: 0
... A141: 2304236 | B141: 23 | C141: Ceará | D141: 4236 | E141: Croatá | F141: Nordeste | G141: https://croata.ce.gov.br/ | H141: Sim | I141: Sim | J141: Apto | K141: 17481 | L141: 696,348 | M141: 25,1 | N141: 0.071170911 | O141: 0
A142: 2206407 | B142: 22 | C142: Piauí | D142: 6407 | E142: Monsenhor Gil | F142: Nordeste | G142: https://monsenhorgil.pi.gov.br/ | H142: Sim | I142: Sim | J142: Apto | K142: 10255 | L142: 567.86 | M142: 18.06 | N142: 0.071459944 | O142: 0
A143: 2105203 | B143: 21 | C143: Maranhão | D143: 5203 | E143: Igarapé Grande | F143: Nordeste | G143: https://www.igarapegrande.ma.gov.br/ | H143: Sim | I143: Sim | J143: Apto | K143: 10231 | L143: 346.218 | M143: 29.55 | N143: 0.071777594 | O143: 0
A144: 2105104 | B144: 21 | C144: Maranhão | D144: 5104 | E144: Icatu | F144: Nordeste | G144: https://www.icatu.ma.gov.br/ | H144: Sim | I144: Sim | J144: Apto | K144: 24794 | L144: 1124.445 | M144: 22.05 | N144: 0.072415158 | O144: 0
A145: 2504074 | B145: 25 | C145: Paraíba | D145: 4074 | E145: Caraúbas | F145: Nordeste | G145: https://caraubas.rn.gov.br/ | H145: Sim | I145: Sim | J145: Apto | K145: 19727 | L145: 1095.803 | M145: 18 | N145: 0.072676517 | O145: 0
A146: 2109809 | B146: 21 | C146: Maranhão | D146: 9809 | E146: Santa Helena | F146: Nordeste | G146: https://santahelena.ma.gov.br/ | H146: Sim | I146: Sim | J146: Apto | K146: 41561 | L146: 2191.168 | M146: 18.97 | N146: 0.073116644 | O146: 0
A147: 2614501 | B147: 26 | C147: Pernambuco | D147: 14501 | E147: Surubim | F147: Nordeste | G147: https://surubim.pe.gov.br/ | H147: Sim | I147: Sim | J147: Apto | K147: 64120 | L147: 252,896 | M147: 253,54 | N147: 0.073506142 | O147: 0
A148: 2927002 | B148: 29 | C148: Bahia | D148: 27002 | E148: Rio Real | F148: Nordeste | G148: https://rioreal.ba.gov.br/ | H148: Sim | I148: Sim | J148: Apto | K148: 35362 | L148: 739,775 | M148: 47,8 | N148: 0.074273743 | O148: 0
A149: 1502707 | B149: 15 | C149: Pará | D149: 2707 | E149: Conceição do Araguaia | F149: Norte | G149: https://www.conceicaodoaraguaia.pa.gov.br/ | H149: Sim | I149: Sim | J149: Apto | K149: 44617 | L149: 5829,482 | M149: 7,65 | N149: 0.002090179 | O149: 0
A150: 1303403 | B150: 13 | C150: Amazonas | D150: 3403 | E150: Parintins | F150: Norte | G150: https://www.parintins.am.gov.br/ | H150: Sim | I150: Sim | J150: Apto | K150: 96372 | L150: 5956,047 | M150: 16,18 | N150: 0.003152961 | O150: 0
A151: 1101807 | B151: 11 | C151: Rondônia | D151: 1807 | E151: Vale do Paraíso | F151: Norte | G151: https://www.valedoparaiso.ro.gov.br/ | H151: Sim | I151: Sim | J151: Apto | K151: 6479 | L151: 965,676 | M151: 6,71 | N151: 0.003862403 | O151: 0
A152: 1600550 | B152: 16 | C152: Amapá | D152: 550 | E152: Pracuúba | F152: Norte | G152: https://www.pracuuba.ap.gov.br/ | H152: Sim | I152: Sim | J152: Apto | K152: 3803 | L152: 4948,508 | M152: 0,77 | N152: 0.005229401 | O152: 0
A153: 1718808 | B153: 17 | C153: Tocantins | D153: 18808 | E153: Sampaio | F153: Norte | G153: https://www.sampaio.to.gov.br/ | H153: Sim | I153: Sim | J153: Apto | K153: 4215 | L153: 222,435 | M153: 18,95 | N153: 0.014196673 | O153: 0
A154: 1702208 | B154: 17 | C154: Tocantins | D154: 2208 | E154: Araguatins | F154: Norte | G154: https://www.araguatins.to.gov.br/ | H154: Sim | I154: Sim | J154: Apto | K154: 31918 | L154: 2633,278 | M154: 12,12 | N154: 0.014233899 | O154: 0
A155: 1600709 | B155: 16 | C155: Amapá | D155: 709 | E155: Tartarugalzinho | F155: Norte | G155: https://www.tartarugalzinho.ap.gov.br/ | H155: Sim | I155: Sim | J155: Apto | K155: 12945 | L155: 6684,705 | M155: 1,94 | N155: 0.014378356 | O155: 0
A156: 1200393 | B156: 12 | C156: Acre | D156: 393 | E156: Porto Walter | F156: Norte | G156: https://www.portowalter.ac.gov.br/ | H156: Sim | I156: Sim | J156: Apto | K156: 10735 | L156: 6446,385 | M156: 1,67 | N156: 0.015577227 | O156: 0
A157: 1300839 | B157: 13 | C157: Amazonas | D157: 839 | E157: Caapiranga | F157: Norte | G157: https://www.caapiranga.am.gov.br/ | H157: Sim | I157: Sim | J157: Apto | K157: 13469 | L157: 9455,539 | M157: 1,42 | N157: 0.016174427 | O157: 0
A158: 1100015 | B158: 11 | C158: Rondônia | D158: 15 | E158: Alta Floresta D'Oeste | F158: Norte | G158: https://www.altaflorestadoeste.ro.gov.br/ | H158: Sim | I158: Sim | J158: Apto | K158: 21494 | L158: 7067,127 | M158: 3,04 | N158: 0.016815501 | O158: 0
... A363: 4300570 | B363: 43 | C363: Rio Grande do Sul | D363: 570 | E363: Alto Feliz | F363: Sul | G363: https://www.altofeliz.rs.gov.br/web/ | H363: Sim | I363: Sim | J363: Apto | K363: 3072 | L363: 78,175 | M363: 39,3 | N363: 0.06913189 | O363: 0

Sheet Execucoes
A1: id_execucao | B1: rodada | C1: sessao | D1: codigo_municipio_completo | E1: nota_amaweb | F1: status_amaweb | G1: avaliado_amaweb_em | H1: nota_accessmonitor | I1: status_accessmonitor | J1: avaliado_accessmonitor_em | K1: tem_resultado_amaweb | L1: tem_resultado_accessmonitor | M1: status_geral | N1: observacao_analise | O1: criado_em | P1: atualizado_em | Q1: chave_municipio_rodada
A2: 1 | B2: r00 | C2: 2026-06-20_00-25-00__validacao_tcc_unifal_r00 | D2: 1200179 | E2: 61 | F2: sucesso | G2: 46193.018 | H2: 61 | I2: sucesso | J2: 46193.019 | K2: 1 | L2: 1 | M2: completo | O2: 46193.018 | P2: 46193.019 | Q2: =D2&"|"&B2 -> 1200179|r00
A3: 2 | B3: r00 | C3: 2026-06-20_00-25-00__validacao_tcc_unifal_r00 | D3: 2700102 | E3: 57 | F3: sucesso | G3: 46193.02 | I3: sucesso_sem_nota | J3: 46193.021 | K3: 1 | L3: 0 | M3: parcial | O3: 46193.018 | P3: 46193.021 | Q3: =D3&"|"&B3 -> 2700102|r00
A4: 3 | B4: r00 | C4: 2026-06-20_00-25-00__validacao_tcc_unifal_r00 | D4: 5203939 | E4: 75 | F4: sucesso | G4: 46193.018 | H4: 72 | I4: sucesso | J4: 46193.018 | K4: 1 | L4: 1 | M4: completo | O4: 46193.018 | P4: 46193.018 | Q4: =D4&"|"&B4 -> 5203939|r00
A5: 4 | B5: r00 | C5: 2026-06-20_00-25-00__validacao_tcc_unifal_r00 | D5: 5204656 | E5: 69 | F5: sucesso | G5: 46193.019 | H5: 69 | I5: sucesso | J5: 46193.019 | K5: 1 | L5: 1 | M5: completo | O5: 46193.018 | P5: 46193.019 | Q5: =D5&"|"&B5 -> 5204656|r00
A6: 5 | B6: r00 | C6: 2026-06-20_00-25-00__validacao_tcc_unifal_r00 | D6: 1200393 | E6: 61 | F6: sucesso | G6: 46193.021 | H6: 61 | I6: sucesso | J6: 46193.022 | K6: 1 | L6: 1 | M6: completo | O6: 46193.019 | P6: 46193.022 | Q6: =D6&"|"&B6 -> 1200393|r00
A7: 6 | B7: r00 | C7: 2026-06-20_00-25-00__validacao_tcc_unifal_r00 | D7: 5205802 | E7: 74 | F7: sucesso | G7: 46193.019 | H7: 74 | I7: sucesso | J7: 46193.02 | K7: 1 | L7: 1 | M7: completo | O7: 46193.019 | P7: 46193.02 | Q7: =D7&"|"&B7 -> 5205802|r00
A8: 7 | B8: r00 | C8: 2026-06-20_00-25-00__validacao_tcc_unifal_r00 | D8: 5206602 | E8: 70 | F8: sucesso | G8: 46193.02 | H8: 69 | I8: sucesso | J8: 46193.02 | K8: 1 | L8: 1 | M8: completo | O8: 46193.02 | P8: 46193.02 | Q8: =D8&"|"&B8 -> 5206602|r00
A9: 8 | B9: r00 | C9: 2026-06-20_00-25-00__validacao_tcc_unifal_r00 | D9: 5207253 | E9: 76 | F9: sucesso | G9: 46193.021 | H9: 78 | I9: sucesso | J9: 46193.021 | K9: 1 | L9: 1 | M9: completo | O9: 46193.02 | P9: 46193.021 | Q9: =D9&"|"&B9 -> 5207253|r00
A10: 9 | B10: r00 | C10: 2026-06-20_00-25-00__validacao_tcc_unifal_r00 | D10: 2702207 | E10: 54 | F10: sucesso | G10: 46193.021 | H10: 58 | I10: sucesso | J10: 46193.021 | K10: 1 | L10: 1 | M10: completo | O10: 46193.021 | P10: 46193.021 | Q10: =D10&"|"&B10 -> 2702207|r00
A11: 10 | B11: r00 | C11: 2026-06-20_00-25-00__validacao_tcc_unifal_r00 | D11: 5208806 | E11: 70 | F11: sucesso | G11: 46193.021 | H11: 72 | I11: sucesso | J11: 46193.022 | K11: 1 | L11: 1 | M11: completo | O11: 46193.021 | P11: 46193.022 | Q11: =D11&"|"&B11 -> 5208806|r00
A12: 11 | B12: r00 | C12: 2026-06-20_00-25-00__validacao_tcc_unifal_r00 | D12: 2702900 | E12: 64 | F12: sucesso | G12: 46193.022 | H12: 68 | I12: sucesso | J12: 46193.022 | K12: 1 | L12: 1 | M12: completo | O12: 46193.021 | P12: 46193.022 | Q12: =D12&"|"&B12 -> 2702900|r00
A13: 12 | B13: r00 | C13: 2026-06-20_00-25-00__validacao_tcc_unifal_r00 | D13: 5209457 | E13: 73 | F13: sucesso | G13: 46193.022 | H13: 72 | I13: sucesso | J13: 46193.022 | K13: 1 | L13: 1 | M13: completo | O13: 46193.022 | P13: 46193.022 | Q13: =D13&"|"&B13 -> 5209457|r00
A14: 13 | B14: r00 | C14: 2026-06-20_00-25-00__validacao_tcc_unifal_r00 | D14: 1600303 | E14: 92 | F14: sucesso | G14: 46193.022 | I14: sucesso_sem_nota | J14: 46193.023 | K14: 1 | L14: 0 | M14: parcial | O14: 46193.022 | P14: 46193.023 | Q14: =D14&"|"&B14 -> 1600303|r00
A15: 14 | B15: r00 | C15: 2026-06-20_00-25-00__validacao_tcc_unifal_r00 | D15: 2703304 | E15: 64 | F15: sucesso | G15: 46193.023 | H15: 60 | I15: sucesso | J15: 46193.023 | K15: 1 | L15: 1 | M15: completo | O15: 46193.022 | P15: 46193.023 | Q15: =D15&"|"&B15 -> 2703304|r00
A16: 15 | B16: r00 | C16: 2026-06-20_00-25-00__validacao_tcc_unifal_r00 | D16: 5210802 | E16: 63 | F16: sucesso | G16: 46193.023 | H16: 62 | I16: sucesso | J16: 46193.023 | K16: 1 | L16: 1 | M16: completo | O16: 46193.022 | P16: 46193.023 | Q16: =D16&"|"&B16 -> 5210802|r00
A17: 16 | B17: r00 | C17: 2026-06-20_00-25-00__validacao_tcc_unifal_r00 | D17: 2706422 | E17: 58 | F17: sucesso | G17: 46193.023 | H17: 57 | I17: sucesso | J17: 46193.023 | K17: 1 | L17: 1 | M17: completo | O17: 46193.023 | P17: 46193.023 | Q17: =D17&"|"&B17 -> 2706422|r00
A18: 17 | B18: r00 | C18: 2026-06-20_00-25-00__validacao_tcc_unifal_r00 | D18: 5211800 | E18: 70 | F18: sucesso | G18: 46193.023 | H18: 71 | I18: sucesso | J18: 46193.024 | K18: 1 | L18: 1 | M18: completo | O18: 46193.023 | P18: 46193.024 | Q18: =D18&"|"&B18 -> 5211800|r00
A19: 18 | B19: r00 | C19: 2026-06-20_00-25-00__validacao_tcc_unifal_r00 | D19: 1600550 | E19: 65 | F19: sucesso | G19: 46193.024 | H19: 68 | I19: sucesso | J19: 46193.024 | K19: 1 | L19: 1 | M19: completo | O19: 46193.023 | P19: 46193.024 | Q19: =D19&"|"&B19 -> 1600550|r00
A20: 19 | B20: r00 | C20: 2026-06-20_00-25-00__validacao_tcc_unifal_r00 | D20: 2708808 | E20: 52 | F20: sucesso | G20: 46193.024 | H20: 52 | I20: sucesso | J20: 46193.024 | K20: 1 | L20: 1 | M20: completo | O20: 46193.023 | P20: 46193.024 | Q20: =D20&"|"&B20 -> 2708808|r00
A21: 20 | B21: r00 | C21: 2026-06-20_00-25-00__validacao_tcc_unifal_r00 | D21: 5213806 | E21: 76 | F21: sucesso | G21: 46193.024 | H21: 73 | I21: sucesso | J21: 46193.024 | K21: 1 | L21: 1 | M21: completo | O21: 46193.024 | P21: 46193.024 | Q21: =D21&"|"&B21 -> 5213806|r00
A22: 21 | B22: r00 | C22: 2026-06-20_00-25-00__validacao_tcc_unifal_r00 | D22: 1600709 | E22: 59 | F22: sucesso | G22: 46193.024 | H22: 66 | I22: sucesso | J22: 46193.025 | K22: 1 | L22: 1 | M22: completo | O22: 46193.024 | P22: 46193.025 | Q22: =D22&"|"&B22 -> 1600709|r00
A23: 22 | B23: r00 | C23: 2026-06-20_00-25-00__validacao_tcc_unifal_r00 | D23: 2900603 | E23: 60 | F23: sucesso | G23: 46193.025 | H23: 61 | I23: sucesso | J23: 46193.025 | K23: 1 | L23: 1 | M23: completo | O23: 46193.024 | P23: 46193.025 | Q23: =D23&"|"&B23 -> 2900603|r00
A24: 23 | B24: r00 | C24: 2026-06-20_00-25-00__validacao_tcc_unifal_r00 | D24: 5213905 | E24: 76 | F24: sucesso | G24: 46193.025 | H24: 75 | I24: sucesso | J24: 46193.025 | K24: 1 | L24: 1 | M24: completo | O24: 46193.024 | P24: 46193.025 | Q24: =D24&"|"&B24 -> 5213905|r00
A25: 24 | B25: r00 | C25: 2026-06-20_00-25-00__validacao_tcc_unifal_r00 | D25: 1300508 | E25: 92 | F25: sucesso | G25: 46193.025 | H25: 71 | I25: sucesso | J25: 46193.025 | K25: 1 | L25: 1 | M25: completo | O25: 46193.025 | P25: 46193.025 | Q25: =D25&"|"&B25 -> 1300508|r00
A26: 25 | B26: r00 | C26: 2026-06-20_00-25-00__validacao_tcc_unifal_r00 | D26: 2901106 | E26: 79 | F26: sucesso | G26: 46193.025 | H26: 82 | I26: sucesso | J26: 46193.025 | K26: 1 | L26: 1 | M26: completo | O26: 46193.025 | P26: 46193.025 | Q26: =D26&"|"&B26 -> 2901106|r00
... A35: 34 | B35: r00 | C35: 2026-06-20_00-25-00__validacao_tcc_unifal_r00 | D35: 5216908 | E35: 74 | F35: sucesso | G35: 46193.027 | H35: 72 | I35: sucesso | J35: 46193.027 | K35: 1 | L35: 1 | M35: completo | O35: 46193.026 | P35: 46193.027 | Q35: =D35&"|"&B35 -> 5216908|r00
A36: 35 | B36: r00 | C36: 2026-06-20_00-25-00__validacao_tcc_unifal_r00 | D36: 1303403 | E36: 92 | F36: sucesso | G36: 46193.027 | I36: sucesso_sem_nota | J36: 46193.028 | K36: 1 | L36: 0 | M36: parcial | O36: 46193.027 | P36: 46193.028 | Q36: =D36&"|"&B36 -> 1303403|r00
A37: 36 | B37: r00 | C37: 2026-06-20_00-25-00__validacao_tcc_unifal_r00 | D37: 5220454 | E37: 67 | F37: sucesso | G37: 46193.027 | H37: 69 | I37: sucesso | J37: 46193.028 | K37: 1 | L37: 1 | M37: completo | O37: 46193.027 | P37: 46193.028 | Q37: =D37&"|"&B37 -> 5220454|r00
A38: 37 | B38: r00 | C38: 2026-06-20_00-25-00__validacao_tcc_unifal_r00 | D38: 2911402 | E38: 80 | F38: sucesso | G38: 46193.027 | H38: 83 | I38: sucesso | J38: 46193.028 | K38: 1 | L38: 1 | M38: completo | O38: 46193.027 | P38: 46193.028 | Q38: =D38&"|"&B38 -> 2911402|r00
A39: 38 | B39: r00 | C39: 2026-06-20_00-25-00__validacao_tcc_unifal_r00 | D39: 2912103 | E39: 53 | F39: sucesso | G39: 46193.028 | H39: 54 | I39: sucesso | J39: 46193.028 | K39: 1 | L39: 1 | M39: completo | O39: 46193.028 | P39: 46193.028 | Q39: =D39&"|"&B39 -> 2912103|r00
A40: 39 | B40: r00 | C40: 2026-06-20_00-25-00__validacao_tcc_unifal_r00 | D40: 5100102 | F40: falha_de_carregamento | G40: 46193.035 | H40: 63 | I40: sucesso | J40: 46193.035 | K40: 0 | L40: 1 | M40: parcial | O40: 46193.028 | P40: 46193.035 | Q40: =D40&"|"&B40 -> 5100102|r00
A41: 40 | B41: r00 | C41: 2026-06-20_00-25-00__validacao_tcc_unifal_r00 | D41: 1500107 | F41: falha_de_carregamento | G41: 46193.035 | H41: 60 | I41: sucesso | J41: 46193.036 | K41: 0 | L41: 1 | M41: parcial | O41: 46193.028 | P41: 46193.036 | Q41: =D41&"|"&B41 -> 1500107|r00
A42: 41 | B42: r00 | C42: 2026-06-20_00-25-00__validacao_tcc_unifal_r00 | D42: 2913705 | E42: 50 | F42: sucesso | G42: 46193.029 | H42: 57 | I42: sucesso | J42: 46193.029 | K42: 1 | L42: 1 | M42: completo | O42: 46193.028 | P42: 46193.029 | Q42: =D42&"|"&B42 -> 2913705|r00
A43: 42 | B43: r00 | C43: 2026-06-20_00-25-00__validacao_tcc_unifal_r00 | D43: 2915007 | F43: falha_de_carregamento | G43: 46193.036 | I43: sucesso_sem_nota | J43: 46193.037 | K43: 0 | L43: 0 | M43: falha_total | O43: 46193.029 | P43: 46193.037 | Q43: =D43&"|"&B43 -> 2915007|r00
A44: 43 | B44: r00 | C44: 2026-06-20_00-25-00__validacao_tcc_unifal_r00 | D44: 5101902 | E44: 51 | F44: sucesso | G44: 46193.037 | H44: 52 | I44: sucesso | J44: 46193.037 | K44: 1 | L44: 1 | M44: completo | O44: 46193.035 | P44: 46193.037 | Q44: =D44&"|"&B44 -> 5101902|r00
A45: 44 | B45: r00 | C45: 2026-06-20_00-25-00__validacao_tcc_unifal_r00 | D45: 1500958 | E45: 62 | F45: sucesso | G45: 46193.036 | H45: 64 | I45: sucesso | J45: 46193.036 | K45: 1 | L45: 1 | M45: completo | O45: 46193.036 | P45: 46193.036 | Q45: =D45&"|"&B45 -> 1500958|r00
A46: 45 | B46: r00 | C46: 2026-06-20_00-25-00__validacao_tcc_unifal_r00 | D46: 1502707 | E46: 92 | F46: sucesso | G46: 46193.04 | H46: 61 | I46: sucesso | J46: 46193.04 | K46: 1 | L46: 1 | M46: completo | O46: 46193.036 | P46: 46193.04 | Q46: =D46&"|"&B46 -> 1502707|r00
A47: 46 | B47: r00 | C47: 2026-06-20_00-25-00__validacao_tcc_unifal_r00 | D47: 5102504 | E47: 66 | F47: sucesso | G47: 46193.037 | H47: 72 | I47: sucesso | J47: 46193.038 | K47: 1 | L47: 1 | M47: completo | O47: 46193.037 | P47: 46193.038 | Q47: =D47&"|"&B47 -> 5102504|r00
A48: 47 | B48: r00 | C48: 2026-06-20_00-25-00__validacao_tcc_unifal_r00 | D48: 2915106 | E48: 92 | F48: sucesso | G48: 46193.039 | H48: 73 | I48: sucesso | J48: 46193.04 | K48: 1 | L48: 1 | M48: completo | O48: 46193.037 | P48: 46193.04 | Q48: =D48&"|"&B48 -> 2915106|r00
A49: 48 | B49: r00 | C49: 2026-06-20_00-25-00__validacao_tcc_unifal_r00 | D49: 5103437 | E49: 92 | F49: sucesso | G49: 46193.038 | H49: 81 | I49: sucesso | J49: 46193.038 | K49: 1 | L49: 1 | M49: completo | O49: 46193.038 | P49: 46193.038 | Q49: =D49&"|"&B49 -> 5103437|r00
A50: 49 | B50: r00 | C50: 2026-06-20_00-25-00__validacao_tcc_unifal_r00 | D50: 5104807 | E50: 77 | F50: sucesso | G50: 46193.038 | H50: 74 | I50: sucesso | J50: 46193.039 | K50: 1 | L50: 1 | M50: completo | O50: 46193.038 | P50: 46193.039 | Q50: =D50&"|"&B50 -> 5104807|r00
A51: 50 | B51: r00 | C51: 2026-06-20_00-25-00__validacao_tcc_unifal_r00 | D51: 5105580 | E51: 44 | F51: sucesso | G51: 46193.039 | H51: 54 | I51: sucesso | J51: 46193.039 | K51: 1 | L51: 1 | M51: completo | O51: 46193.039 | P51: 46193.039 | Q51: =D51&"|"&B51 -> 5105580|r00
A52: 51 | B52: r00 | C52: 2026-06-20_00-25-00__validacao_tcc_unifal_r00 | D52: 5106828 | E52: 81 | F52: sucesso | G52: 46193.04 | H52: 78 | I52: sucesso | J52: 46193.04 | K52: 1 | L52: 1 | M52: completo | O52: 46193.039 | P52: 46193.04 | Q52: =D52&"|"&B52 -> 5106828|r00
A53: 52 | B53: r00 | C53: 2026-06-20_00-25-00__validacao_tcc_unifal_r00 | D53: 2918357 | E53: 66 | F53: sucesso | G53: 46193.045 | H53: 77 | I53: sucesso | J53: 46193.045 | K53: 1 | L53: 1 | M53: completo | O53: 46193.04 | P53: 46193.045 | Q53: =D53&"|"&B53 -> 2918357|r00
A54: 53 | B54: r00 | C54: 2026-06-20_00-25-00__validacao_tcc_unifal_r00 | D54: 5107107 | E54: 62 | F54: sucesso | G54: 46193.041 | H54: 62 | I54: sucesso | J54: 46193.041 | K54: 1 | L54: 1 | M54: completo | O54: 46193.04 | P54: 46193.041 | Q54: =D54&"|"&B54 -> 5107107|r00
A55: 54 | B55: r00 | C55: 2026-06-20_00-25-00__validacao_tcc_unifal_r00 | D55: 1502939 | E55: 62 | F55: sucesso | G55: 46193.041 | H55: 62 | I55: sucesso | J55: 46193.041 | K55: 1 | L55: 1 | M55: completo | O55: 46193.04 | P55: 46193.041 | Q55: =D55&"|"&B55 -> 1502939|r00
... A97: 96 | B97: r00 | C97: 2026-06-20_00-25-00__validacao_tcc_unifal_r00 | D97: 2926202 | E97: 51 | F97: sucesso | G97: 46193.06 | H97: 63 | I97: sucesso | J97: 46193.061 | K97: 1 | L97: 1 | M97: completo | O97: 46193.055 | P97: 46193.061 | Q97: =D97&"|"&B97 -> 2926202|r00
A98: 97 | B98: r00 | C98: 2026-06-20_00-25-00__validacao_tcc_unifal_r00 | D98: 1718881 | E98: 92 | F98: sucesso | G98: 46193.055 | I98: sucesso_sem_nota | J98: 46193.056 | K98: 1 | L98: 0 | M98: parcial | O98: 46193.055 | P98: 46193.056 | Q98: =D98&"|"&B98 -> 1718881|r00
A99: 98 | B99: r00 | C99: 2026-06-20_00-25-00__validacao_tcc_unifal_r00 | D99: 1722107 | E99: 92 | F99: sucesso | G99: 46193.059 | H99: 71 | I99: sucesso | J99: 46193.059 | K99: 1 | L99: 1 | M99: completo | O99: 46193.056 | P99: 46193.059 | Q99: =D99&"|"&B99 -> 1722107|r00
A100: 99 | B100: r00 | C100: 2026-06-20_00-25-00__validacao_tcc_unifal_r00 | D100: 3108701 | E100: 92 | F100: sucesso | G100: 46193.06 | H100: 77 | I100: sucesso | J100: 46193.06 | K100: 1 | L100: 1 | M100: completo | O100: 46193.057 | P100: 46193.06 | Q100: =D100&"|"&B100 -> 3108701|r00
A101: 100 | B101: r00 | C101: 2026-06-20_00-25-00__validacao_tcc_unifal_r00 | D101: 4101101 | E101: 62 | F101: sucesso | G101: 46193.06 | H101: 67 | I101: sucesso | J101: 46193.06 | K101: 1 | L101: 1 | M101: completo | O101: 46193.059 | P101: 46193.06 | Q101: =D101&"|"&B101 -> 4101101|r00
A102: 101 | B102: r00 | C102: 2026-06-20_00-25-00__validacao_tcc_unifal_r00 | D102: 3109600 | E102: 63 | F102: sucesso | G102: 46193.061 | H102: 74 | I102: sucesso | J102: 46193.061 | K102: 1 | L102: 1 | M102: completo | O102: 46193.06 | P102: 46193.061 | Q102: =D102&"|"&B102 -> 3109600|r00
A103: 102 | B103: r00 | C103: 2026-06-20_00-25-00__validacao_tcc_unifal_r00 | D103: 4101655 | E103: 68 | F103: sucesso | G103: 46193.061 | H103: 69 | I103: sucesso | J103: 46193.061 | K103: 1 | L103: 1 | M103: completo | O103: 46193.061 | P103: 46193.061 | Q103: =D103&"|"&B103 -> 4101655|r00
A104: 103 | B104: r00 | C104: 2026-06-20_00-25-00__validacao_tcc_unifal_r00 | D104: 2926806 | E104: 61 | F104: sucesso | G104: 46193.061 | H104: 63 | I104: sucesso | J104: 46193.061 | K104: 1 | L104: 1 | M104: completo | O104: 46193.061 | P104: 46193.061 | Q104: =D104&"|"&B104 -> 2926806|r00
A105: 104 | B105: r00 | C105: 2026-06-20_00-25-00__validacao_tcc_unifal_r00 | D105: 3109808 | E105: 56 | F105: sucesso | G105: 46193.061 | H105: 60 | I105: sucesso | J105: 46193.062 | K105: 1 | L105: 1 | M105: completo | O105: 46193.061 | P105: 46193.062 | Q105: =D105&"|"&B105 -> 3109808|r00
A106: 105 | B106: r00 | C106: 2026-06-20_00-25-00__validacao_tcc_unifal_r00 | D106: 2927002 | E106: 80 | F106: sucesso | G106: 46193.061 | H106: 87 | I106: sucesso | J106: 46193.062 | K106: 1 | L106: 1 | M106: completo | O106: 46193.061 | P106: 46193.062 | Q106: =D106&"|"&B106 -> 2927002|r00
A107: 106 | B107: r00 | C107: 2026-06-20_00-25-00__validacao_tcc_unifal_r00 | D107: 4102901 | E107: 92 | F107: sucesso | G107: 46193.064 | H107: 66 | I107: sucesso | J107: 46193.064 | K107: 1 | L107: 1 | M107: completo | O107: 46193.061 | P107: 46193.064 | Q107: =D107&"|"&B107 -> 4102901|r00
A108: 107 | B108: r00 | C108: 2026-06-20_00-25-00__validacao_tcc_unifal_r00 | D108: 3113008 | E108: 92 | F108: sucesso | G108: 46193.062 | H108: 65 | I108: sucesso | J108: 46193.062 | K108: 1 | L108: 1 | M108: completo | O108: 46193.062 | P108: 46193.062 | Q108: =D108&"|"&B108 -> 3113008|r00
A109: 108 | B109: r00 | C109: 2026-06-20_00-25-00__validacao_tcc_unifal_r00 | D109: 2928406 | E109: 70 | F109: sucesso | G109: 46193.062 | H109: 73 | I109: sucesso | J109: 46193.062 | K109: 1 | L109: 1 | M109: completo | O109: 46193.062 | P109: 46193.062 | Q109: =D109&"|"&B109 -> 2928406|r00
A110: 109 | B110: r00 | C110: 2026-06-20_00-25-00__validacao_tcc_unifal_r00 | D110: 3115102 | E110: 92 | F110: sucesso | G110: 46193.062 | H110: 72 | I110: sucesso | J110: 46193.062 | K110: 1 | L110: 1 | M110: completo | O110: 46193.062 | P110: 46193.062 | Q110: =D110&"|"&B110 -> 3115102|r00
... A197: 196 | B197: r00 | C197: 2026-06-20_00-25-00__validacao_tcc_unifal_r00 | D197: 2107605 | E197: 63 | F197: sucesso | G197: 46193.095 | H197: 63 | I197: sucesso | J197: 46193.096 | K197: 1 | L197: 1 | M197: completo | O197: 46193.095 | P197: 46193.096 | Q197: =D197&"|"&B197 -> 2107605|r00
A198: 197 | B198: r00 | C198: 2026-06-20_00-25-00__validacao_tcc_unifal_r00 | D198: 4300638 | F198: falha_de_carregamento | G198: 46193.102 | I198: erro | J198: 46193.103 | K198: 0 | L198: 0 | M198: falha_total | O198: 46193.095 | P198: 46193.103 | Q198: =D198&"|"&B198 -> 4300638|r00
A199: 198 | B199: r00 | C199: 2026-06-20_00-25-00__validacao_tcc_unifal_r00 | D199: 3145356 | E199: 92 | F199: sucesso | G199: 46193.095 | H199: 66 | I199: sucesso | J199: 46193.095 | K199: 1 | L199: 1 | M199: completo | O199: 46193.095 | P199: 46193.095 | Q199: =D199&"|"&B199 -> 3145356|r00
A200: 199 | B200: r00 | C200: 2026-06-20_00-25-00__validacao_tcc_unifal_r00 | D200: 3145505 | E200: 54 | F200: sucesso | G200: 46193.096 | H200: 63 | I200: sucesso | J200: 46193.096 | K200: 1 | L200: 1 | M200: completo | O200: 46193.095 | P200: 46193.096 | Q200: =D200&"|"&B200 -> 3145505|r00
A201: 200 | B201: r00 | C201: 2026-06-20_00-25-00__validacao_tcc_unifal_r00 | D201: 2108801 | E201: 69 | F201: sucesso | G201: 46193.096 | H201: 60 | I201: sucesso | J201: 46193.096 | K201: 1 | L201: 1 | M201: completo | O201: 46193.096 | P201: 46193.096 | Q201: =D201&"|"&B201 -> 2108801|r00
A202: 201 | B202: r00 | C202: 2026-06-20_00-25-00__validacao_tcc_unifal_r00 | D202: 2109809 | E202: 65 | F202: sucesso | G202: 46193.097 | H202: 60 | I202: sucesso | J202: 46193.097 | K202: 1 | L202: 1 | M202: completo | O202: 46193.096 | P202: 46193.097 | Q202: =D202&"|"&B202 -> 2109809|r00
A203: 202 | B203: r00 | C203: 2026-06-20_00-25-00__validacao_tcc_unifal_r00 | D203: 3145901 | E203: 51 | F203: sucesso | G203: 46193.097 | H203: 64 | I203: sucesso | J203: 46193.097 | K203: 1 | L203: 1 | M203: completo | O203: 46193.096 | P203: 46193.097 | Q203: =D203&"|"&B203 -> 3145901|r00
A204: 203 | B204: r00 | C204: 2026-06-20_00-25-00__validacao_tcc_unifal_r00 | D204: 2109908 | E204: 65 | F204: sucesso | G204: 46193.097 | H204: 66 | I204: sucesso | J204: 46193.097 | K204: 1 | L204: 1 | M204: completo | O204: 46193.097 | P204: 46193.097 | Q204: =D204&"|"&B204 -> 2109908|r00
A205: 204 | B205: r00 | C205: 2026-06-20_00-25-00__validacao_tcc_unifal_r00 | D205: 3146404 | E205: 59 | F205: sucesso | G205: 46193.098 | H205: 67 | I205: sucesso | J205: 46193.098 | K205: 1 | L205: 1 | M205: completo | O205: 46193.097 | P205: 46193.098 | Q205: =D205&"|"&B205 -> 3146404|r00
A206: 205 | B206: r00 | C206: 2026-06-20_00-25-00__validacao_tcc_unifal_r00 | D206: 2110906 | E206: 42 | F206: sucesso | G206: 46193.098 | H206: 50 | I206: sucesso | J206: 46193.098 | K206: 1 | L206: 1 | M206: completo | O206: 46193.097 | P206: 46193.098 | Q206: =D206&"|"&B206 -> 2110906|r00
A207: 206 | B207: r00 | C207: 2026-06-20_00-25-00__validacao_tcc_unifal_r00 | D207: 2111805 | E207: 84 | F207: sucesso | G207: 46193.099 | H207: 83 | I207: sucesso | J207: 46193.099 | K207: 1 | L207: 1 | M207: completo | O207: 46193.098 | P207: 46193.099 | Q207: =D207&"|"&B207 -> 2111805|r00
A208: 207 | B208: r00 | C208: 2026-06-20_00-25-00__validacao_tcc_unifal_r00 | D208: 3149200 | E208: 58 | F208: sucesso | G208: 46193.099 | H208: 61 | I208: sucesso | J208: 46193.099 | K208: 1 | L208: 1 | M208: completo | O208: 46193.098 | P208: 46193.099 | Q208: =D208&"|"&B208 -> 3149200|r00
A209: 208 | B209: r00 | C209: 2026-06-20_00-25-00__validacao_tcc_unifal_r00 | D209: 2504074 | E209: 66 | F209: sucesso | G209: 46193.099 | H209: 76 | I209: sucesso | J209: 46193.1 | K209: 1 | L209: 1 | M209: completo | O209: 46193.099 | P209: 46193.1 | Q209: =D209&"|"&B209 -> 2504074|r00
A210: 209 | B210: r00 | C210: 2026-06-20_00-25-00__validacao_tcc_unifal_r00 | D210: 3149804 | E210: 56 | F210: sucesso | G210: 46193.099 | H210: 59 | I210: sucesso | J210: 46193.099 | K210: 1 | L210: 1 | M210: completo | O210: 46193.099 | P210: 46193.099 | Q210: =D210&"|"&B210 -> 3149804|r00
... A247: 246 | B247: r00 | C247: 2026-06-20_00-25-00__validacao_tcc_unifal_r00 | D247: 4307500 | E247: 75 | F247: sucesso | G247: 46193.108 | H247: 77 | I247: sucesso | J247: 46193.108 | K247: 1 | L247: 1 | M247: completo | O247: 46193.108 | P247: 46193.108 | Q247: =D247&"|"&B247 -> 4307500|r00
A248: 247 | B248: r00 | C248: 2026-06-20_00-25-00__validacao_tcc_unifal_r00 | D248: 2604403 | F248: falha_de_carregamento | G248: 46193.115 | H248: 54 | I248: sucesso | J248: 46193.115 | K248: 0 | L248: 1 | M248: parcial | O248: 46193.108 | P248: 46193.115 | Q248: =D248&"|"&B248 -> 2604403|r00
A249: 248 | B249: r00 | C249: 2026-06-20_00-25-00__validacao_tcc_unifal_r00 | D249: 3169059 | E249: 70 | F249: sucesso | G249: 46193.108 | H249: 73 | I249: sucesso | J249: 46193.109 | K249: 1 | L249: 1 | M249: completo | O249: 46193.108 | P249: 46193.109 | Q249: =D249&"|"&B249 -> 3169059|r00
A250: 249 | B250: r00 | C250: 2026-06-20_00-25-00__validacao_tcc_unifal_r00 | D250: 4308078 | E250: 92 | F250: sucesso | G250: 46193.108 | H250: 67 | I250: sucesso | J250: 46193.109 | K250: 1 | L250: 1 | M250: completo | O250: 46193.108 | P250: 46193.109 | Q250: =D250&"|"&B250 -> 4308078|r00
A251: 250 | B251: r00 | C251: 2026-06-20_00-25-00__validacao_tcc_unifal_r00 | D251: 3170008 | E251: 62 | F251: sucesso | G251: 46193.109 | H251: 64 | I251: sucesso | J251: 46193.109 | K251: 1 | L251: 1 | M251: completo | O251: 46193.109 | P251: 46193.109 | Q251: =D251&"|"&B251 -> 3170008|r00
A252: 251 | B252: r00 | C252: 2026-06-20_00-25-00__validacao_tcc_unifal_r00 | D252: 4308904 | E252: 63 | F252: sucesso | G252: 46193.109 | H252: 66 | I252: sucesso | J252: 46193.109 | K252: 1 | L252: 1 | M252: completo | O252: 46193.109 | P252: 46193.109 | Q252: =D252&"|"&B252 -> 4308904|r00
A253: 252 | B253: r00 | C253: 2026-06-20_00-25-00__validacao_tcc_unifal_r00 | D253: 4309050 | E253: 66 | F253: sucesso | G253: 46193.11 | H253: 68 | I253: sucesso | J253: 46193.11 | K253: 1 | L253: 1 | M253: completo | O253: 46193.109 | P253: 46193.11 | Q253: =D253&"|"&B253 -> 4309050|r00
A254: 253 | B254: r00 | C254: 2026-06-20_00-25-00__validacao_tcc_unifal_r00 | D254: 3170057 | E254: 70 | F254: sucesso | G254: 46193.11 | H254: 67 | I254: sucesso | J254: 46193.11 | K254: 1 | L254: 1 | M254: completo | O254: 46193.109 | P254: 46193.11 | Q254: =D254&"|"&B254 -> 3170057|r00
A255: 254 | B255: r00 | C255: 2026-06-20_00-25-00__validacao_tcc_unifal_r00 | D255: 4309506 | E255: 39 | F255: sucesso | G255: 46193.111 | H255: 45 | I255: sucesso | J255: 46193.111 | K255: 1 | L255: 1 | M255: completo | O255: 46193.11 | P255: 46193.111 | Q255: =D255&"|"&B255 -> 4309506|r00
A256: 255 | B256: r00 | C256: 2026-06-20_00-25-00__validacao_tcc_unifal_r00 | D256: 3170701 | E256: 92 | F256: sucesso | G256: 46193.11 | H256: 76 | I256: sucesso | J256: 46193.111 | K256: 1 | L256: 1 | M256: completo | O256: 46193.11 | P256: 46193.111 | Q256: =D256&"|"&B256 -> 3170701|r00
A257: 256 | B257: r00 | C257: 2026-06-20_00-25-00__validacao_tcc_unifal_r00 | D257: 3300951 | E257: 76 | F257: sucesso | G257: 46193.111 | H257: 75 | I257: sucesso | J257: 46193.111 | K257: 1 | L257: 1 | M257: completo | O257: 46193.111 | P257: 46193.111 | Q257: =D257&"|"&B257 -> 3300951|r00
A258: 257 | B258: r00 | C258: 2026-06-20_00-25-00__validacao_tcc_unifal_r00 | D258: 4310108 | E258: 87 | F258: sucesso | G258: 46193.111 | H258: 83 | I258: sucesso | J258: 46193.112 | K258: 1 | L258: 1 | M258: completo | O258: 46193.111 | P258: 46193.112 | Q258: =D258&"|"&B258 -> 4310108|r00
A259: 258 | B259: r00 | C259: 2026-06-20_00-25-00__validacao_tcc_unifal_r00 | D259: 3301405 | E259: 92 | F259: sucesso | G259: 46193.111 | H259: 56 | I259: sucesso | J259: 46193.112 | K259: 1 | L259: 1 | M259: completo | O259: 46193.111 | P259: 46193.112 | Q259: =D259&"|"&B259 -> 3301405|r00
A260: 259 | B260: r00 | C260: 2026-06-20_00-25-00__validacao_tcc_unifal_r00 | D260: 4310579 | E260: 54 | F260: sucesso | G260: 46193.112 | H260: 53 | I260: sucesso | J260: 46193.113 | K260: 1 | L260: 1 | M260: completo | O260: 46193.112 | P260: 46193.113 | Q260: =D260&"|"&B260 -> 4310579|r00
... A300: 299 | B300: r00 | C300: 2026-06-20_00-25-00__validacao_tcc_unifal_r00 | D300: 4210209 | E300: 61 | F300: sucesso | G300: 46193.127 | H300: 68 | I300: sucesso | J300: 46193.127 | K300: 1 | L300: 1 | M300: completo | O300: 46193.126 | P300: 46193.127 | Q300: =D300&"|"&B300 -> 4210209|r00
A301: 300 | B301: r00 | C301: 2026-06-20_00-25-00__validacao_tcc_unifal_r00 | D301: 2204352 | E301: 92 | F301: sucesso | G301: 46193.127 | I301: sucesso_sem_nota | J301: 46193.128 | K301: 1 | L301: 0 | M301: parcial | O301: 46193.127 | P301: 46193.128 | Q301: =D301&"|"&B301 -> 2204352|r00
A302: 301 | B302: r00 | C302: 2026-06-20_00-25-00__validacao_tcc_unifal_r00 | D302: 3519204 | E302: 63 | F302: sucesso | G302: 46193.127 | H302: 71 | I302: sucesso | J302: 46193.128 | K302: 1 | L302: 1 | M302: completo | O302: 46193.127 | P302: 46193.128 | Q302: =D302&"|"&B302 -> 3519204|r00
A303: 302 | B303: r00 | C303: 2026-06-20_00-25-00__validacao_tcc_unifal_r00 | D303: 4210308 | E303: 63 | F303: sucesso | G303: 46193.127 | H303: 68 | I303: sucesso | J303: 46193.128 | K303: 1 | L303: 1 | M303: completo | O303: 46193.127 | P303: 46193.128 | Q303: =D303&"|"&B303 -> 4210308|r00
A304: 303 | B304: r00 | C304: 2026-06-20_00-25-00__validacao_tcc_unifal_r00 | D304: 3519709 | E304: 59 | F304: sucesso | G304: 46193.131 | H304: 56 | I304: sucesso | J304: 46193.131 | K304: 1 | L304: 1 | M304: completo | O304: 46193.128 | P304: 46193.131 | Q304: =D304&"|"&B304 -> 3519709|r00
A305: 304 | B305: r00 | C305: 2026-06-20_00-25-00__validacao_tcc_unifal_r00 | D305: 4211801 | E305: 58 | F305: sucesso | G305: 46193.128 | H305: 61 | I305: sucesso | J305: 46193.128 | K305: 1 | L305: 1 | M305: completo | O305: 46193.128 | P305: 46193.128 | Q305: =D305&"|"&B305 -> 4211801|r00
A306: 305 | B306: r00 | C306: 2026-06-20_00-25-00__validacao_tcc_unifal_r00 | D306: 2205250 | E306: 88 | F306: sucesso | G306: 46193.128 | H306: 81 | I306: sucesso | J306: 46193.128 | K306: 1 | L306: 1 | M306: completo | O306: 46193.128 | P306: 46193.128 | Q306: =D306&"|"&B306 -> 2205250|r00
A307: 306 | B307: r00 | C307: 2026-06-20_00-25-00__validacao_tcc_unifal_r00 | D307: 2205359 | E307: 67 | F307: sucesso | G307: 46193.131 | H307: 68 | I307: sucesso | J307: 46193.131 | K307: 1 | L307: 1 | M307: completo | O307: 46193.128 | P307: 46193.131 | Q307: =D307&"|"&B307 -> 2205359|r00
A308: 307 | B308: r00 | C308: 2026-06-20_00-25-00__validacao_tcc_unifal_r00 | D308: 4212700 | E308: 61 | F308: sucesso | G308: 46193.129 | H308: 65 | I308: sucesso | J308: 46193.129 | K308: 1 | L308: 1 | M308: completo | O308: 46193.128 | P308: 46193.129 | Q308: =D308&"|"&B308 -> 4212700|r00
A309: 308 | B309: r00 | C309: 2026-06-20_00-25-00__validacao_tcc_unifal_r00 | D309: 4213302 | E309: 59 | F309: sucesso | G309: 46193.129 | H309: 62 | I309: sucesso | J309: 46193.13 | K309: 1 | L309: 1 | M309: completo | O309: 46193.129 | P309: 46193.13 | Q309: =D309&"|"&B309 -> 4213302|r00
A310: 309 | B310: r00 | C310: 2026-06-20_00-25-00__validacao_tcc_unifal_r00 | D310: 4214805 | E310: 67 | F310: sucesso | G310: 46193.13 | H310: 67 | I310: sucesso | J310: 46193.13 | K310: 1 | L310: 1 | M310: completo | O310: 46193.13 | P310: 46193.13 | Q310: =D310&"|"&B310 -> 4214805|r00
...

Sheet Logs
A1: id_log | B1: rodada | C1: sessao | D1: codigo_municipio_completo | E1: ferramenta | F1: tentativa | G1: url_enviada | H1: url_final | I1: dominio_final | J1: houve_redirecionamento | K1: titulo_pagina | L1: inicio_em | M1: fim_em | N1: duracao_segundos | O1: status_tentativa | P1: nota_extraida | Q1: nota_bruta | R1: caminho_pdf | S1: caminho_csv | T1: caminho_print | U1: caminho_json | V1: mensagem_erro | W1: traceback_resumido | X1: criado_em
A2: 1 | B2: r00 | C2: 2026-06-20_00-25-00__validacao_tcc_unifal_r00 | D2: 5203939 | E2: amaweb | F2: 1 | G2: https://buritidegoias.go.gov.br/ | H2: https://amaweb.unifesp.br/avaliador/results/https%3A%2F%2Fburitidegoias.go.gov.br%2F | I2: amaweb.unifesp.br | J2: 1 | K2: AMAWeb | Avaliador | L2: 46193.018 | M2: 46193.018 | N2: 4507 | O2: sucesso | P2: 75 | Q2: 7.5 | R2: /media/serv-bot/cebece73-ca34-45fa-ba0e-9a1a1807e5c3/TCC_Unifal/Evidencias_TCC_Unifal/relatorios_ferramentas/2026-06-20_00-25-00__validacao_tcc_unifal_r00/amaweb/buriti-de-goias-goias-5203939/buriti-de-goias_goiás_5203939_r00_amaweb_t1_20260620_002559.pdf | U2: /media/serv-bot/cebece73-ca34-45fa-ba0e-9a1a1807e5c3/TCC_Unifal/Processamento_TCC_Unifal/sessoes/2026-06-20_00-25-00__validacao_tcc_unifal_r00/json/r00_5203939_49c814da.json | X2: 46193.018
A3: 2 | B3: r00 | C3: 2026-06-20_00-25-00__validacao_tcc_unifal_r00 | D3: 1200179 | E3: amaweb | F3: 1 | G3: https://www.capixaba.ac.gov.br/ | H3: https://amaweb.unifesp.br/avaliador/results/https%3A%2F%2Fwww.capixaba.ac.gov.br%2F | I3: amaweb.unifesp.br | J3: 1 | K3: AMAWeb | Avaliador | L3: 46193.018 | M3: 46193.018 | N3: 5481 | O3: sucesso | P3: 61 | Q3: 6.1 | R3: /media/serv-bot/cebece73-ca34-45fa-ba0e-9a1a1807e5c3/TCC_Unifal/Evidencias_TCC_Unifal/relatorios_ferramentas/2026-06-20_00-25-00__validacao_tcc_unifal_r00/amaweb/capixaba-acre-1200179/capixaba_acre_1200179_r00_amaweb_t1_20260620_002609.pdf | U3: /media/serv-bot/cebece73-ca34-45fa-ba0e-9a1a1807e5c3/TCC_Unifal/Processamento_TCC_Unifal/sessoes/2026-06-20_00-25-00__validacao_tcc_unifal_r00/json/r00_1200179_9cc651b6.json | X3: 46193.018
A4: 3 | B4: r00 | C4: 2026-06-20_00-25-00__validacao_tcc_unifal_r00 | D4: 5203939 | E4: accessmonitor | F4: 1 | G4: https://buritidegoias.go.gov.br/ | H4: https://buritidegoias.go.gov.br/ | I4: buritidegoias.go.gov.br | J4: 0 | K4: Prefeitura Municipal de Buriti de Goiás | L4: 46193.018 | M4: 46193.018 | N4: 1224 | O4: sucesso | P4: 72 | Q4: 7.2 | U4: /media/serv-bot/cebece73-ca34-45fa-ba0e-9a1a1807e5c3/TCC_Unifal/Evidencias_TCC_Unifal/relatorios_ferramentas/2026-06-20_00-25-00__validacao_tcc_unifal_r00/accessmonitor/buriti-de-goias-goias-5203939/buriti-de-goias_goiás_5203939_r00_accessmonitor_t1_20260620_002611.json | X4: 46193.018
A5: 4 | B5: r00 | C5: 2026-06-20_00-25-00__validacao_tcc_unifal_r00 | D5: 1200179 | E5: accessmonitor | F5: 1 | G5: https://www.capixaba.ac.gov.br/ | H5: https://www.capixaba.ac.gov.br/ | I5: www.capixaba.ac.gov.br | J5: 0 | K5: Prefeitura de Capixaba | L5: 46193.018 | M5: 46193.019 | N5: 2064 | O5: sucesso | P5: 61 | Q5: 6.1 | U5: /media/serv-bot/cebece73-ca34-45fa-ba0e-9a1a1807e5c3/TCC_Unifal/Evidencias_TCC_Unifal/relatorios_ferramentas/2026-06-20_00-25-00__validacao_tcc_unifal_r00/accessmonitor/capixaba-acre-1200179/capixaba_acre_1200179_r00_accessmonitor_t1_20260620_002620.json | X5: 46193.019
A6: 5 | B6: r00 | C6: 2026-06-20_00-25-00__validacao_tcc_unifal_r00 | D6: 5204656 | E6: amaweb | F6: 1 | G6: https://www.campinacu.go.gov.br/ | H6: https://amaweb.unifesp.br/avaliador/results/https%3A%2F%2Fwww.campinacu.go.gov.br%2F | I6: amaweb.unifesp.br | J6: 1 | K6: AMAWeb | Avaliador | L6: 46193.018 | M6: 46193.019 | N6: 4005 | O6: sucesso | P6: 69 | Q6: 6.9 | R6: /media/serv-bot/cebece73-ca34-45fa-ba0e-9a1a1807e5c3/TCC_Unifal/Evidencias_TCC_Unifal/relatorios_ferramentas/2026-06-20_00-25-00__validacao_tcc_unifal_r00/amaweb/campinacu-goias-5204656/campinacu_goiás_5204656_r00_amaweb_t1_20260620_002707.pdf | U6: /media/serv-bot/cebece73-ca34-45fa-ba0e-9a1a1807e5c3/TCC_Unifal/Processamento_TCC_Unifal/sessoes/2026-06-20_00-25-00__validacao_tcc_unifal_r00/json/r00_5204656_1a4a6b79.json | X6: 46193.019
A7: 6 | B7: r00 | C7: 2026-06-20_00-25-00__validacao_tcc_unifal_r00 | D7: 5204656 | E7: accessmonitor | F7: 1 | G7: https://www.campinacu.go.gov.br/ | H7: https://www.campinacu.go.gov.br/ | I7: www.campinacu.go.gov.br | J7: 0 | K7: Prefeitura de Campinaçu – Um novo tempo, uma nova história. | L7: 46193.019 | M7: 46193.019 | N7: 824 | O7: sucesso | P7: 69 | Q7: 6.9 | U7: /media/serv-bot/cebece73-ca34-45fa-ba0e-9a1a1807e5c3/TCC_Unifal/Evidencias_TCC_Unifal/relatorios_ferramentas/2026-06-20_00-25-00__validacao_tcc_unifal_r00/accessmonitor/campinacu-goias-5204656/campinacu_goiás_5204656_r00_accessmonitor_t1_20260620_002719.json | X7: 46193.019
A8: 7 | B8: r00 | C8: 2026-06-20_00-25-00__validacao_tcc_unifal_r00 | D8: 5205802 | E8: amaweb | F8: 1 | G8: https://corumbadegoias.go.gov.br/ | H8: https://amaweb.unifesp.br/avaliador/results/https%3A%2F%2Fcorumbadegoias.go.gov.br%2F | I8: amaweb.unifesp.br | J8: 1 | K8: AMAWeb | Avaliador | L8: 46193.019 | M8: 46193.019 | N8: 2654 | O8: sucesso | P8: 74 | Q8: 7.4 | R8: /media/serv-bot/cebece73-ca34-45fa-ba0e-9a1a1807e5c3/TCC_Unifal/Evidencias_TCC_Unifal/relatorios_ferramentas/2026-06-20_00-25-00__validacao_tcc_unifal_r00/amaweb/corumba-de-goias-goias-5205802/corumba-de-goias_goiás_5205802_r00_amaweb_t1_20260620_002757.pdf | U8: /media/serv-bot/cebece73-ca34-45fa-ba0e-9a1a1807e5c3/TCC_Unifal/Processamento_TCC_Unifal/sessoes/2026-06-20_00-25-00__validacao_tcc_unifal_r00/json/r00_5205802_7cf4a7a6.json | X8: 46193.019
A9: 8 | B9: r00 | C9: 2026-06-20_00-25-00__validacao_tcc_unifal_r00 | D9: 5205802 | E9: accessmonitor | F9: 1 | G9: https://corumbadegoias.go.gov.br/ | H9: https://corumbadegoias.go.gov.br/ | I9: corumbadegoias.go.gov.br | J9: 0 | K9: Prefeitura de Corumbá de Goiás | L9: 46193.02 | M9: 46193.02 | N9: 629 | O9: sucesso | P9: 74 | Q9: 7.4 | U9: /media/serv-bot/cebece73-ca34-45fa-ba0e-9a1a1807e5c3/TCC_Unifal/Evidencias_TCC_Unifal/relatorios_ferramentas/2026-06-20_00-25-00__validacao_tcc_unifal_r00/accessmonitor/corumba-de-goias-goias-5205802/corumba-de-goias_goiás_5205802_r00_accessmonitor_t1_20260620_002810.json | X9: 46193.02
A10: 9 | B10: r00 | C10: 2026-06-20_00-25-00__validacao_tcc_unifal_r00 | D10: 2700102 | E10: amaweb | F10: 1 | G10: https://aguabranca.al.gov.br/ | H10: https://amaweb.unifesp.br/avaliador/results/https%3A%2F%2Faguabranca.al.gov.br%2F | I10: amaweb.unifesp.br | J10: 1 | K10: AMAWeb | Avaliador | L10: 46193.018 | M10: 46193.02 | N10: 19283 | O10: falha_de_carregamento | R10: /media/serv-bot/cebece73-ca34-45fa-ba0e-9a1a1807e5c3/TCC_Unifal/Evidencias_TCC_Unifal/relatorios_ferramentas/2026-06-20_00-25-00__validacao_tcc_unifal_r00/amaweb/agua-branca-alagoas-2700102/agua-branca_alagoas_2700102_r00_amaweb_t1_20260620_002827.pdf | U10: /media/serv-bot/cebece73-ca34-45fa-ba0e-9a1a1807e5c3/TCC_Unifal/Processamento_TCC_Unifal/sessoes/2026-06-20_00-25-00__validacao_tcc_unifal_r00/json/r00_2700102_05d402b4.json | V10: falha_de_carregamento | X10: 46193.02
A11: 10 | B11: r00 | C11: 2026-06-20_00-25-00__validacao_tcc_unifal_r00 | D11: 2700102 | E11: amaweb | F11: 2 | G11: https://aguabranca.al.gov.br/ | H11: https://amaweb.unifesp.br/avaliador/results/https%3A%2F%2Faguabranca.al.gov.br%2F | I11: amaweb.unifesp.br | J11: 1 | K11: AMAWeb | Avaliador | L11: 46193.02 | M11: 46193.02 | N11: 824 | O11: sucesso | P11: 57 | Q11: 5.7 | R11: /media/serv-bot/cebece73-ca34-45fa-ba0e-9a1a1807e5c3/TCC_Unifal/Evidencias_TCC_Unifal/relatorios_ferramentas/2026-06-20_00-25-00__validacao_tcc_unifal_r00/amaweb/agua-branca-alagoas-2700102/agua-branca_alagoas_2700102_r00_amaweb_t2_20260620_002850.pdf | U11: /media/serv-bot/cebece73-ca34-45fa-ba0e-9a1a1807e5c3/TCC_Unifal/Processamento_TCC_Unifal/sessoes/2026-06-20_00-25-00__validacao_tcc_unifal_r00/json/r00_2700102_05d402b4.json | X11: 46193.02
A12: 11 | B12: r00 | C12: 2026-06-20_00-25-00__validacao_tcc_unifal_r00 | D12: 5206602 | E12: amaweb | F12: 1 | G12: https://cumari.go.gov.br/ | H12: https://amaweb.unifesp.br/avaliador/results/https%3A%2F%2Fcumari.go.gov.br%2F | I12: amaweb.unifesp.br | J12: 1 | K12: AMAWeb | Avaliador | L12: 46193.02 | M12: 46193.02 | N12: 3368 | O12: sucesso | P12: 70 | Q12: 7 | R12: /media/serv-bot/cebece73-ca34-45fa-ba0e-9a1a1807e5c3/TCC_Unifal/Evidencias_TCC_Unifal/relatorios_ferramentas/2026-06-20_00-25-00__validacao_tcc_unifal_r00/amaweb/cumari-goias-5206602/cumari_goiás_5206602_r00_amaweb_t1_20260620_002854.pdf | U12: /media/serv-bot/cebece73-ca34-45fa-ba0e-9a1a1807e5c3/TCC_Unifal/Processamento_TCC_Unifal/sessoes/2026-06-20_00-25-00__validacao_tcc_unifal_r00/json/r00_5206602_cc2e0a52.json | X12: 46193.02
A13: 12 | B13: r00 | C13: 2026-06-20_00-25-00__validacao_tcc_unifal_r00 | D13: 2700102 | E13: accessmonitor | F13: 1 | G13: https://aguabranca.al.gov.br/ | H13: https://aguabranca.al.gov.br/ | I13: aguabranca.al.gov.br | J13: 0 | K13: Prefeitura - Água Branca | L13: 46193.02 | M13: 46193.02 | N13: 1147 | O13: sucesso_sem_nota | U13: /media/serv-bot/cebece73-ca34-45fa-ba0e-9a1a1807e5c3/TCC_Unifal/Evidencias_TCC_Unifal/relatorios_ferramentas/2026-06-20_00-25-00__validacao_tcc_unifal_r00/accessmonitor/agua-branca-alagoas-2700102/agua-branca_alagoas_2700102_r00_accessmonitor_t1_20260620_002903.json | X13: 46193.02
A14: 13 | B14: r00 | C14: 2026-06-20_00-25-00__validacao_tcc_unifal_r00 | D14: 5206602 | E14: accessmonitor | F14: 1 | G14: https://cumari.go.gov.br/ | H14: https://cumari.go.gov.br/ | I14: cumari.go.gov.br | J14: 0 | K14: Prefeitura Municipal de Cumari | L14: 46193.02 | M14: 46193.02 | N14: 1224 | O14: sucesso | P14: 69 | Q14: 6.9 | U14: /media/serv-bot/cebece73-ca34-45fa-ba0e-9a1a1807e5c3/TCC_Unifal/Evidencias_TCC_Unifal/relatorios_ferramentas/2026-06-20_00-25-00__validacao_tcc_unifal_r00/accessmonitor/cumari-goias-5206602/cumari_goiás_5206602_r00_accessmonitor_t1_20260620_002906.json | X14: 46193.02
A15: 14 | B15: r00 | C15: 2026-06-20_00-25-00__validacao_tcc_unifal_r00 | D15: 2700102 | E15: accessmonitor | F15: 2 | G15: https://aguabranca.al.gov.br/ | H15: https://aguabranca.al.gov.br/ | I15: aguabranca.al.gov.br | J15: 0 | K15: Prefeitura - Água Branca | L15: 46193.02 | M15: 46193.021 | N15: 1108 | O15: sucesso_sem_nota | U15: /media/serv-bot/cebece73-ca34-45fa-ba0e-9a1a1807e5c3/TCC_Unifal/Evidencias_TCC_Unifal/relatorios_ferramentas/2026-06-20_00-25-00__validacao_tcc_unifal_r00/accessmonitor/agua-branca-alagoas-2700102/agua-branca_alagoas_2700102_r00_accessmonitor_t2_20260620_002925.json | X15: 46193.021
A16: 15 | B16: r00 | C16: 2026-06-20_00-25-00__validacao_tcc_unifal_r00 | D16: 1200393 | E16: amaweb | F16: 1 | G16: https://www.portowalter.ac.gov.br/ | H16: https://amaweb.unifesp.br/avaliador/results/https%3A%2F%2Fwww.portowalter.ac.gov.br%2F | I16: amaweb.unifesp.br | J16: 1 | K16: AMAWeb | Avaliador | L16: 46193.019 | M16: 46193.021 | N16: 18700 | O16: falha_de_carregamento | R16: /media/serv-bot/cebece73-ca34-45fa-ba0e-9a1a1807e5c3/TCC_Unifal/Evidencias_TCC_Unifal/relatorios_ferramentas/2026-06-20_00-25-00__validacao_tcc_unifal_r00/amaweb/porto-walter-acre-1200393/porto-walter_acre_1200393_r00_amaweb_t1_20260620_002951.pdf | U16: /media/serv-bot/cebece73-ca34-45fa-ba0e-9a1a1807e5c3/TCC_Unifal/Processamento_TCC_Unifal/sessoes/2026-06-20_00-25-00__validacao_tcc_unifal_r00/json/r00_1200393_363ff175.json | V16: falha_de_carregamento | X16: 46193.021
A17: 16 | B17: r00 | C17: 2026-06-20_00-25-00__validacao_tcc_unifal_r00 | D17: 5207253 | E17: amaweb | F17: 1 | G17: https://doverlandia.go.gov.br/ | H17: https://amaweb.unifesp.br/avaliador/results/https%3A%2F%2Fdoverlandia.go.gov.br%2F | I17: amaweb.unifesp.br | J17: 1 | K17: AMAWeb | Avaliador | L17: 46193.02 | M17: 46193.021 | N17: 3030 | O17: sucesso | P17: 76 | Q17: 7.6 | R17: /media/serv-bot/cebece73-ca34-45fa-ba0e-9a1a1807e5c3/TCC_Unifal/Evidencias_TCC_Unifal/relatorios_ferramentas/2026-06-20_00-25-00__validacao_tcc_unifal_r00/amaweb/doverlandia-goias-5207253/doverlandia_goiás_5207253_r00_amaweb_t1_20260620_002952.pdf | U17: /media/serv-bot/cebece73-ca34-45fa-ba0e-9a1a1807e5c3/TCC_Unifal/Processamento_TCC_Unifal/sessoes/2026-06-20_00-25-00__validacao_tcc_unifal_r00/json/r00_5207253_0b053355.json | X17: 46193.021
A18: 17 | B18: r00 | C18: 2026-06-20_00-25-00__validacao_tcc_unifal_r00 | D18: 2700102 | E18: accessmonitor | F18: 3 | G18: https://aguabranca.al.gov.br/ | H18: https://aguabranca.al.gov.br/ | I18: aguabranca.al.gov.br | J18: 0 | K18: Prefeitura - Água Branca | L18: 46193.021 | M18: 46193.021 | N18: 1122 | O18: sucesso_sem_nota | U18: /media/serv-bot/cebece73-ca34-45fa-ba0e-9a1a1807e5c3/TCC_Unifal/Evidencias_TCC_Unifal/relatorios_ferramentas/2026-06-20_00-25-00__validacao_tcc_unifal_r00/accessmonitor/agua-branca-alagoas-2700102/agua-branca_alagoas_2700102_r00_accessmonitor_t3_20260620_002955.json | X18: 46193.021
A19: 18 | B19: r00 | C19: 2026-06-20_00-25-00__validacao_tcc_unifal_r00 | D19: 5207253 | E19: accessmonitor | F19: 1 | G19: https://doverlandia.go.gov.br/ | H19: https://doverlandia.go.gov.br/ | I19: doverlandia.go.gov.br | J19: 0 | K19: Prefeitura de Doverlândia | L19: 46193.021 | M19: 46193.021 | N19: 586 | O19: sucesso | P19: 78 | Q19: 7.8 | U19: /media/serv-bot/cebece73-ca34-45fa-ba0e-9a1a1807e5c3/TCC_Unifal/Evidencias_TCC_Unifal/relatorios_ferramentas/2026-06-20_00-25-00__validacao_tcc_unifal_r00/accessmonitor/doverlandia-goias-5207253/doverlandia_goiás_5207253_r00_accessmonitor_t1_20260620_003005.json | X19: 46193.021
A20: 19 | B20: r00 | C20: 2026-06-20_00-25-00__validacao_tcc_unifal_r00 | D20: 2702207 | E20: amaweb | F20: 1 | G20: https://coqueiroseco.al.gov.br/ | H20: https://amaweb.unifesp.br/avaliador/results/https%3A%2F%2Fcoqueiroseco.al.gov.br%2F | I20: amaweb.unifesp.br | J20: 1 | K20: AMAWeb | Avaliador | L20: 46193.021 | M20: 46193.021 | N20: 1870 | O20: sucesso | P20: 54 | Q20: 5.4 | R20: /media/serv-bot/cebece73-ca34-45fa-ba0e-9a1a1807e5c3/TCC_Unifal/Evidencias_TCC_Unifal/relatorios_ferramentas/2026-06-20_00-25-00__validacao_tcc_unifal_r00/amaweb/coqueiro-seco-alagoas-2702207/coqueiro-seco_alagoas_2702207_r00_amaweb_t1_20260620_003029.pdf | U20: /media/serv-bot/cebece73-ca34-45fa-ba0e-9a1a1807e5c3/TCC_Unifal/Processamento_TCC_Unifal/sessoes/2026-06-20_00-25-00__validacao_tcc_unifal_r00/json/r00_2702207_71b8a360.json | X20: 46193.021
A21: 20 | B21: r00 | C21: 2026-06-20_00-25-00__validacao_tcc_unifal_r00 | D21: 5208806 | E21: amaweb | F21: 1 | G21: https://goianira.go.gov.br/ | H21: https://amaweb.unifesp.br/avaliador/results/https%3A%2F%2Fgoianira.go.gov.br%2F | I21: amaweb.unifesp.br | J21: 1 | K21: AMAWeb | Avaliador | L21: 46193.021 | M21: 46193.021 | N21: 3289 | O21: sucesso | P21: 70 | Q21: 7 | R21: /media/serv-bot/cebece73-ca34-45fa-ba0e-9a1a1807e5c3/TCC_Unifal/Evidencias_TCC_Unifal/relatorios_ferramentas/2026-06-20_00-25-00__validacao_tcc_unifal_r00/amaweb/goianira-goias-5208806/goianira_goiás_5208806_r00_amaweb_t1_20260620_003049.pdf | U21: /media/serv-bot/cebece73-ca34-45fa-ba0e-9a1a1807e5c3/TCC_Unifal/Processamento_TCC_Unifal/sessoes/2026-06-20_00-25-00__validacao_tcc_unifal_r00/json/r00_5208806_d034b0c6.json | X21: 46193.021
A22: 21 | B22: r00 | C22: 2026-06-20_00-25-00__validacao_tcc_unifal_r00 | D22: 2702207 | E22: accessmonitor | F22: 1 | G22: https://coqueiroseco.al.gov.br/ | H22: https://coqueiroseco.al.gov.br/ | I22: coqueiroseco.al.gov.br | J22: 0 | K22: Prefeitura de Coqueiro Seco | L22: 46193.021 | M22: 46193.021 | N22: 958 | O22: sucesso | P22: 58 | Q22: 5.8 | U22: /media/serv-bot/cebece73-ca34-45fa-ba0e-9a1a1807e5c3/TCC_Unifal/Evidencias_TCC_Unifal/relatorios_ferramentas/2026-06-20_00-25-00__validacao_tcc_unifal_r00/accessmonitor/coqueiro-seco-alagoas-2702207/coqueiro-seco_alagoas_2702207_r00_accessmonitor_t1_20260620_003042.json | X22: 46193.021
A23: 22 | B23: r00 | C23: 2026-06-20_00-25-00__validacao_tcc_unifal_r00 | D23: 1200393 | E23: amaweb | F23: 2 | G23: https://www.portowalter.ac.gov.br/ | H23: https://amaweb.unifesp.br/avaliador/results/https%3A%2F%2Fwww.portowalter.ac.gov.br%2F | I23: amaweb.unifesp.br | J23: 1 | K23: AMAWeb | Avaliador | L23: 46193.021 | M23: 46193.021 | N23: 4274 | O23: sucesso | P23: 61 | Q23: 6.1 | R23: /media/serv-bot/cebece73-ca34-45fa-ba0e-9a1a1807e5c3/TCC_Unifal/Evidencias_TCC_Unifal/relatorios_ferramentas/2026-06-20_00-25-00__validacao_tcc_unifal_r00/amaweb/porto-walter-acre-1200393/porto-walter_acre_1200393_r00_amaweb_t2_20260620_003054.pdf | U23: /media/serv-bot/cebece73-ca34-45fa-ba0e-9a1a1807e5c3/TCC_Unifal/Processamento_TCC_Unifal/sessoes/2026-06-20_00-25-00__validacao_tcc_unifal_r00/json/r00_1200393_363ff175.json | X23: 46193.021
A24: 23 | B24: r00 | C24: 2026-06-20_00-25-00__validacao_tcc_unifal_r00 | D24: 5208806 | E24: accessmonitor | F24: 1 | G24: https://goianira.go.gov.br/ | H24: https://goianira.go.gov.br/ | I24: goianira.go.gov.br | J24: 0 | K24: Prefeitura de Goianira - Acesse informações sobre receitas, gastos em serviços públicos, investimentos. | L24: 46193.022 | M24: 46193.022 | N24: 999 | O24: sucesso | P24: 72 | Q24: 7.2 | U24: /media/serv-bot/cebece73-ca34-45fa-ba0e-9a1a1807e5c3/TCC_Unifal/Evidencias_TCC_Unifal/relatorios_ferramentas/2026-06-20_00-25-00__validacao_tcc_unifal_r00/accessmonitor/goianira-goias-5208806/goianira_goiás_5208806_r00_accessmonitor_t1_20260620_003100.json | X24: 46193.022
A25: 24 | B25: r00 | C25: 2026-06-20_00-25-00__validacao_tcc_unifal_r00 | D25: 1200393 | E25: accessmonitor | F25: 1 | G25: https://www.portowalter.ac.gov.br/ | H25: https://www.portowalter.ac.gov.br/ | I25: www.portowalter.ac.gov.br | J25: 0 | K25: Prefeitura de Porto Walter | L25: 46193.022 | M25: 46193.022 | N25: 2704 | O25: sucesso | P25: 61 | Q25: 6.1 | U25: /media/serv-bot/cebece73-ca34-45fa-ba0e-9a1a1807e5c3/TCC_Unifal/Evidencias_TCC_Unifal/relatorios_ferramentas/2026-06-20_00-25-00__validacao_tcc_unifal_r00/accessmonitor/porto-walter-acre-1200393/porto-walter_acre_1200393_r00_accessmonitor_t1_20260620_003106.json | X25: 46193.022
A26: 25 | B26: r00 | C26: 2026-06-20_00-25-00__validacao_tcc_unifal_r00 | D26: 2702900 | E26: amaweb | F26: 1 | G26: https://giraudoponciano.al.gov.br/ | H26: https://amaweb.unifesp.br/avaliador/results/https%3A%2F%2Fgiraudoponciano.al.gov.br%2F | I26: amaweb.unifesp.br | J26: 1 | K26: AMAWeb | Avaliador | L26: 46193.021 | M26: 46193.022 | N26: 3913 | O26: sucesso | P26: 64 | Q26: 6.4 | R26: /media/serv-bot/cebece73-ca34-45fa-ba0e-9a1a1807e5c3/TCC_Unifal/Evidencias_TCC_Unifal/relatorios_ferramentas/2026-06-20_00-25-00__validacao_tcc_unifal_r00/amaweb/girau-do-ponciano-alagoas-2702900/girau-do-ponciano_alagoas_2702900_r00_amaweb_t1_20260620_003134.pdf | U26: /media/serv-bot/cebece73-ca34-45fa-ba0e-9a1a1807e5c3/TCC_Unifal/Processamento_TCC_Unifal/sessoes/2026-06-20_00-25-00__validacao_tcc_unifal_r00/json/r00_2702900_392785d8.json | X26: 46193.022
A27: 26 | B27: r00 | C27: 2026-06-20_00-25-00__validacao_tcc_unifal_r00 | D27: 5209457 | E27: amaweb | F27: 1 | G27: https://guarinos.go.gov.br/ | H27: https://amaweb.unifesp.br/avaliador/results/https%3A%2F%2Fguarinos.go.gov.br%2F | I27: amaweb.unifesp.br | J27: 1 | K27: AMAWeb | Avaliador | L27: 46193.022 | M27: 46193.022 | N27: 3245 | O27: sucesso | P27: 73 | Q27: 7.3 | R27: /media/serv-bot/cebece73-ca34-45fa-ba0e-9a1a1807e5c3/TCC_Unifal/Evidencias_TCC_Unifal/relatorios_ferramentas/2026-06-20_00-25-00__validacao_tcc_unifal_r00/amaweb/guarinos-goias-5209457/guarinos_goiás_5209457_r00_amaweb_t1_20260620_003147.pdf | U27: /media/serv-bot/cebece73-ca34-45fa-ba0e-9a1a1807e5c3/TCC_Unifal/Processamento_TCC_Unifal/sessoes/2026-06-20_00-25-00__validacao_tcc_unifal_r00/json/r00_5209457_5902cc66.json | X27: 46193.022
A28: 27 | B28: r00 | C28: 2026-06-20_00-25-00__validacao_tcc_unifal_r00 | D28: 1600303 | E28: amaweb | F28: 1 | G28: https://www.macapa.ap.gov.br/ | H28: https://amaweb.unifesp.br/avaliador/results/https%3A%2F%2Fwww.macapa.ap.gov.br%2F | I28: amaweb.unifesp.br | J28: 1 | K28: AMAWeb | Avaliador | L28: 46193.022 | M28: 46193.022 | N28: 1263 | O28: sucesso | P28: 92 | Q28: 9.2 | R28: /media/serv-bot/cebece73-ca34-45fa-ba0e-9a1a1807e5c3/TCC_Unifal/Evidencias_TCC_Unifal/relatorios_ferramentas/2026-06-20_00-25-00__validacao_tcc_unifal_r00/amaweb/macapa-amapa-1600303/macapa_amapá_1600303_r00_amaweb_t1_20260620_003149.pdf | U28: /media/serv-bot/cebece73-ca34-45fa-ba0e-9a1a1807e5c3/TCC_Unifal/Processamento_TCC_Unifal/sessoes/2026-06-20_00-25-00__validacao_tcc_unifal_r00/json/r00_1600303_f7a8ad76.json | X28: 46193.022
A29: 28 | B29: r00 | C29: 2026-06-20_00-25-00__validacao_tcc_unifal_r00 | D29: 2702900 | E29: accessmonitor | F29: 1 | G29: https://giraudoponciano.al.gov.br/ | H29: https://giraudoponciano.al.gov.br/ | I29: giraudoponciano.al.gov.br | J29: 0 | K29: Home - Girau do Ponciano | L29: 46193.022 | M29: 46193.022 | N29: 845 | O29: sucesso | P29: 68 | Q29: 6.8 | U29: /media/serv-bot/cebece73-ca34-45fa-ba0e-9a1a1807e5c3/TCC_Unifal/Evidencias_TCC_Unifal/relatorios_ferramentas/2026-06-20_00-25-00__validacao_tcc_unifal_r00/accessmonitor/girau-do-ponciano-alagoas-2702900/girau-do-ponciano_alagoas_2702900_r00_accessmonitor_t1_20260620_003147.json | X29: 46193.022
A30: 29 | B30: r00 | C30: 2026-06-20_00-25-00__validacao_tcc_unifal_r00 | D30: 5209457 | E30: accessmonitor | F30: 1 | G30: https://guarinos.go.gov.br/ | H30: https://guarinos.go.gov.br/ | I30: guarinos.go.gov.br | J30: 0 | K30: Prefeitura Municipal de Guarinos | L30: 46193.022 | M30: 46193.022 | N30: 655 | O30: sucesso | P30: 72 | Q30: 7.2 | U30: /media/serv-bot/cebece73-ca34-45fa-ba0e-9a1a1807e5c3/TCC_Unifal/Evidencias_TCC_Unifal/relatorios_ferramentas/2026-06-20_00-25-00__validacao_tcc_unifal_r00/accessmonitor/guarinos-goias-5209457/guarinos_goiás_5209457_r00_accessmonitor_t1_20260620_003200.json | X30: 46193.022
A31: 30 | B31: r00 | C31: 2026-06-20_00-25-00__validacao_tcc_unifal_r00 | D31: 1600303 | E31: accessmonitor | F31: 1 | G31: https://www.macapa.ap.gov.br/ | H31: https://macapa.ap.gov.br/ | I31: macapa.ap.gov.br | J31: 1 | K31: Home - Prefeitura Municipal de Macapá | L31: 46193.022 | M31: 46193.023 | N31: 2664 | O31: sucesso_sem_nota | U31: /media/serv-bot/cebece73-ca34-45fa-ba0e-9a1a1807e5c3/TCC_Unifal/Evidencias_TCC_Unifal/relatorios_ferramentas/2026-06-20_00-25-00__validacao_tcc_unifal_r00/accessmonitor/macapa-amapa-1600303/macapa_amapá_1600303_r00_accessmonitor_t1_20260620_003200.json | X31: 46193.023
A32: 31 | B32: r00 | C32: 2026-06-20_00-25-00__validacao_tcc_unifal_r00 | D32: 2703304 | E32: amaweb | F32: 1 | G32: https://inhapi.al.gov.br/ | H32: https://amaweb.unifesp.br/avaliador/results/https%3A%2F%2Finhapi.al.gov.br%2F | I32: amaweb.unifesp.br | J32: 1 | K32: AMAWeb | Avaliador | L32: 46193.022 | M32: 46193.023 | N32: 3044 | O32: sucesso | P32: 64 | Q32: 6.4 | R32: /media/serv-bot/cebece73-ca34-45fa-ba0e-9a1a1807e5c3/TCC_Unifal/Evidencias_TCC_Unifal/relatorios_ferramentas/2026-06-20_00-25-00__validacao_tcc_unifal_r00/amaweb/inhapi-alagoas-2703304/inhapi_alagoas_2703304_r00_amaweb_t1_20260620_003229.pdf | U32: /media/serv-bot/cebece73-ca34-45fa-ba0e-9a1a1807e5c3/TCC_Unifal/Processamento_TCC_Unifal/sessoes/2026-06-20_00-25-00__validacao_tcc_unifal_r00/json/r00_2703304_fd39433c.json | X32: 46193.023
A33: 32 | B33: r00 | C33: 2026-06-20_00-25-00__validacao_tcc_unifal_r00 | D33: 5210802 | E33: amaweb | F33: 1 | G33: https://itaja.go.gov.br/ | H33: https://amaweb.unifesp.br/avaliador/results/https%3A%2F%2Fitaja.go.gov.br%2F | I33: amaweb.unifesp.br | J33: 1 | K33: AMAWeb | Avaliador | L33: 46193.022 | M33: 46193.023 | N33: 3694 | O33: sucesso | P33: 63 | Q33: 6.3 | R33: /media/serv-bot/cebece73-ca34-45fa-ba0e-9a1a1807e5c3/TCC_Unifal/Evidencias_TCC_Unifal/relatorios_ferramentas/2026-06-20_00-25-00__validacao_tcc_unifal_r00/amaweb/itaja-goias-5210802/itaja_goiás_5210802_r00_amaweb_t1_20260620_003248.pdf | U33: /media/serv-bot/cebece73-ca34-45fa-ba0e-9a1a1807e5c3/TCC_Unifal/Processamento_TCC_Unifal/sessoes/2026-06-20_00-25-00__validacao_tcc_unifal_r00/json/r00_5210802_8407d26c.json | X33: 46193.023
A34: 33 | B34: r00 | C34: 2026-06-20_00-25-00__validacao_tcc_unifal_r00 | D34: 1600303 | E34: accessmonitor | F34: 2 | G34: https://www.macapa.ap.gov.br/ | H34: https://macapa.ap.gov.br/ | I34: macapa.ap.gov.br | J34: 1 | K34: Home - Prefeitura Municipal de Macapá | L34: 46193.023 | M34: 46193.023 | N34: 1167 | O34: sucesso_sem_nota | U34: /media/serv-bot/cebece73-ca34-45fa-ba0e-9a1a1807e5c3/TCC_Unifal/Evidencias_TCC_Unifal/relatorios_ferramentas/2026-06-20_00-25-00__validacao_tcc_unifal_r00/accessmonitor/macapa-amapa-1600303/macapa_amapá_1600303_r00_accessmonitor_t2_20260620_003237.json | X34: 46193.023
A35: 34 | B35: r00 | C35: 2026-06-20_00-25-00__validacao_tcc_unifal_r00 | D35: 2703304 | E35: accessmonitor | F35: 1 | G35: https://inhapi.al.gov.br/ | H35: https://inhapi.al.gov.br/ | I35: inhapi.al.gov.br | J35: 0 | K35: BEM - VINDO - Prefeitura de Inhapi | L35: 46193.023 | M35: 46193.023 | N35: 1011 | O35: sucesso | P35: 60 | Q35: 6 | U35: /media/serv-bot/cebece73-ca34-45fa-ba0e-9a1a1807e5c3/TCC_Unifal/Evidencias_TCC_Unifal/relatorios_ferramentas/2026-06-20_00-25-00__validacao_tcc_unifal_r00/accessmonitor/inhapi-alagoas-2703304/inhapi_alagoas_2703304_r00_accessmonitor_t1_20260620_003241.json | X35: 46193.023
A36: 35 | B36: r00 | C36: 2026-06-20_00-25-00__validacao_tcc_unifal_r00 | D36: 5210802 | E36: accessmonitor | F36: 1 | G36: https://itaja.go.gov.br/ | H36: https://itaja.go.gov.br/ | I36: itaja.go.gov.br | J36: 0 | K36: Prefeitura Municipal de Itajá | L36: 46193.023 | M36: 46193.023 | N36: 733 | O36: sucesso | P36: 62 | Q36: 6.2 | U36: /media/serv-bot/cebece73-ca34-45fa-ba0e-9a1a1807e5c3/TCC_Unifal/Evidencias_TCC_Unifal/relatorios_ferramentas/2026-06-20_00-25-00__validacao_tcc_unifal_r00/accessmonitor/itaja-goias-5210802/itaja_goiás_5210802_r00_accessmonitor_t1_20260620_003300.json | X36: 46193.023
A37: 36 | B37: r00 | C37: 2026-06-20_00-25-00__validacao_tcc_unifal_r00 | D37: 1600303 | E37: accessmonitor | F37: 3 | G37: https://www.macapa.ap.gov.br/ | H37: https://macapa.ap.gov.br/ | I37: macapa.ap.gov.br | J37: 1 | K37: Home - Prefeitura Municipal de Macapá | L37: 46193.023 | M37: 46193.023 | N37: 1198 | O37: sucesso_sem_nota | U37: /media/serv-bot/cebece73-ca34-45fa-ba0e-9a1a1807e5c3/TCC_Unifal/Evidencias_TCC_Unifal/relatorios_ferramentas/2026-06-20_00-25-00__validacao_tcc_unifal_r00/accessmonitor/macapa-amapa-1600303/macapa_amapá_1600303_r00_accessmonitor_t3_20260620_003309.json | X37: 46193.023
A38: 37 | B38: r00 | C38: 2026-06-20_00-25-00__validacao_tcc_unifal_r00 | D38: 2706422 | E38: amaweb | F38: 1 | G38: https://pariconha.al.gov.br/ | H38: https://amaweb.unifesp.br/avaliador/results/https%3A%2F%2Fpariconha.al.gov.br%2F | I38: amaweb.unifesp.br | J38: 1 | K38: AMAWeb | Avaliador | L38: 46193.023 | M38: 46193.023 | N38: 2616 | O38: sucesso | P38: 58 | Q38: 5.8 | R38: /media/serv-bot/cebece73-ca34-45fa-ba0e-9a1a1807e5c3/TCC_Unifal/Evidencias_TCC_Unifal/relatorios_ferramentas/2026-06-20_00-25-00__validacao_tcc_unifal_r00/amaweb/pariconha-alagoas-2706422/pariconha_alagoas_2706422_r00_amaweb_t1_20260620_003320.pdf | U38: /media/serv-bot/cebece73-ca34-45fa-ba0e-9a1a1807e5c3/TCC_Unifal/Processamento_TCC_Unifal/sessoes/2026-06-20_00-25-00__validacao_tcc_unifal_r00/json/r00_2706422_b775a631.json | X38: 46193.023
A39: 38 | B39: r00 | C39: 2026-06-20_00-25-00__validacao_tcc_unifal_r00 | D39: 5211800 | E39: amaweb | F39: 1 | G39: https://jaragua.go.gov.br/ | H39: https://amaweb.unifesp.br/avaliador/results/https%3A%2F%2Fjaragua.go.gov.br%2F | I39: amaweb.unifesp.br | J39: 1 | K39: AMAWeb | Avaliador | L39: 46193.023 | M39: 46193.023 | N39: 2789 | O39: sucesso | P39: 70 | Q39: 7 | R39: /media/serv-bot/cebece73-ca34-45fa-ba0e-9a1a1807e5c3/TCC_Unifal/Evidencias_TCC_Unifal/relatorios_ferramentas/2026-06-20_00-25-00__validacao_tcc_unifal_r00/amaweb/jaragua-goias-5211800/jaragua_goiás_5211800_r00_amaweb_t1_20260620_003339.pdf | U39: /media/serv-bot/cebece73-ca34-45fa-ba0e-9a1a1807e5c3/TCC_Unifal/Processamento_TCC_Unifal/sessoes/2026-06-20_00-25-00__validacao_tcc_unifal_r00/json/r00_5211800_dd51de7e.json | X39: 46193.023
A40: 39 | B40: r00 | C40: 2026-06-20_00-25-00__validacao_tcc_unifal_r00 | D40: 2706422 | E40: accessmonitor | F40: 1 | G40: https://pariconha.al.gov.br/ | H40: https://pariconha.al.gov.br/ | I40: pariconha.al.gov.br | J40: 0 | K40: Prefeitura de Pariconha – Alagoas – O novo jeito de governar | L40: 46193.023 | M40: 46193.023 | N40: 987 | O40: sucesso | P40: 57 | Q40: 5.7 | U40: /media/serv-bot/cebece73-ca34-45fa-ba0e-9a1a1807e5c3/TCC_Unifal/Evidencias_TCC_Unifal/relatorios_ferramentas/2026-06-20_00-25-00__validacao_tcc_unifal_r00/accessmonitor/pariconha-alagoas-2706422/pariconha_alagoas_2706422_r00_accessmonitor_t1_20260620_003332.json | X40: 46193.023
A41: 40 | B41: r00 | C41: 2026-06-20_00-25-00__validacao_tcc_unifal_r00 | D41: 1600550 | E41: amaweb | F41: 1 | G41: https://www.pracuuba.ap.gov.br/ | H41: https://amaweb.unifesp.br/avaliador/results/https%3A%2F%2Fwww.pracuuba.ap.gov.br%2F | I41: amaweb.unifesp.br | J41: 1 | K41: AMAWeb | Avaliador | L41: 46193.023 | M41: 46193.024 | N41: 3372 | O41: sucesso | P41: 65 | Q41: 6.5 | R41: /media/serv-bot/cebece73-ca34-45fa-ba0e-9a1a1807e5c3/TCC_Unifal/Evidencias_TCC_Unifal/relatorios_ferramentas/2026-06-20_00-25-00__validacao_tcc_unifal_r00/amaweb/pracuuba-amapa-1600550/pracuuba_amapá_1600550_r00_amaweb_t1_20260620_003400.pdf | U41: /media/serv-bot/cebece73-ca34-45fa-ba0e-9a1a1807e5c3/TCC_Unifal/Processamento_TCC_Unifal/sessoes/2026-06-20_00-25-00__validacao_tcc_unifal_r00/json/r00_1600550_17ed217b.json | X41: 46193.024
A42: 41 | B42: r00 | C42: 2026-06-20_00-25-00__validacao_tcc_unifal_r00 | D42: 5211800 | E42: accessmonitor | F42: 1 | G42: https://jaragua.go.gov.br/ | H42: https://jaragua.go.gov.br/ | I42: jaragua.go.gov.br | J42: 0 | K42: Prefeitura Municipal de Jaraguá | L42: 46193.024 | M42: 46193.024 | N42: 1004 | O42: sucesso | P42: 71 | Q42: 7.1 | U42: /media/serv-bot/cebece73-ca34-45fa-ba0e-9a1a1807e5c3/TCC_Unifal/Evidencias_TCC_Unifal/relatorios_ferramentas/2026-06-20_00-25-00__validacao_tcc_unifal_r00/accessmonitor/jaragua-goias-5211800/jaragua_goiás_5211800_r00_accessmonitor_t1_20260620_003352.json | X42: 46193.024
A43: 42 | B43: r00 | C43: 2026-06-20_00-25-00__validacao_tcc_unifal_r00 | D43: 1600550 | E43: accessmonitor | F43: 1 | G43: https://www.pracuuba.ap.gov.br/ | H43: https://www.pracuuba.ap.gov.br/ | I43: www.pracuuba.ap.gov.br | J43: 0 | K43: Prefeitura de Pracuuba | L43: 46193.024 | M43: 46193.024 | N43: 1196 | O43: sucesso | P43: 68 | Q43: 6.8 | U43: /media/serv-bot/cebece73-ca34-45fa-ba0e-9a1a1807e5c3/TCC_Unifal/Evidencias_TCC_Unifal/relatorios_ferramentas/2026-06-20_00-25-00__validacao_tcc_unifal_r00/accessmonitor/pracuuba-amapa-1600550/pracuuba_amapá_1600550_r00_accessmonitor_t1_20260620_003411.json | X43: 46193.024
A44: 43 | B44: r00 | C44: 2026-06-20_00-25-00__validacao_tcc_unifal_r00 | D44: 2708808 | E44: amaweb | F44: 1 | G44: https://saosebastiao.al.gov.br/ | H44: https://amaweb.unifesp.br/avaliador/results/https%3A%2F%2Fsaosebastiao.al.gov.br%2F | I44: amaweb.unifesp.br | J44: 1 | K44: AMAWeb | Avaliador | L44: 46193.023 | M44: 46193.024 | N44: 4641 | O44: sucesso | P44: 52 | Q44: 5.2 | R44: /media/serv-bot/cebece73-ca34-45fa-ba0e-9a1a1807e5c3/TCC_Unifal/Evidencias_TCC_Unifal/relatorios_ferramentas/2026-06-20_00-25-00__validacao_tcc_unifal_r00/amaweb/sao-sebastiao-alagoas-2708808/sao-sebastiao_alagoas_2708808_r00_amaweb_t1_20260620_003432.pdf | U44: /media/serv-bot/cebece73-ca34-45fa-ba0e-9a1a1807e5c3/TCC_Unifal/Processamento_TCC_Unifal/sessoes/2026-06-20_00-25-00__validacao_tcc_unifal_r00/json/r00_2708808_bc6be2d4.json | X44: 46193.024
A45: 44 | B45: r00 | C45: 2026-06-20_00-25-00__validacao_tcc_unifal_r00 | D45: 5213806 | E45: amaweb | F45: 1 | G45: https://morrinhos.go.gov.br/ | H45: https://amaweb.unifesp.br/avaliador/results/https%3A%2F%2Fmorrinhos.go.gov.br%2F | I45: amaweb.unifesp.br | J45: 1 | K45: AMAWeb | Avaliador | L45: 46193.024 | M45: 46193.024 | N45: 3196 | O45: sucesso | P45: 76 | Q45: 7.6 | R45: /media/serv-bot/cebece73-ca34-45fa-ba0e-9a1a1807e5c3/TCC_Unifal/Evidencias_TCC_Unifal/relatorios_ferramentas/2026-06-20_00-25-00__validacao_tcc_unifal_r00/amaweb/morrinhos-goias-5213806/morrinhos_goiás_5213806_r00_amaweb_t1_20260620_003438.pdf | U45: /media/serv-bot/cebece73-ca34-45fa-ba0e-9a1a1807e5c3/TCC_Unifal/Processamento_TCC_Unifal/sessoes/2026-06-20_00-25-00__validacao_tcc_unifal_r00/json/r00_5213806_93e28da9.json | X45: 46193.024
A46: 45 | B46: r00 | C46: 2026-06-20_00-25-00__validacao_tcc_unifal_r00 | D46: 2708808 | E46: accessmonitor | F46: 1 | G46: https://saosebastiao.al.gov.br/ | H46: https://saosebastiao.al.gov.br/ | I46: saosebastiao.al.gov.br | J46: 0 | K46: Prefeitura de São Sebastião - Alagoas | L46: 46193.024 | M46: 46193.024 | N46: 1110 | O46: sucesso | P46: 52 | Q46: 5.2 | U46: /media/serv-bot/cebece73-ca34-45fa-ba0e-9a1a1807e5c3/TCC_Unifal/Evidencias_TCC_Unifal/relatorios_ferramentas/2026-06-20_00-25-00__validacao_tcc_unifal_r00/accessmonitor/sao-sebastiao-alagoas-2708808/sao-sebastiao_alagoas_2708808_r00_accessmonitor_t1_20260620_003444.json | X46: 46193.024
A47: 46 | B47: r00 | C47: 2026-06-20_00-25-00__validacao_tcc_unifal_r00 | D47: 1600709 | E47: amaweb | F47: 1 | G47: https://www.tartarugalzinho.ap.gov.br/ | H47: https://amaweb.unifesp.br/avaliador/results/https%3A%2F%2Fwww.tartarugalzinho.ap.gov.br%2F | I47: amaweb.unifesp.br | J47: 1 | K47: AMAWeb | Avaliador | L47: 46193.024 | M47: 46193.024 | N47: 2976 | O47: sucesso | P47: 59 | Q47: 5.9 | R47: /media/serv-bot/cebece73-ca34-45fa-ba0e-9a1a1807e5c3/TCC_Unifal/Evidencias_TCC_Unifal/relatorios_ferramentas/2026-06-20_00-25-00__validacao_tcc_unifal_r00/amaweb/tartarugalzinho-amapa-1600709/tartarugalzinho_amapá_1600709_r00_amaweb_t1_20260620_003456.pdf | U47: /media/serv-bot/cebece73-ca34-45fa-ba0e-9a1a1807e5c3/TCC_Unifal/Processamento_TCC_Unifal/sessoes/2026-06-20_00-25-00__validacao_tcc_unifal_r00/json/r00_1600709_0217d7e9.json | X47: 46193.024
A48: 47 | B48: r00 | C48: 2026-06-20_00-25-00__validacao_tcc_unifal_r00 | D48: 5213806 | E48: accessmonitor | F48: 1 | G48: https://morrinhos.go.gov.br/ | H48: https://morrinhos.go.gov.br/ | I48: morrinhos.go.gov.br | J48: 0 | K48: Prefeitura Municipal de Morrinhos | L48: 46193.024 | M48: 46193.024 | N48: 630 | O48: sucesso | P48: 73 | Q48: 7.3 | U48: /media/serv-bot/cebece73-ca34-45fa-ba0e-9a1a1807e5c3/TCC_Unifal/Evidencias_TCC_Unifal/relatorios_ferramentas/2026-06-20_00-25-00__validacao_tcc_unifal_r00/accessmonitor/morrinhos-goias-5213806/morrinhos_goiás_5213806_r00_accessmonitor_t1_20260620_003451.json | X48: 46193.024
A49: 48 | B49: r00 | C49: 2026-06-20_00-25-00__validacao_tcc_unifal_r00 | D49: 1600709 | E49: accessmonitor | F49: 1 | G49: https://www.tartarugalzinho.ap.gov.br/ | H49: https://www.tartarugalzinho.ap.gov.br/ | I49: www.tartarugalzinho.ap.gov.br | J49: 0 | K49: Prefeitura de Tartarugalzinho | L49: 46193.024 | M49: 46193.025 | N49: 1075 | O49: sucesso | P49: 66 | Q49: 6.6 | U49: /media/serv-bot/cebece73-ca34-45fa-ba0e-9a1a1807e5c3/TCC_Unifal/Evidencias_TCC_Unifal/relatorios_ferramentas/2026-06-20_00-25-00__validacao_tcc_unifal_r00/accessmonitor/tartarugalzinho-amapa-1600709/tartarugalzinho_amapá_1600709_r00_accessmonitor_t1_20260620_003509.json | X49: 46193.025
A50: 49 | B50: r00 | C50: 2026-06-20_00-25-00__validacao_tcc_unifal_r00 | D50: 2900603 | E50: amaweb | F50: 1 | G50: https://www.aiquara.ba.gov.br/ | H50: https://amaweb.unifesp.br/avaliador/results/https%3A%2F%2Fwww.aiquara.ba.gov.br%2F | I50: amaweb.unifesp.br | J50: 1 | K50: AMAWeb | Avaliador | L50: 46193.024 | M50: 46193.025 | N50: 2195 | O50: sucesso | P50: 60 | Q50: 6 | R50: /media/serv-bot/cebece73-ca34-45fa-ba0e-9a1a1807e5c3/TCC_Unifal/Evidencias_TCC_Unifal/relatorios_ferramentas/2026-06-20_00-25-00__validacao_tcc_unifal_r00/amaweb/aiquara-bahia-2900603/aiquara_bahia_2900603_r00_amaweb_t1_20260620_003521.pdf | U50: /media/serv-bot/cebece73-ca34-45fa-ba0e-9a1a1807e5c3/TCC_Unifal/Processamento_TCC_Unifal/sessoes/2026-06-20_00-25-00__validacao_tcc_unifal_r00/json/r00_2900603_6c94c9a5.json | X50: 46193.025
A51: 50 | B51: r00 | C51: 2026-06-20_00-25-00__validacao_tcc_unifal_r00 | D51: 5213905 | E51: amaweb | F51: 1 | G51: http://mossamedes.go.gov.br/ | H51: https://amaweb.unifesp.br/avaliador/results/http%3A%2F%2Fmossamedes.go.gov.br%2F | I51: amaweb.unifesp.br | J51: 1 | K51: AMAWeb | Avaliador | L51: 46193.024 | M51: 46193.025 | N51: 2687 | O51: sucesso | P51: 76 | Q51: 7.6 | R51: /media/serv-bot/cebece73-ca34-45fa-ba0e-9a1a1807e5c3/TCC_Unifal/Evidencias_TCC_Unifal/relatorios_ferramentas/2026-06-20_00-25-00__validacao_tcc_unifal_r00/amaweb/mossamedes-goias-5213905/mossamedes_goiás_5213905_r00_amaweb_t1_20260620_003529.pdf | U51: /media/serv-bot/cebece73-ca34-45fa-ba0e-9a1a1807e5c3/TCC_Unifal/Processamento_TCC_Unifal/sessoes/2026-06-20_00-25-00__validacao_tcc_unifal_r00/json/r00_5213905_0aa63ad9.json | X51: 46193.025
A52: 51 | B52: r00 | C52: 2026-06-20_00-25-00__validacao_tcc_unifal_r00 | D52: 1300508 | E52: amaweb | F52: 1 | G52: https://www.barreirinha.am.gov.br/ | H52: https://amaweb.unifesp.br/avaliador/results/https%3A%2F%2Fwww.barreirinha.am.gov.br%2F | I52: amaweb.unifesp.br | J52: 1 | K52: AMAWeb | Avaliador | L52: 46193.025 | M52: 46193.025 | N52: 1186 | O52: sucesso | P52: 92 | Q52: 9.2 | R52: /media/serv-bot/cebece73-ca34-45fa-ba0e-9a1a1807e5c3/TCC_Unifal/Evidencias_TCC_Unifal/relatorios_ferramentas/2026-06-20_00-25-00__validacao_tcc_unifal_r00/amaweb/barreirinha-amazonas-1300508/barreirinha_amazonas_1300508_r00_amaweb_t1_20260620_003536.pdf | U52: /media/serv-bot/cebece73-ca34-45fa-ba0e-9a1a1807e5c3/TCC_Unifal/Processamento_TCC_Unifal/sessoes/2026-06-20_00-25-00__validacao_tcc_unifal_r00/json/r00_1300508_7221c5bb.json | X52: 46193.025
A53: 52 | B53: r00 | C53: 2026-06-20_00-25-00__validacao_tcc_unifal_r00 | D53: 2900603 | E53: accessmonitor | F53: 1 | G53: https://www.aiquara.ba.gov.br/ | H53: https://www.aiquara.ba.gov.br/ | I53: www.aiquara.ba.gov.br | J53: 0 | K53: SAI - Prefeitura - Prefeitura Municipal de Aiquara | L53: 46193.025 | M53: 46193.025 | N53: 1066 | O53: sucesso | P53: 61 | Q53: 6.1 | U53: /media/serv-bot/cebece73-ca34-45fa-ba0e-9a1a1807e5c3/TCC_Unifal/Evidencias_TCC_Unifal/relatorios_ferramentas/2026-06-20_00-25-00__validacao_tcc_unifal_r00/accessmonitor/aiquara-bahia-2900603/aiquara_bahia_2900603_r00_accessmonitor_t1_20260620_003532.json | X53: 46193.025
A54: 53 | B54: r00 | C54: 2026-06-20_00-25-00__validacao_tcc_unifal_r00 | D54: 5213905 | E54: accessmonitor | F54: 1 | G54: http://mossamedes.go.gov.br/ | H54: http://www.mossamedes.go.gov.br/ | I54: www.mossamedes.go.gov.br | J54: 1 | K54: Prefeitura de Mossâmedes | L54: 46193.025 | M54: 46193.025 | N54: 686 | O54: sucesso | P54: 75 | Q54: 7.5 | U54: /media/serv-bot/cebece73-ca34-45fa-ba0e-9a1a1807e5c3/TCC_Unifal/Evidencias_TCC_Unifal/relatorios_ferramentas/2026-06-20_00-25-00__validacao_tcc_unifal_r00/accessmonitor/mossamedes-goias-5213905/mossamedes_goiás_5213905_r00_accessmonitor_t1_20260620_003542.json | X54: 46193.025
A55: 54 | B55: r00 | C55: 2026-06-20_00-25-00__validacao_tcc_unifal_r00 | D55: 1300508 | E55: accessmonitor | F55: 1 | G55: https://www.barreirinha.am.gov.br/ | H55: https://barreirinha.am.gov.br/ | I55: barreirinha.am.gov.br | J55: 1 | K55: Home - Prefeitura Municipal de Barreirinha | L55: 46193.025 | M55: 46193.025 | N55: 1152 | O55: sucesso | P55: 71 | Q55: 7.1 | U55: /media/serv-bot/cebece73-ca34-45fa-ba0e-9a1a1807e5c3/TCC_Unifal/Evidencias_TCC_Unifal/relatorios_ferramentas/2026-06-20_00-25-00__validacao_tcc_unifal_r00/accessmonitor/barreirinha-amazonas-1300508/barreirinha_amazonas_1300508_r00_accessmonitor_t1_20260620_003549.json | X55: 46193.025
A56: 55 | B56: r00 | C56: 2026-06-20_00-25-00__validacao_tcc_unifal_r00 | D56: 2901106 | E56: amaweb | F56: 1 | G56: https://ameliarodrigues.ba.gov.br/ | H56: https://amaweb.unifesp.br/avaliador/results/https%3A%2F%2Fameliarodrigues.ba.gov.br%2F | I56: amaweb.unifesp.br | J56: 1 | K56: AMAWeb | Avaliador | L56: 46193.025 | M56: 46193.025 | N56: 1807 | O56: sucesso | P56: 79 | Q56: 7.9 | R56: /media/serv-bot/cebece73-ca34-45fa-ba0e-9a1a1807e5c3/TCC_Unifal/Evidencias_TCC_Unifal/relatorios_ferramentas/2026-06-20_00-25-00__validacao_tcc_unifal_r00/amaweb/amelia-rodrigues-bahia-2901106/amelia-rodrigues_bahia_2901106_r00_amaweb_t1_20260620_003604.pdf | U56: /media/serv-bot/cebece73-ca34-45fa-ba0e-9a1a1807e5c3/TCC_Unifal/Processamento_TCC_Unifal/sessoes/2026-06-20_00-25-00__validacao_tcc_unifal_r00/json/r00_2901106_045220f9.json | X56: 46193.025
A57: 56 | B57: r00 | C57: 2026-06-20_00-25-00__validacao_tcc_unifal_r00 | D57: 1300706 | E57: amaweb | F57: 1 | G57: https://www.bocadoacre.am.gov.br/ | H57: https://amaweb.unifesp.br/avaliador/results/https%3A%2F%2Fwww.bocadoacre.am.gov.br%2F | I57: amaweb.unifesp.br | J57: 1 | K57: AMAWeb | Avaliador | L57: 46193.025 | M57: 46193.025 | N57: 1361 | O57: sucesso | P57: 92 | Q57: 9.2 | R57: /media/serv-bot/cebece73-ca34-45fa-ba0e-9a1a1807e5c3/TCC_Unifal/Evidencias_TCC_Unifal/relatorios_ferramentas/2026-06-20_00-25-00__validacao_tcc_unifal_r00/amaweb/boca-do-acre-amazonas-1300706/boca-do-acre_amazonas_1300706_r00_amaweb_t1_20260620_003618.pdf | U57: /media/serv-bot/cebece73-ca34-45fa-ba0e-9a1a1807e5c3/TCC_Unifal/Processamento_TCC_Unifal/sessoes/2026-06-20_00-25-00__validacao_tcc_unifal_r00/json/r00_1300706_48113828.json | X57: 46193.025
A58: 57 | B58: r00 | C58: 2026-06-20_00-25-00__validacao_tcc_unifal_r00 | D58: 2901106 | E58: accessmonitor | F58: 1 | G58: https://ameliarodrigues.ba.gov.br/ | H58: https://ameliarodrigues.ba.gov.br/ | I58: ameliarodrigues.ba.gov.br | J58: 0 | K58: Prefeitura de Amélia Rodrigues - Início | L58: 46193.025 | M58: 46193.025 | N58: 581 | O58: sucesso | P58: 82 | Q58: 8.2 | U58: /media/serv-bot/cebece73-ca34-45fa-ba0e-9a1a1807e5c3/TCC_Unifal/Evidencias_TCC_Unifal/relatorios_ferramentas/2026-06-20_00-25-00__validacao_tcc_unifal_r00/accessmonitor/amelia-rodrigues-bahia-2901106/amelia-rodrigues_bahia_2901106_r00_accessmonitor_t1_20260620_003616.json | X58: 46193.025
A59: 58 | B59: r00 | C59: 2026-06-20_00-25-00__validacao_tcc_unifal_r00 | D59: 5214838 | E59: amaweb | F59: 1 | G59: https://novacrixas.go.gov.br/ | H59: https://amaweb.unifesp.br/avaliador/results/https%3A%2F%2Fnovacrixas.go.gov.br%2F | I59: amaweb.unifesp.br | J59: 1 | K59: AMAWeb | Avaliador | L59: 46193.025 | M59: 46193.025 | N59: 4066 | O59: sucesso | P59: 69 | Q59: 6.9 | R59: /media/serv-bot/cebece73-ca34-45fa-ba0e-9a1a1807e5c3/TCC_Unifal/Evidencias_TCC_Unifal/relatorios_ferramentas/2026-06-20_00-25-00__validacao_tcc_unifal_r00/amaweb/nova-crixas-goias-5214838/nova-crixas_goiás_5214838_r00_amaweb_t1_20260620_003633.pdf | U59: /media/serv-bot/cebece73-ca34-45fa-ba0e-9a1a1807e5c3/TCC_Unifal/Processamento_TCC_Unifal/sessoes/2026-06-20_00-25-00__validacao_tcc_unifal_r00/json/r00_5214838_66ff17f7.json | X59: 46193.025
A60: 59 | B60: r00 | C60: 2026-06-20_00-25-00__validacao_tcc_unifal_r00 | D60: 1300706 | E60: accessmonitor | F60: 1 | G60: https://www.bocadoacre.am.gov.br/ | H60: https://bocadoacre.am.gov.br/ | I60: bocadoacre.am.gov.br | J60: 1 | K60: Home - Prefeitura Municipal de Boca do Acre | L60: 46193.025 | M60: 46193.025 | N60: 940 | O60: sucesso | P60: 97 | Q60: 9.7 | U60: /media/serv-bot/cebece73-ca34-45fa-ba0e-9a1a1807e5c3/TCC_Unifal/Evidencias_TCC_Unifal/relatorios_ferramentas/2026-06-20_00-25-00__validacao_tcc_unifal_r00/accessmonitor/boca-do-acre-amazonas-1300706/boca-do-acre_amazonas_1300706_r00_accessmonitor_t1_20260620_003630.json | X60: 46193.025
A61: 60 | B61: r00 | C61: 2026-06-20_00-25-00__validacao_tcc_unifal_r00 | D61: 2902500 | E61: amaweb | F61: 1 | G61: https://baianopolis.ba.gov.br/ | H61: https://amaweb.unifesp.br/avaliador/results/https%3A%2F%2Fbaianopolis.ba.gov.br%2F | I61: amaweb.unifesp.br | J61: 1 | K61: AMAWeb | Avaliador | L61: 46193.025 | M61: 46193.026 | N61: 2191 | O61: sucesso | P61: 55 | Q61: 5.5 | R61: /media/serv-bot/cebece73-ca34-45fa-ba0e-9a1a1807e5c3/TCC_Unifal/Evidencias_TCC_Unifal/relatorios_ferramentas/2026-06-20_00-25-00__validacao_tcc_unifal_r00/amaweb/baianopolis-bahia-2902500/baianopolis_bahia_2902500_r00_amaweb_t1_20260620_003648.pdf | U61: /media/serv-bot/cebece73-ca34-45fa-ba0e-9a1a1807e5c3/TCC_Unifal/Processamento_TCC_Unifal/sessoes/2026-06-20_00-25-00__validacao_tcc_unifal_r00/json/r00_2902500_d521296b.json | X61: 46193.026
A62: 61 | B62: r00 | C62: 2026-06-20_00-25-00__validacao_tcc_unifal_r00 | D62: 5214838 | E62: accessmonitor | F62: 1 | G62: https://novacrixas.go.gov.br/ | H62: https://novacrixas.go.gov.br/ | I62: novacrixas.go.gov.br | J62: 0 | K62: Prefeitura Municipal de Nova Crixás | L62: 46193.026 | M62: 46193.026 | N62: 1258 | O62: sucesso | P62: 68 | Q62: 6.8 | U62: /media/serv-bot/cebece73-ca34-45fa-ba0e-9a1a1807e5c3/TCC_Unifal/Evidencias_TCC_Unifal/relatorios_ferramentas/2026-06-20_00-25-00__validacao_tcc_unifal_r00/accessmonitor/nova-crixas-goias-5214838/nova-crixas_goiás_5214838_r00_accessmonitor_t1_20260620_003645.json | X62: 46193.026
A63: 62 | B63: r00 | C63: 2026-06-20_00-25-00__validacao_tcc_unifal_r00 | D63: 1300839 | E63: amaweb | F63: 1 | G63: https://www.caapiranga.am.gov.br/ | H63: https://amaweb.unifesp.br/avaliador/results/https%3A%2F%2Fwww.caapiranga.am.gov.br%2F | I63: amaweb.unifesp.br | J63: 1 | K63: AMAWeb | Avaliador | L63: 46193.025 | M63: 46193.026 | N63: 1933 | O63: sucesso | P63: 76 | Q63: 7.6 | R63: /media/serv-bot/cebece73-ca34-45fa-ba0e-9a1a1807e5c3/TCC_Unifal/Evidencias_TCC_Unifal/relatorios_ferramentas/2026-06-20_00-25-00__validacao_tcc_unifal_r00/amaweb/caapiranga-amazonas-1300839/caapiranga_amazonas_1300839_r00_amaweb_t1_20260620_003703.pdf | U63: /media/serv-bot/cebece73-ca34-45fa-ba0e-9a1a1807e5c3/TCC_Unifal/Processamento_TCC_Unifal/sessoes/2026-06-20_00-25-00__validacao_tcc_unifal_r00/json/r00_1300839_d92abbe8.json | X63: 46193.026
A64: 63 | B64: r00 | C64: 2026-06-20_00-25-00__validacao_tcc_unifal_r00 | D64: 2902500 | E64: accessmonitor | F64: 1 | G64: https://baianopolis.ba.gov.br/ | H64: https://baianopolis.ba.gov.br/ | I64: baianopolis.ba.gov.br | J64: 0 | K64: Prefeitura Municipal de Baianópolis – BA | L64: 46193.026 | M64: 46193.026 | N64: 499 | O64: sucesso | P64: 63 | Q64: 6.3 | U64: /media/serv-bot/cebece73-ca34-45fa-ba0e-9a1a1807e5c3/TCC_Unifal/Evidencias_TCC_Unifal/relatorios_ferramentas/2026-06-20_00-25-00__validacao_tcc_unifal_r00/accessmonitor/baianopolis-bahia-2902500/baianopolis_bahia_2902500_r00_accessmonitor_t1_20260620_003659.json | X64: 46193.026
A65: 64 | B65: r00 | C65: 2026-06-20_00-25-00__validacao_tcc_unifal_r00 | D65: 1300839 | E65: accessmonitor | F65: 1 | G65: https://www.caapiranga.am.gov.br/ | H65: https://caapiranga.am.gov.br/ | I65: caapiranga.am.gov.br | J65: 1 | K65: Prefeitura Municipal de Caapiranga | L65: 46193.026 | M65: 46193.026 | N65: 627 | O65: sucesso | P65: 78 | Q65: 7.8 | U65: /media/serv-bot/cebece73-ca34-45fa-ba0e-9a1a1807e5c3/TCC_Unifal/Evidencias_TCC_Unifal/relatorios_ferramentas/2026-06-20_00-25-00__validacao_tcc_unifal_r00/accessmonitor/caapiranga-amazonas-1300839/caapiranga_amazonas_1300839_r00_accessmonitor_t1_20260620_003715.json | X65: 46193.026
A66: 65 | B66: r00 | C66: 2026-06-20_00-25-00__validacao_tcc_unifal_r00 | D66: 2903201 | E66: amaweb | F66: 1 | G66: https://barreiras.ba.gov.br/ | H66: https://amaweb.unifesp.br/avaliador/results/https%3A%2F%2Fbarreiras.ba.gov.br%2F | I66: amaweb.unifesp.br | J66: 1 | K66: AMAWeb | Avaliador | L66: 46193.026 | M66: 46193.026 | N66: 2186 | O66: sucesso | P66: 63 | Q66: 6.3 | R66: /media/serv-bot/cebece73-ca34-45fa-ba0e-9a1a1807e5c3/TCC_Unifal/Evidencias_TCC_Unifal/relatorios_ferramentas/2026-06-20_00-25-00__validacao_tcc_unifal_r00/amaweb/barreiras-bahia-2903201/barreiras_bahia_2903201_r00_amaweb_t1_20260620_003730.pdf | U66: /media/serv-bot/cebece73-ca34-45fa-ba0e-9a1a1807e5c3/TCC_Unifal/Processamento_TCC_Unifal/sessoes/2026-06-20_00-25-00__validacao_tcc_unifal_r00/json/r00_2903201_8ab29daa.json | X66: 46193.026
A67: 66 | B67: r00 | C67: 2026-06-20_00-25-00__validacao_tcc_unifal_r00 | D67: 5214861 | E67: amaweb | F67: 1 | G67: https://novagloria.go.gov.br/ | H67: https://amaweb.unifesp.br/avaliador/results/https%3A%2F%2Fnovagloria.go.gov.br%2F | I67: amaweb.unifesp.br | J67: 1 | K67: AMAWeb | Avaliador | L67: 46193.026 | M67: 46193.026 | N67: 3017 | O67: sucesso | P67: 71 | Q67: 7.1 | R67: /media/serv-bot/cebece73-ca34-45fa-ba0e-9a1a1807e5c3/TCC_Unifal/Evidencias_TCC_Unifal/relatorios_ferramentas/2026-06-20_00-25-00__validacao_tcc_unifal_r00/amaweb/nova-gloria-goias-5214861/nova-gloria_goiás_5214861_r00_amaweb_t1_20260620_003732.pdf | U67: /media/serv-bot/cebece73-ca34-45fa-ba0e-9a1a1807e5c3/TCC_Unifal/Processamento_TCC_Unifal/sessoes/2026-06-20_00-25-00__validacao_tcc_unifal_r00/json/r00_5214861_1dacf8cb.json | X67: 46193.026
A68: 67 | B68: r00 | C68: 2026-06-20_00-25-00__validacao_tcc_unifal_r00 | D68: 2903201 | E68: accessmonitor | F68: 1 | G68: https://barreiras.ba.gov.br/ | H68: https://barreiras.ba.gov.br/ | I68: barreiras.ba.gov.br | J68: 0 | K68: Prefeitura de Barreiras – BA | Site Oficial | L68: 46193.026 | M68: 46193.026 | N68: 580 | O68: sucesso | P68: 66 | Q68: 6.6 | U68: /media/serv-bot/cebece73-ca34-45fa-ba0e-9a1a1807e5c3/TCC_Unifal/Evidencias_TCC_Unifal/relatorios_ferramentas/2026-06-20_00-25-00__validacao_tcc_unifal_r00/accessmonitor/barreiras-bahia-2903201/barreiras_bahia_2903201_r00_accessmonitor_t1_20260620_003742.json | X68: 46193.026
A69: 68 | B69: r00 | C69: 2026-06-20_00-25-00__validacao_tcc_unifal_r00 | D69: 5214861 | E69: accessmonitor | F69: 1 | G69: https://novagloria.go.gov.br/ | H69: https://novagloria.go.gov.br/ | I69: novagloria.go.gov.br | J69: 0 | K69: Prefeitura Municipal de Nova Glória | L69: 46193.026 | M69: 46193.026 | N69: 628 | O69: sucesso | P69: 72 | Q69: 7.2 | U69: /media/serv-bot/cebece73-ca34-45fa-ba0e-9a1a1807e5c3/TCC_Unifal/Evidencias_TCC_Unifal/relatorios_ferramentas/2026-06-20_00-25-00__validacao_tcc_unifal_r00/accessmonitor/nova-gloria-goias-5214861/nova-gloria_goiás_5214861_r00_accessmonitor_t1_20260620_003744.json | X69: 46193.026
A70: 69 | B70: r00 | C70: 2026-06-20_00-25-00__validacao_tcc_unifal_r00 | D70: 1301209 | E70: amaweb | F70: 1 | G70: https://prefeitura.coari.am.gov.br/ | H70: https://amaweb.unifesp.br/avaliador/results/https%3A%2F%2Fprefeitura.coari.am.gov.br%2F | I70: amaweb.unifesp.br | J70: 1 | K70: AMAWeb | Avaliador | L70: 46193.026 | M70: 46193.027 | N70: 5486 | O70: sucesso | P70: 63 | Q70: 6.3 | R70: /media/serv-bot/cebece73-ca34-45fa-ba0e-9a1a1807e5c3/TCC_Unifal/Evidencias_TCC_Unifal/relatorios_ferramentas/2026-06-20_00-25-00__validacao_tcc_unifal_r00/amaweb/coari-amazonas-1301209/coari_amazonas_1301209_r00_amaweb_t1_20260620_003820.pdf | U70: /media/serv-bot/cebece73-ca34-45fa-ba0e-9a1a1807e5c3/TCC_Unifal/Processamento_TCC_Unifal/sessoes/2026-06-20_00-25-00__validacao_tcc_unifal_r00/json/r00_1301209_a081044b.json | X70: 46193.027
A71: 70 | B71: r00 | C71: 2026-06-20_00-25-00__validacao_tcc_unifal_r00 | D71: 2911303 | E71: amaweb | F71: 1 | G71: https://gentiodoouro.ba.gov.br/ | H71: https://amaweb.unifesp.br/avaliador/results/https%3A%2F%2Fgentiodoouro.ba.gov.br%2F | I71: amaweb.unifesp.br | J71: 1 | K71: AMAWeb | Avaliador | L71: 46193.026 | M71: 46193.027 | N71: 3662 | O71: sucesso | P71: 78 | Q71: 7.8 | R71: /media/serv-bot/cebece73-ca34-45fa-ba0e-9a1a1807e5c3/TCC_Unifal/Evidencias_TCC_Unifal/relatorios_ferramentas/2026-06-20_00-25-00__validacao_tcc_unifal_r00/amaweb/gentio-do-ouro-bahia-2911303/gentio-do-ouro_bahia_2911303_r00_amaweb_t1_20260620_003829.pdf | U71: /media/serv-bot/cebece73-ca34-45fa-ba0e-9a1a1807e5c3/TCC_Unifal/Processamento_TCC_Unifal/sessoes/2026-06-20_00-25-00__validacao_tcc_unifal_r00/json/r00_2911303_bfe53d3e.json | X71: 46193.027
A72: 71 | B72: r00 | C72: 2026-06-20_00-25-00__validacao_tcc_unifal_r00 | D72: 5216908 | E72: amaweb | F72: 1 | G72: https://pilar.go.gov.br/ | H72: https://amaweb.unifesp.br/avaliador/results/https%3A%2F%2Fpilar.go.gov.br%2F | I72: amaweb.unifesp.br | J72: 1 | K72: AMAWeb | Avaliador | L72: 46193.026 | M72: 46193.027 | N72: 3675 | O72: sucesso | P72: 74 | Q72: 7.4 | R72: /media/serv-bot/cebece73-ca34-45fa-ba0e-9a1a1807e5c3/TCC_Unifal/Evidencias_TCC_Unifal/relatorios_ferramentas/2026-06-20_00-25-00__validacao_tcc_unifal_r00/amaweb/pilar-de-goias-goias-5216908/pilar-de-goias_goiás_5216908_r00_amaweb_t1_20260620_003831.pdf | U72: /media/serv-bot/cebece73-ca34-45fa-ba0e-9a1a1807e5c3/TCC_Unifal/Processamento_TCC_Unifal/sessoes/2026-06-20_00-25-00__validacao_tcc_unifal_r00/json/r00_5216908_fa8ed367.json | X72: 46193.027
A73: 72 | B73: r00 | C73: 2026-06-20_00-25-00__validacao_tcc_unifal_r00 | D73: 1301209 | E73: accessmonitor | F73: 1 | G73: https://prefeitura.coari.am.gov.br/ | H73: https://prefeitura.coari.am.gov.br/ | I73: prefeitura.coari.am.gov.br | J73: 0 | K73: Prefeitura Municipal de Coari | L73: 46193.027 | M73: 46193.027 | N73: 1643 | O73: sucesso | P73: 66 | Q73: 6.6 | U73: /media/serv-bot/cebece73-ca34-45fa-ba0e-9a1a1807e5c3/TCC_Unifal/Evidencias_TCC_Unifal/relatorios_ferramentas/2026-06-20_00-25-00__validacao_tcc_unifal_r00/accessmonitor/coari-amazonas-1301209/coari_amazonas_1301209_r00_accessmonitor_t1_20260620_003833.json | X73: 46193.027
A74: 73 | B74: r00 | C74: 2026-06-20_00-25-00__validacao_tcc_unifal_r00 | D74: 5216908 | E74: accessmonitor | F74: 1 | G74: https://pilar.go.gov.br/ | H74: https://pilar.go.gov.br/ | I74: pilar.go.gov.br | J74: 0 | K74: Prefeitura de Pilar de Goiás | L74: 46193.027 | M74: 46193.027 | N74: 617 | O74: sucesso | P74: 72 | Q74: 7.2 | U74: /media/serv-bot/cebece73-ca34-45fa-ba0e-9a1a1807e5c3/TCC_Unifal/Evidencias_TCC_Unifal/relatorios_ferramentas/2026-06-20_00-25-00__validacao_tcc_unifal_r00/accessmonitor/pilar-de-goias-goias-5216908/pilar-de-goias_goiás_5216908_r00_accessmonitor_t1_20260620_003844.json | X74: 46193.027
A75: 74 | B75: r00 | C75: 2026-06-20_00-25-00__validacao_tcc_unifal_r00 | D75: 2911303 | E75: accessmonitor | F75: 1 | G75: https://gentiodoouro.ba.gov.br/ | H75: https://www.gentiodoouro.ba.gov.br/ | I75: www.gentiodoouro.ba.gov.br | J75: 1 | K75: Prefeitura Municipal de Gentio do Ouro - Bahia | L75: 46193.027 | M75: 46193.027 | N75: 1291 | O75: sucesso | P75: 79 | Q75: 7.9 | U75: /media/serv-bot/cebece73-ca34-45fa-ba0e-9a1a1807e5c3/TCC_Unifal/Evidencias_TCC_Unifal/relatorios_ferramentas/2026-06-20_00-25-00__validacao_tcc_unifal_r00/accessmonitor/gentio-do-ouro-bahia-2911303/gentio-do-ouro_bahia_2911303_r00_accessmonitor_t1_20260620_003841.json | X75: 46193.027
A76: 75 | B76: r00 | C76: 2026-06-20_00-25-00__validacao_tcc_unifal_r00 | D76: 1303403 | E76: amaweb | F76: 1 | G76: https://www.parintins.am.gov.br/ | H76: https://amaweb.unifesp.br/avaliador/results/https%3A%2F%2Fwww.parintins.am.gov.br%2F | I76: amaweb.unifesp.br | J76: 1 | K76: AMAWeb | Avaliador | L76: 46193.027 | M76: 46193.027 | N76: 1854 | O76: sucesso | P76: 92 | Q76: 9.2 | R76: /media/serv-bot/cebece73-ca34-45fa-ba0e-9a1a1807e5c3/TCC_Unifal/Evidencias_TCC_Unifal/relatorios_ferramentas/2026-06-20_00-25-00__validacao_tcc_unifal_r00/amaweb/parintins-amazonas-1303403/parintins_amazonas_1303403_r00_amaweb_t1_20260620_003913.pdf | U76: /media/serv-bot/cebece73-ca34-45fa-ba0e-9a1a1807e5c3/TCC_Unifal/Processamento_TCC_Unifal/sessoes/2026-06-20_00-25-00__validacao_tcc_unifal_r00/json/r00_1303403_46f00585.json | X76: 46193.027
A77: 76 | B77: r00 | C77: 2026-06-20_00-25-00__validacao_tcc_unifal_r00 | D77: 2911402 | E77: amaweb | F77: 1 | G77: https://gloria.ba.gov.br/ | H77: https://amaweb.unifesp.br/avaliador/results/https%3A%2F%2Fgloria.ba.gov.br%2F | I77: amaweb.unifesp.br | J77: 1 | K77: AMAWeb | Avaliador | L77: 46193.027 | M77: 46193.027 | N77: 2295 | O77: sucesso | P77: 80 | Q77: 8 | R77: /media/serv-bot/cebece73-ca34-45fa-ba0e-9a1a1807e5c3/TCC_Unifal/Evidencias_TCC_Unifal/relatorios_ferramentas/2026-06-20_00-25-00__validacao_tcc_unifal_r00/amaweb/gloria-bahia-2911402/gloria_bahia_2911402_r00_amaweb_t1_20260620_003923.pdf | U77: /media/serv-bot/cebece73-ca34-45fa-ba0e-9a1a1807e5c3/TCC_Unifal/Processamento_TCC_Unifal/sessoes/2026-06-20_00-25-00__validacao_tcc_unifal_r00/json/r00_2911402_7ba5622c.json | X77: 46193.027
A78: 77 | B78: r00 | C78: 2026-06-20_00-25-00__validacao_tcc_unifal_r00 | D78: 5220454 | E78: amaweb | F78: 1 | G78: https://senadorcanedo.go.gov.br/ | H78: https://amaweb.unifesp.br/avaliador/results/https%3A%2F%2Fsenadorcanedo.go.gov.br%2F | I78: amaweb.unifesp.br | J78: 1 | K78: AMAWeb | Avaliador | L78: 46193.027 | M78: 46193.027 | N78: 3681 | O78: sucesso | P78: 67 | Q78: 6.7 | R78: /media/serv-bot/cebece73-ca34-45fa-ba0e-9a1a1807e5c3/TCC_Unifal/Evidencias_TCC_Unifal/relatorios_ferramentas/2026-06-20_00-25-00__validacao_tcc_unifal_r00/amaweb/senador-canedo-goias-5220454/senador-canedo_goiás_5220454_r00_amaweb_t1_20260620_003931.pdf | U78: /media/serv-bot/cebece73-ca34-45fa-ba0e-9a1a1807e5c3/TCC_Unifal/Processamento_TCC_Unifal/sessoes/2026-06-20_00-25-00__validacao_tcc_unifal_r00/json/r00_5220454_5861af0f.json | X78: 46193.027
A79: 78 | B79: r00 | C79: 2026-06-20_00-25-00__validacao_tcc_unifal_r00 | D79: 1303403 | E79: accessmonitor | F79: 1 | G79: https://www.parintins.am.gov.br/ | H79: https://www.parintins.am.gov.br/ | I79: www.parintins.am.gov.br | J79: 0 | K79: Prefeitura de Parintins | Portal institucional com serviços, transparência e notícias | L79: 46193.027 | M79: 46193.027 | N79: 1085 | O79: sucesso_sem_nota | U79: /media/serv-bot/cebece73-ca34-45fa-ba0e-9a1a1807e5c3/TCC_Unifal/Evidencias_TCC_Unifal/relatorios_ferramentas/2026-06-20_00-25-00__validacao_tcc_unifal_r00/accessmonitor/parintins-amazonas-1303403/parintins_amazonas_1303403_r00_accessmonitor_t1_20260620_003925.json | X79: 46193.027
A80: 79 | B80: r00 | C80: 2026-06-20_00-25-00__validacao_tcc_unifal_r00 | D80: 2911402 | E80: accessmonitor | F80: 1 | G80: https://gloria.ba.gov.br/ | H80: https://gloria.ba.gov.br/ | I80: gloria.ba.gov.br | J80: 0 | K80: Prefeitura Municipal de Glória - Bahia | L80: 46193.027 | M80: 46193.028 | N80: 1081 | O80: sucesso | P80: 83 | Q80: 8.3 | U80: /media/serv-bot/cebece73-ca34-45fa-ba0e-9a1a1807e5c3/TCC_Unifal/Evidencias_TCC_Unifal/relatorios_ferramentas/2026-06-20_00-25-00__validacao_tcc_unifal_r00/accessmonitor/gloria-bahia-2911402/gloria_bahia_2911402_r00_accessmonitor_t1_20260620_003936.json | X80: 46193.028
A81: 80 | B81: r00 | C81: 2026-06-20_00-25-00__validacao_tcc_unifal_r00 | D81: 5220454 | E81: accessmonitor | F81: 1 | G81: https://senadorcanedo.go.gov.br/ | H81: https://senadorcanedo.go.gov.br/ | I81: senadorcanedo.go.gov.br | J81: 0 | K81: Prefeitura Municipal de Senador Canedo – Site da Prefeitura de Senador Canedo | L81: 46193.028 | M81: 46193.028 | N81: 1156 | O81: sucesso | P81: 69 | Q81: 6.9 | U81: /media/serv-bot/cebece73-ca34-45fa-ba0e-9a1a1807e5c3/TCC_Unifal/Evidencias_TCC_Unifal/relatorios_ferramentas/2026-06-20_00-25-00__validacao_tcc_unifal_r00/accessmonitor/senador-canedo-goias-5220454/senador-canedo_goiás_5220454_r00_accessmonitor_t1_20260620_003944.json | X81: 46193.028
A82: 81 | B82: r00 | C82: 2026-06-20_00-25-00__validacao_tcc_unifal_r00 | D82: 1303403 | E82: accessmonitor | F82: 2 | G82: https://www.parintins.am.gov.br/ | H82: https://www.parintins.am.gov.br/ | I82: www.parintins.am.gov.br | J82: 0 | K82: Prefeitura de Parintins | Portal institucional com serviços, transparência e notícias | L82: 46193.028 | M82: 46193.028 | N82: 1194 | O82: sucesso_sem_nota | U82: /media/serv-bot/cebece73-ca34-45fa-ba0e-9a1a1807e5c3/TCC_Unifal/Evidencias_TCC_Unifal/relatorios_ferramentas/2026-06-20_00-25-00__validacao_tcc_unifal_r00/accessmonitor/parintins-amazonas-1303403/parintins_amazonas_1303403_r00_accessmonitor_t2_20260620_003949.json | X82: 46193.028
A83: 82 | B83: r00 | C83: 2026-06-20_00-25-00__validacao_tcc_unifal_r00 | D83: 2912103 | E83: amaweb | F83: 1 | G83: https://ibicarai.ba.gov.br/ | H83: https://amaweb.unifesp.br/avaliador/results/https%3A%2F%2Fibicarai.ba.gov.br%2F | I83: amaweb.unifesp.br | J83: 1 | K83: AMAWeb | Avaliador | L83: 46193.028 | M83: 46193.028 | N83: 2475 | O83: sucesso | P83: 53 | Q83: 5.3 | R83: /media/serv-bot/cebece73-ca34-45fa-ba0e-9a1a1807e5c3/TCC_Unifal/Evidencias_TCC_Unifal/relatorios_ferramentas/2026-06-20_00-25-00__validacao_tcc_unifal_r00/amaweb/ibicarai-bahia-2912103/ibicarai_bahia_2912103_r00_amaweb_t1_20260620_004015.pdf | U83: /media/serv-bot/cebece73-ca34-45fa-ba0e-9a1a1807e5c3/TCC_Unifal/Processamento_TCC_Unifal/sessoes/2026-06-20_00-25-00__validacao_tcc_unifal_r00/json/r00_2912103_eaa342b8.json | X83: 46193.028
A84: 83 | B84: r00 | C84: 2026-06-20_00-25-00__validacao_tcc_unifal_r00 | D84: 1303403 | E84: accessmonitor | F84: 3 | G84: https://www.parintins.am.gov.br/ | H84: https://www.parintins.am.gov.br/ | I84: www.parintins.am.gov.br | J84: 0 | K84: Prefeitura de Parintins | Portal institucional com serviços, transparência e notícias | L84: 46193.028 | M84: 46193.028 | N84: 1193 | O84: sucesso_sem_nota | U84: /media/serv-bot/cebece73-ca34-45fa-ba0e-9a1a1807e5c3/TCC_Unifal/Evidencias_TCC_Unifal/relatorios_ferramentas/2026-06-20_00-25-00__validacao_tcc_unifal_r00/accessmonitor/parintins-amazonas-1303403/parintins_amazonas_1303403_r00_accessmonitor_t3_20260620_004017.json | X84: 46193.028
A85: 84 | B85: r00 | C85: 2026-06-20_00-25-00__validacao_tcc_unifal_r00 | D85: 2912103 | E85: accessmonitor | F85: 1 | G85: https://ibicarai.ba.gov.br/ | H85: https://www.ibicarai.ba.gov.br/ | I85: www.ibicarai.ba.gov.br | J85: 1 | K85: SAI - Prefeitura - Prefeitura Municipal de Ibicaraí | L85: 46193.028 | M85: 46193.028 | N85: 1145 | O85: sucesso | P85: 54 | Q85: 5.4 | U85: /media/serv-bot/cebece73-ca34-45fa-ba0e-9a1a1807e5c3/TCC_Unifal/Evidencias_TCC_Unifal/relatorios_ferramentas/2026-06-20_00-25-00__validacao_tcc_unifal_r00/accessmonitor/ibicarai-bahia-2912103/ibicarai_bahia_2912103_r00_accessmonitor_t1_20260620_004028.json | X85: 46193.028
A86: 85 | B86: r00 | C86: 2026-06-20_00-25-00__validacao_tcc_unifal_r00 | D86: 2913705 | E86: amaweb | F86: 1 | G86: https://inhambupe.ba.gov.br/ | H86: https://amaweb.unifesp.br/avaliador/results/https%3A%2F%2Finhambupe.ba.gov.br%2F | I86: amaweb.unifesp.br | J86: 1 | K86: AMAWeb | Avaliador | L86: 46193.028 | M86: 46193.029 | N86: 3655 | O86: sucesso | P86: 50 | Q86: 5 | R86: /media/serv-bot/cebece73-ca34-45fa-ba0e-9a1a1807e5c3/TCC_Unifal/Evidencias_TCC_Unifal/relatorios_ferramentas/2026-06-20_00-25-00__validacao_tcc_unifal_r00/amaweb/inhambupe-bahia-2913705/inhambupe_bahia_2913705_r00_amaweb_t1_20260620_004120.pdf | U86: /media/serv-bot/cebece73-ca34-45fa-ba0e-9a1a1807e5c3/TCC_Unifal/Processamento_TCC_Unifal/sessoes/2026-06-20_00-25-00__validacao_tcc_unifal_r00/json/r00_2913705_feece31e.json | X86: 46193.029
A87: 86 | B87: r00 | C87: 2026-06-20_00-25-00__validacao_tcc_unifal_r00 | D87: 2913705 | E87: accessmonitor | F87: 1 | G87: https://inhambupe.ba.gov.br/ | H87: https://inhambupe.ba.gov.br/ | I87: inhambupe.ba.gov.br | J87: 0 | K87: Prefeitura Municipal Inhambupe | L87: 46193.029 | M87: 46193.029 | N87: 1697 | O87: sucesso | P87: 57 | Q87: 5.7 | U87: /media/serv-bot/cebece73-ca34-45fa-ba0e-9a1a1807e5c3/TCC_Unifal/Evidencias_TCC_Unifal/relatorios_ferramentas/2026-06-20_00-25-00__validacao_tcc_unifal_r00/accessmonitor/inhambupe-bahia-2913705/inhambupe_bahia_2913705_r00_accessmonitor_t1_20260620_004131.json | X87: 46193.029
A88: 87 | B88: r00 | C88: 2026-06-20_00-25-00__validacao_tcc_unifal_r00 | D88: 5100102 | E88: amaweb | F88: 1 | G88: https://www.acorizal.mt.gov.br/ | H88: https://amaweb.unifesp.br/avaliador/results/https%3A%2F%2Fwww.acorizal.mt.gov.br%2F | I88: amaweb.unifesp.br | J88: 1 | K88: AMAWeb | Avaliador | L88: 46193.028 | M88: 46193.03 | N88: 18796 | O88: falha_de_carregamento | R88: /media/serv-bot/cebece73-ca34-45fa-ba0e-9a1a1807e5c3/TCC_Unifal/Evidencias_TCC_Unifal/relatorios_ferramentas/2026-06-20_00-25-00__validacao_tcc_unifal_r00/amaweb/acorizal-mato-grosso-5100102/acorizal_mato grosso_5100102_r00_amaweb_t1_20260620_004307.pdf | U88: /media/serv-bot/cebece73-ca34-45fa-ba0e-9a1a1807e5c3/TCC_Unifal/Processamento_TCC_Unifal/sessoes/2026-06-20_00-25-00__validacao_tcc_unifal_r00/json/r00_5100102_d0f6659d.json | V88: falha_de_carregamento | X88: 46193.03
A89: 88 | B89: r00 | C89: 2026-06-20_00-25-00__validacao_tcc_unifal_r00 | D89: 1500107 | E89: amaweb | F89: 1 | G89: https://abaetetuba.pa.gov.br/ | H89: https://amaweb.unifesp.br/avaliador/results/https%3A%2F%2Fabaetetuba.pa.gov.br%2F | I89: amaweb.unifesp.br | J89: 1 | K89: AMAWeb | Avaliador | L89: 46193.028 | M89: 46193.03 | N89: 18886 | O89: falha_de_carregamento | R89: /media/serv-bot/cebece73-ca34-45fa-ba0e-9a1a1807e5c3/TCC_Unifal/Evidencias_TCC_Unifal/relatorios_ferramentas/2026-06-20_00-25-00__validacao_tcc_unifal_r00/amaweb/abaetetuba-para-1500107/abaetetuba_pará_1500107_r00_amaweb_t1_20260620_004342.pdf | U89: /media/serv-bot/cebece73-ca34-45fa-ba0e-9a1a1807e5c3/TCC_Unifal/Processamento_TCC_Unifal/sessoes/2026-06-20_00-25-00__validacao_tcc_unifal_r00/json/r00_1500107_85719c71.json | V89: falha_de_carregamento | X89: 46193.03
A90: 89 | B90: r00 | C90: 2026-06-20_00-25-00__validacao_tcc_unifal_r00 | D90: 2915007 | E90: amaweb | F90: 1 | G90: https://itaete.ba.gov.br/ | H90: https://amaweb.unifesp.br/avaliador/results/https%3A%2F%2Fitaete.ba.gov.br%2F | I90: amaweb.unifesp.br | J90: 1 | K90: AMAWeb | Avaliador | L90: 46193.029 | M90: 46193.031 | N90: 18685 | O90: falha_de_carregamento | R90: /media/serv-bot/cebece73-ca34-45fa-ba0e-9a1a1807e5c3/TCC_Unifal/Evidencias_TCC_Unifal/relatorios_ferramentas/2026-06-20_00-25-00__validacao_tcc_unifal_r00/amaweb/itaete-bahia-2915007/itaete_bahia_2915007_r00_amaweb_t1_20260620_004459.pdf | U90: /media/serv-bot/cebece73-ca34-45fa-ba0e-9a1a1807e5c3/TCC_Unifal/Processamento_TCC_Unifal/sessoes/2026-06-20_00-25-00__validacao_tcc_unifal_r00/json/r00_2915007_8b7829e2.json | V90: falha_de_carregamento | X90: 46193.031
A91: 90 | B91: r00 | C91: 2026-06-20_00-25-00__validacao_tcc_unifal_r00 | D91: 5100102 | E91: amaweb | F91: 2 | G91: https://www.acorizal.mt.gov.br/ | H91: https://amaweb.unifesp.br/avaliador/results/https%3A%2F%2Fwww.acorizal.mt.gov.br%2F | I91: amaweb.unifesp.br | J91: 1 | K91: AMAWeb | Avaliador | L91: 46193.03 | M91: 46193.032 | N91: 18248 | O91: falha_de_carregamento | R91: /media/serv-bot/cebece73-ca34-45fa-ba0e-9a1a1807e5c3/TCC_Unifal/Evidencias_TCC_Unifal/relatorios_ferramentas/2026-06-20_00-25-00__validacao_tcc_unifal_r00/amaweb/acorizal-mato-grosso-5100102/acorizal_mato grosso_5100102_r00_amaweb_t2_20260620_004625.pdf | U91: /media/serv-bot/cebece73-ca34-45fa-ba0e-9a1a1807e5c3/TCC_Unifal/Processamento_TCC_Unifal/sessoes/2026-06-20_00-25-00__validacao_tcc_unifal_r00/json/r00_5100102_d0f6659d.json | V91: falha_de_carregamento | X91: 46193.032
A92: 91 | B92: r00 | C92: 2026-06-20_00-25-00__validacao_tcc_unifal_r00 | D92: 1500107 | E92: amaweb | F92: 2 | G92: https://abaetetuba.pa.gov.br/ | H92: https://amaweb.unifesp.br/avaliador/results/https%3A%2F%2Fabaetetuba.pa.gov.br%2F | I92: amaweb.unifesp.br | J92: 1 | K92: AMAWeb | Avaliador | L92: 46193.031 | M92: 46193.033 | N92: 18355 | O92: falha_de_carregamento | R92: /media/serv-bot/cebece73-ca34-45fa-ba0e-9a1a1807e5c3/TCC_Unifal/Evidencias_TCC_Unifal/relatorios_ferramentas/2026-06-20_00-25-00__validacao_tcc_unifal_r00/amaweb/abaetetuba-para-1500107/abaetetuba_pará_1500107_r00_amaweb_t2_20260620_004706.pdf | U92: /media/serv-bot/cebece73-ca34-45fa-ba0e-9a1a1807e5c3/TCC_Unifal/Processamento_TCC_Unifal/sessoes/2026-06-20_00-25-00__validacao_tcc_unifal_r00/json/r00_1500107_85719c71.json | V92: falha_de_carregamento | X92: 46193.033
A93: 92 | B93: r00 | C93: 2026-06-20_00-25-00__validacao_tcc_unifal_r00 | D93: 2915007 | E93: amaweb | F93: 2 | G93: https://itaete.ba.gov.br/ | H93: https://amaweb.unifesp.br/avaliador/results/https%3A%2F%2Fitaete.ba.gov.br%2F | I93: amaweb.unifesp.br | J93: 1 | K93: AMAWeb | Avaliador | L93: 46193.031 | M93: 46193.034 | N93: 18259 | O93: falha_de_carregamento | R93: /media/serv-bot/cebece73-ca34-45fa-ba0e-9a1a1807e5c3/TCC_Unifal/Evidencias_TCC_Unifal/relatorios_ferramentas/2026-06-20_00-25-00__validacao_tcc_unifal_r00/amaweb/itaete-bahia-2915007/itaete_bahia_2915007_r00_amaweb_t2_20260620_004818.pdf | U93: /media/serv-bot/cebece73-ca34-45fa-ba0e-9a1a1807e5c3/TCC_Unifal/Processamento_TCC_Unifal/sessoes/2026-06-20_00-25-00__validacao_tcc_unifal_r00/json/r00_2915007_8b7829e2.json | V93: falha_de_carregamento | X93: 46193.034
A94: 93 | B94: r00 | C94: 2026-06-20_00-25-00__validacao_tcc_unifal_r00 | D94: 5100102 | E94: amaweb | F94: 3 | G94: https://www.acorizal.mt.gov.br/ | H94: https://amaweb.unifesp.br/avaliador/results/https%3A%2F%2Fwww.acorizal.mt.gov.br%2F | I94: amaweb.unifesp.br | J94: 1 | K94: AMAWeb | Avaliador | L94: 46193.033 | M94: 46193.035 | N94: 18247 | O94: falha_de_carregamento | R94: /media/serv-bot/cebece73-ca34-45fa-ba0e-9a1a1807e5c3/TCC_Unifal/Evidencias_TCC_Unifal/relatorios_ferramentas/2026-06-20_00-25-00__validacao_tcc_unifal_r00/amaweb/acorizal-mato-grosso-5100102/acorizal_mato grosso_5100102_r00_amaweb_t3_20260620_004957.pdf | U94: /media/serv-bot/cebece73-ca34-45fa-ba0e-9a1a1807e5c3/TCC_Unifal/Processamento_TCC_Unifal/sessoes/2026-06-20_00-25-00__validacao_tcc_unifal_r00/json/r00_5100102_d0f6659d.json | V94: falha_de_carregamento | X94: 46193.035
A95: 94 | B95: r00 | C95: 2026-06-20_00-25-00__validacao_tcc_unifal_r00 | D95: 5100102 | E95: accessmonitor | F95: 1 | G95: https://www.acorizal.mt.gov.br/ | H95: https://www.acorizal.mt.gov.br/ | I95: www.acorizal.mt.gov.br | J95: 0 | K95: :: Prefeitura Municipal de Acorizal - MT | L95: 46193.035 | M95: 46193.035 | N95: 850 | O95: sucesso | P95: 63 | Q95: 6.3 | U95: /media/serv-bot/cebece73-ca34-45fa-ba0e-9a1a1807e5c3/TCC_Unifal/Evidencias_TCC_Unifal/relatorios_ferramentas/2026-06-20_00-25-00__validacao_tcc_unifal_r00/accessmonitor/acorizal-mato-grosso-5100102/acorizal_mato grosso_5100102_r00_accessmonitor_t1_20260620_005010.json | X95: 46193.035
A96: 95 | B96: r00 | C96: 2026-06-20_00-25-00__validacao_tcc_unifal_r00 | D96: 1500107 | E96: amaweb | F96: 3 | G96: https://abaetetuba.pa.gov.br/ | H96: https://amaweb.unifesp.br/avaliador/results/https%3A%2F%2Fabaetetuba.pa.gov.br%2F | I96: amaweb.unifesp.br | J96: 1 | K96: AMAWeb | Avaliador | L96: 46193.033 | M96: 46193.035 | N96: 18334 | O96: falha_de_carregamento | R96: /media/serv-bot/cebece73-ca34-45fa-ba0e-9a1a1807e5c3/TCC_Unifal/Evidencias_TCC_Unifal/relatorios_ferramentas/2026-06-20_00-25-00__validacao_tcc_unifal_r00/amaweb/abaetetuba-para-1500107/abaetetuba_pará_1500107_r00_amaweb_t3_20260620_005044.pdf | U96: /media/serv-bot/cebece73-ca34-45fa-ba0e-9a1a1807e5c3/TCC_Unifal/Processamento_TCC_Unifal/sessoes/2026-06-20_00-25-00__validacao_tcc_unifal_r00/json/r00_1500107_85719c71.json | V96: falha_de_carregamento | X96: 46193.035
A97: 96 | B97: r00 | C97: 2026-06-20_00-25-00__validacao_tcc_unifal_r00 | D97: 1500107 | E97: accessmonitor | F97: 1 | G97: https://abaetetuba.pa.gov.br/ | H97: https://abaetetuba.pa.gov.br/ | I97: abaetetuba.pa.gov.br | J97: 0 | K97: Página Inicial - Prefeitura Municipal de Abaetetuba | Gestão 2025-2028 | L97: 46193.035 | M97: 46193.036 | N97: 1258 | O97: sucesso | P97: 60 | Q97: 6 | U97: /media/serv-bot/cebece73-ca34-45fa-ba0e-9a1a1807e5c3/TCC_Unifal/Evidencias_TCC_Unifal/relatorios_ferramentas/2026-06-20_00-25-00__validacao_tcc_unifal_r00/accessmonitor/abaetetuba-para-1500107/abaetetuba_pará_1500107_r00_accessmonitor_t1_20260620_005057.json | X97: 46193.036
A98: 97 | B98: r00 | C98: 2026-06-20_00-25-00__validacao_tcc_unifal_r00 | D98: 1500958 | E98: amaweb | F98: 1 | G98: https://www.auroradopara.pa.gov.br/ | H98: https://amaweb.unifesp.br/avaliador/results/https%3A%2F%2Fwww.auroradopara.pa.gov.br%2F | I98: amaweb.unifesp.br | J98: 1 | K98: AMAWeb | Avaliador | L98: 46193.036 | M98: 46193.036 | N98: 2123 | O98: sucesso | P98: 62 | Q98: 6.2 | R98: /media/serv-bot/cebece73-ca34-45fa-ba0e-9a1a1807e5c3/TCC_Unifal/Evidencias_TCC_Unifal/relatorios_ferramentas/2026-06-20_00-25-00__validacao_tcc_unifal_r00/amaweb/aurora-do-para-para-1500958/aurora-do-para_pará_1500958_r00_amaweb_t1_20260620_005134.pdf | U98: /media/serv-bot/cebece73-ca34-45fa-ba0e-9a1a1807e5c3/TCC_Unifal/Processamento_TCC_Unifal/sessoes/2026-06-20_00-25-00__validacao_tcc_unifal_r00/json/r00_1500958_e12d3d14.json | X98: 46193.036
A99: 98 | B99: r00 | C99: 2026-06-20_00-25-00__validacao_tcc_unifal_r00 | D99: 2915007 | E99: amaweb | F99: 3 | G99: https://itaete.ba.gov.br/ | H99: https://amaweb.unifesp.br/avaliador/results/https%3A%2F%2Fitaete.ba.gov.br%2F | I99: amaweb.unifesp.br | J99: 1 | K99: AMAWeb | Avaliador | L99: 46193.034 | M99: 46193.036 | N99: 18247 | O99: falha_de_carregamento | R99: /media/serv-bot/cebece73-ca34-45fa-ba0e-9a1a1807e5c3/TCC_Unifal/Evidencias_TCC_Unifal/relatorios_ferramentas/2026-06-20_00-25-00__validacao_tcc_unifal_r00/amaweb/itaete-bahia-2915007/itaete_bahia_2915007_r00_amaweb_t3_20260620_005156.pdf | U99: /media/serv-bot/cebece73-ca34-45fa-ba0e-9a1a1807e5c3/TCC_Unifal/Processamento_TCC_Unifal/sessoes/2026-06-20_00-25-00__validacao_tcc_unifal_r00/json/r00_2915007_8b7829e2.json | V99: falha_de_carregamento | X99: 46193.036
A100: 99 | B100: r00 | C100: 2026-06-20_00-25-00__validacao_tcc_unifal_r00 | D100: 1500958 | E100: accessmonitor | F100: 1 | G100: https://www.auroradopara.pa.gov.br/ | H100: https://auroradopara.pa.gov.br/ | I100: auroradopara.pa.gov.br | J100: 1 | K100: Prefeitura Municipal de Aurora do Pará | Gestão 2025-2028 | L100: 46193.036 | M100: 46193.036 | N100: 985 | O100: sucesso | P100: 64 | Q100: 6.4 | U100: /media/serv-bot/cebece73-ca34-45fa-ba0e-9a1a1807e5c3/TCC_Unifal/Evidencias_TCC_Unifal/relatorios_ferramentas/2026-06-20_00-25-00__validacao_tcc_unifal_r00/accessmonitor/aurora-do-para-para-1500958/aurora-do-para_pará_1500958_r00_accessmonitor_t1_20260620_005148.json | X100: 46193.036
...

Sheet 00_Conferencia
A1: Indicador | B1: Resultado | D1: Rodada | E1: Registros
A2: Municípios na base | B2: =COUNTA(Base_Amostral!A:A)-1 -> 362 | D2: r00 | E2: =COUNTIF(Execucoes!B:B,D2) -> 362
A3: Códigos IBGE únicos | B3: {=SUMPRODUCT(1/COUNTIF(Base_Amostral!A2:A363,Base_Amostral!A2:A363))} -> 362 | D3: r01 | E3: =COUNTIF(Execucoes!B:B,D3) -> 362
A4: Registros de execução | B4: =COUNTA(Execucoes!A:A)-1 -> 1810 | D4: r02 | E4: =COUNTIF(Execucoes!B:B,D4) -> 362
A5: Rodadas esperadas | B5: 5 | D5: r03 | E5: =COUNTIF(Execucoes!B:B,D5) -> 362
A6: Registros esperados | B6: =B2*B5 -> 1810 | D6: r04 | E6: =COUNTIF(Execucoes!B:B,D6) -> 362
A7: Municípios por rodada | B7: =B4/B5 -> 362
A8: Duplicidades município + rodada | B8: {=COUNTA(Execucoes!Q2:Q1811)-SUMPRODUCT(1/COUNTIF(Execucoes!Q2:Q1811,Execucoes!Q2:Q1811))} -> 0
A10: Rodada | B10: AMA válidas | C10: Access válidas | D10: Pares válidos
A11: r00 | B11: =COUNTIFS(Execucoes!B:B,A11,Execucoes!K:K,1) -> 355 | C11: =COUNTIFS(Execucoes!B:B,A11,Execucoes!L:L,1) -> 354 | D11: =COUNTIFS(Execucoes!B:B,A11,Execucoes!K:K,1,Execucoes!L:L,1) -> 350
A12: r01 | B12: =COUNTIFS(Execucoes!B:B,A12,Execucoes!K:K,1) -> 356 | C12: =COUNTIFS(Execucoes!B:B,A12,Execucoes!L:L,1) -> 355 | D12: =COUNTIFS(Execucoes!B:B,A12,Execucoes!K:K,1,Execucoes!L:L,1) -> 351
A13: r02 | B13: =COUNTIFS(Execucoes!B:B,A13,Execucoes!K:K,1) -> 355 | C13: =COUNTIFS(Execucoes!B:B,A13,Execucoes!L:L,1) -> 354 | D13: =COUNTIFS(Execucoes!B:B,A13,Execucoes!K:K,1,Execucoes!L:L,1) -> 350
A14: r03 | B14: =COUNTIFS(Execucoes!B:B,A14,Execucoes!K:K,1) -> 355 | C14: =COUNTIFS(Execucoes!B:B,A14,Execucoes!L:L,1) -> 355 | D14: =COUNTIFS(Execucoes!B:B,A14,Execucoes!K:K,1,Execucoes!L:L,1) -> 351
A15: r04 | B15: =COUNTIFS(Execucoes!B:B,A15,Execucoes!K:K,1) -> 357 | C15: =COUNTIFS(Execucoes!B:B,A15,Execucoes!L:L,1) -> 354 | D15: =COUNTIFS(Execucoes!B:B,A15,Execucoes!K:K,1,Execucoes!L:L,1) -> 350
B16: =SUM(B12:B15) -> 1423 | C16: =SUM(C12:C15) -> 1418 | D16: =SUM(D12:D15) -> 1402
A18: Notas AMAWeb na base analítica | B18: =COUNT('01_Base_Analitica'!U2:U1449) -> 1423
A19: Notas AccessMonitor na base analítica | B19: =COUNT('01_Base_Analitica'!V2:V1449) -> 1418
A20: Pares válidos na base analítica | B20: =SUM('01_Base_Analitica'!Y2:Y1449) -> 1402

Sheet 01_Base_Analitica
A1: id_execucao | B1: rodada | C1: sessao | D1: codigo_municipio_completo | E1: nota_amaweb | F1: status_amaweb | G1: avaliado_amaweb_em | H1: nota_accessmonitor | I1: status_accessmonitor | J1: avaliado_accessmonitor_em | K1: tem_resultado_amaweb | L1: tem_resultado_accessmonitor | M1: status_geral | N1: observacao_analise | O1: criado_em | P1: atualizado_em | Q1: chave_municipio_rodada | R1: município | S1: UF | T1: região | U1: nota AMAWeb convertida | V1: nota AccessMonitor convertida | W1: diferença AMA − Access | X1: média das duas ferramentas | Y1: par válido | Z1: variação AMA rodada anterior | AA1: variação Access rodada anterior | AB1: amplitude AMA | AC1: amplitude Access | AD1: número de rodadas válidas AMA | AE1: número de rodadas válidas Access
A2: 429 | B2: r01 | C2: 2026-06-22_23-12-00__validacao_tcc_unifal_r01 | D2: 1100015 | E2: 70 | F2: sucesso | G2: 46195.995 | H2: 72 | I2: sucesso | J2: 46195.995 | K2: 1 | L2: 1 | M2: completo | O2: 46195.995 | P2: 46195.995 | Q2: =D2&"|"&B2 -> 1100015|r01 | R2: =VLOOKUP(D2,Base_Amostral!$A:$G,5,FALSE) -> Alta Floresta D'Oeste | S2: =VLOOKUP(D2,Base_Amostral!$A:$G,3,FALSE) -> Rondônia | T2: =VLOOKUP(D2,Base_Amostral!$A:$G,6,FALSE) -> Norte | U2: =IF(E2="","",E2/10) -> 7 | V2: =IF(H2="","",H2/10) -> 7.2 | W2: =IF(OR(U2="",V2=""),"",U2-V2) -> -0.2 | X2: =IF(OR(U2="",V2=""),"",AVERAGE(U2:V2)) -> 7.1 | Y2: =IF(AND(U2<>"",V2<>""),1,0) -> 1 | Z2: =IF(D2<>D1,"",IF(OR(U2="",U1=""),"",U2-U1)) | AA2: =IF(D2<>D1,"",IF(OR(V2="",V1=""),"",V2-V1)) | AB2: =IF(B2<>"r04","",IF(COUNT(INDEX(U:U,ROW()-3):U2)<2,"",MAX(INDEX(U:U,ROW()-3):U2)-MIN(INDEX(U:U,ROW()-3):U2))) | AC2: =IF(B2<>"r04","",IF(COUNT(INDEX(V:V,ROW()-3):V2)<2,"",MAX(INDEX(V:V,ROW()-3):V2)-MIN(INDEX(V:V,ROW()-3):V2))) | AD2: =IF(B2<>"r04","",COUNT(INDEX(U:U,ROW()-3):U2)) | AE2: =IF(B2<>"r04","",COUNT(INDEX(V:V,ROW()-3):V2))
A3: 775 | B3: r02 | C3: 2026-06-30_18-34-12__validacao_tcc_unifal_r02 | D3: 1100015 | E3: 70 | F3: sucesso | G3: 46203.794 | H3: 72 | I3: sucesso | J3: 46203.794 | K3: 1 | L3: 1 | M3: completo | O3: 46203.794 | P3: 46203.794 | Q3: =D3&"|"&B3 -> 1100015|r02 | R3: =VLOOKUP(D3,Base_Amostral!$A:$G,5,FALSE) -> Alta Floresta D'Oeste | S3: =VLOOKUP(D3,Base_Amostral!$A:$G,3,FALSE) -> Rondônia | T3: =VLOOKUP(D3,Base_Amostral!$A:$G,6,FALSE) -> Norte | U3: =IF(E3="","",E3/10) -> 7 | V3: =IF(H3="","",H3/10) -> 7.2 | W3: =IF(OR(U3="",V3=""),"",U3-V3) -> -0.2 | X3: =IF(OR(U3="",V3=""),"",AVERAGE(U3:V3)) -> 7.1 | Y3: =IF(AND(U3<>"",V3<>""),1,0) -> 1 | Z3: =IF(D3<>D2,"",IF(OR(U3="",U2=""),"",U3-U2)) -> 0 | AA3: =IF(D3<>D2,"",IF(OR(V3="",V2=""),"",V3-V2)) -> 0 | AB3: =IF(B3<>"r04","",IF(COUNT(INDEX(U:U,ROW()-3):U3)<2,"",MAX(INDEX(U:U,ROW()-3):U3)-MIN(INDEX(U:U,ROW()-3):U3))) | AC3: =IF(B3<>"r04","",IF(COUNT(INDEX(V:V,ROW()-3):V3)<2,"",MAX(INDEX(V:V,ROW()-3):V3)-MIN(INDEX(V:V,ROW()-3):V3))) | AD3: =IF(B3<>"r04","",COUNT(INDEX(U:U,ROW()-3):U3)) | AE3: =IF(B3<>"r04","",COUNT(INDEX(V:V,ROW()-3):V3))
A4: 1137 | B4: r03 | C4: 2026-07-06_19-27-44__validacao_tcc_unifal_r03 | D4: 1100015 | E4: 70 | F4: sucesso | G4: 46209.835 | H4: 72 | I4: sucesso | J4: 46209.835 | K4: 1 | L4: 1 | M4: completo | O4: 46209.834 | P4: 46209.835 | Q4: =D4&"|"&B4 -> 1100015|r03 | R4: =VLOOKUP(D4,Base_Amostral!$A:$G,5,FALSE) -> Alta Floresta D'Oeste | S4: =VLOOKUP(D4,Base_Amostral!$A:$G,3,FALSE) -> Rondônia | T4: =VLOOKUP(D4,Base_Amostral!$A:$G,6,FALSE) -> Norte | U4: =IF(E4="","",E4/10) -> 7 | V4: =IF(H4="","",H4/10) -> 7.2 | W4: =IF(OR(U4="",V4=""),"",U4-V4) -> -0.2 | X4: =IF(OR(U4="",V4=""),"",AVERAGE(U4:V4)) -> 7.1 | Y4: =IF(AND(U4<>"",V4<>""),1,0) -> 1 | Z4: =IF(D4<>D3,"",IF(OR(U4="",U3=""),"",U4-U3)) -> 0 | AA4: =IF(D4<>D3,"",IF(OR(V4="",V3=""),"",V4-V3)) -> 0 | AB4: =IF(B4<>"r04","",IF(COUNT(INDEX(U:U,ROW()-3):U4)<2,"",MAX(INDEX(U:U,ROW()-3):U4)-MIN(INDEX(U:U,ROW()-3):U4))) | AC4: =IF(B4<>"r04","",IF(COUNT(INDEX(V:V,ROW()-3):V4)<2,"",MAX(INDEX(V:V,ROW()-3):V4)-MIN(INDEX(V:V,ROW()-3):V4))) | AD4: =IF(B4<>"r04","",COUNT(INDEX(U:U,ROW()-3):U4)) | AE4: =IF(B4<>"r04","",COUNT(INDEX(V:V,ROW()-3):V4))
A5: 1507 | B5: r04 | C5: 2026-07-13_19-07-57__validacao_tcc_unifal_r04 | D5: 1100015 | E5: 80 | F5: sucesso | G5: 46216.817 | H5: 72 | I5: sucesso | J5: 46216.817 | K5: 1 | L5: 1 | M5: completo | O5: 46216.816 | P5: 46216.817 | Q5: =D5&"|"&B5 -> 1100015|r04 | R5: =VLOOKUP(D5,Base_Amostral!$A:$G,5,FALSE) -> Alta Floresta D'Oeste | S5: =VLOOKUP(D5,Base_Amostral!$A:$G,3,FALSE) -> Rondônia | T5: =VLOOKUP(D5,Base_Amostral!$A:$G,6,FALSE) -> Norte | U5: =IF(E5="","",E5/10) -> 8 | V5: =IF(H5="","",H5/10) -> 7.2 | W5: =IF(OR(U5="",V5=""),"",U5-V5) -> 0.8 | X5: =IF(OR(U5="",V5=""),"",AVERAGE(U5:V5)) -> 7.6 | Y5: =IF(AND(U5<>"",V5<>""),1,0) -> 1 | Z5: =IF(D5<>D4,"",IF(OR(U5="",U4=""),"",U5-U4)) -> 1 | AA5: =IF(D5<>D4,"",IF(OR(V5="",V4=""),"",V5-V4)) -> 0 | AB5: =IF(B5<>"r04","",IF(COUNT(INDEX(U:U,ROW()-3):U5)<2,"",MAX(INDEX(U:U,ROW()-3):U5)-MIN(INDEX(U:U,ROW()-3):U5))) -> 1 | AC5: =IF(B5<>"r04","",IF(COUNT(INDEX(V:V,ROW()-3):V5)<2,"",MAX(INDEX(V:V,ROW()-3):V5)-MIN(INDEX(V:V,ROW()-3):V5))) -> 0 | AD5: =IF(B5<>"r04","",COUNT(INDEX(U:U,ROW()-3):U5)) -> 4 | AE5: =IF(B5<>"r04","",COUNT(INDEX(V:V,ROW()-3):V5)) -> 4
A6: 438 | B6: r01 | C6: 2026-06-22_23-12-00__validacao_tcc_unifal_r01 | D6: 1100080 | E6: 65 | F6: sucesso | G6: 46195.997 | H6: 67 | I6: sucesso | J6: 46195.997 | K6: 1 | L6: 1 | M6: completo | O6: 46195.996 | P6: 46195.997 | Q6: =D6&"|"&B6 -> 1100080|r01 | R6: =VLOOKUP(D6,Base_Amostral!$A:$G,5,FALSE) -> Costa Marques | S6: =VLOOKUP(D6,Base_Amostral!$A:$G,3,FALSE) -> Rondônia | T6: =VLOOKUP(D6,Base_Amostral!$A:$G,6,FALSE) -> Norte | U6: =IF(E6="","",E6/10) -> 6.5 | V6: =IF(H6="","",H6/10) -> 6.7 | W6: =IF(OR(U6="",V6=""),"",U6-V6) -> -0.2 | X6: =IF(OR(U6="",V6=""),"",AVERAGE(U6:V6)) -> 6.6 | Y6: =IF(AND(U6<>"",V6<>""),1,0) -> 1 | Z6: =IF(D6<>D5,"",IF(OR(U6="",U5=""),"",U6-U5)) | AA6: =IF(D6<>D5,"",IF(OR(V6="",V5=""),"",V6-V5)) | AB6: =IF(B6<>"r04","",IF(COUNT(INDEX(U:U,ROW()-3):U6)<2,"",MAX(INDEX(U:U,ROW()-3):U6)-MIN(INDEX(U:U,ROW()-3):U6))) | AC6: =IF(B6<>"r04","",IF(COUNT(INDEX(V:V,ROW()-3):V6)<2,"",MAX(INDEX(V:V,ROW()-3):V6)-MIN(INDEX(V:V,ROW()-3):V6))) | AD6: =IF(B6<>"r04","",COUNT(INDEX(U:U,ROW()-3):U6)) | AE6: =IF(B6<>"r04","",COUNT(INDEX(V:V,ROW()-3):V6))
A7: 781 | B7: r02 | C7: 2026-06-30_18-34-12__validacao_tcc_unifal_r02 | D7: 1100080 | E7: 65 | F7: sucesso | G7: 46203.796 | H7: 65 | I7: sucesso | J7: 46203.797 | K7: 1 | L7: 1 | M7: completo | O7: 46203.796 | P7: 46203.797 | Q7: =D7&"|"&B7 -> 1100080|r02 | R7: =VLOOKUP(D7,Base_Amostral!$A:$G,5,FALSE) -> Costa Marques | S7: =VLOOKUP(D7,Base_Amostral!$A:$G,3,FALSE) -> Rondônia | T7: =VLOOKUP(D7,Base_Amostral!$A:$G,6,FALSE) -> Norte | U7: =IF(E7="","",E7/10) -> 6.5 | V7: =IF(H7="","",H7/10) -> 6.5 | W7: =IF(OR(U7="",V7=""),"",U7-V7) -> 0 | X7: =IF(OR(U7="",V7=""),"",AVERAGE(U7:V7)) -> 6.5 | Y7: =IF(AND(U7<>"",V7<>""),1,0) -> 1 | Z7: =IF(D7<>D6,"",IF(OR(U7="",U6=""),"",U7-U6)) -> 0 | AA7: =IF(D7<>D6,"",IF(OR(V7="",V6=""),"",V7-V6)) -> -0.2 | AB7: =IF(B7<>"r04","",IF(COUNT(INDEX(U:U,ROW()-3):U7)<2,"",MAX(INDEX(U:U,ROW()-3):U7)-MIN(INDEX(U:U,ROW()-3):U7))) | AC7: =IF(B7<>"r04","",IF(COUNT(INDEX(V:V,ROW()-3):V7)<2,"",MAX(INDEX(V:V,ROW()-3):V7)-MIN(INDEX(V:V,ROW()-3):V7))) | AD7: =IF(B7<>"r04","",COUNT(INDEX(U:U,ROW()-3):U7)) | AE7: =IF(B7<>"r04","",COUNT(INDEX(V:V,ROW()-3):V7))
A8: 1146 | B8: r03 | C8: 2026-07-06_19-27-44__validacao_tcc_unifal_r03 | D8: 1100080 | E8: 62 | F8: sucesso | G8: 46209.839 | H8: 66 | I8: sucesso | J8: 46209.839 | K8: 1 | L8: 1 | M8: completo | O8: 46209.839 | P8: 46209.839 | Q8: =D8&"|"&B8 -> 1100080|r03 | R8: =VLOOKUP(D8,Base_Amostral!$A:$G,5,FALSE) -> Costa Marques | S8: =VLOOKUP(D8,Base_Amostral!$A:$G,3,FALSE) -> Rondônia | T8: =VLOOKUP(D8,Base_Amostral!$A:$G,6,FALSE) -> Norte | U8: =IF(E8="","",E8/10) -> 6.2 | V8: =IF(H8="","",H8/10) -> 6.6 | W8: =IF(OR(U8="",V8=""),"",U8-V8) -> -0.4 | X8: =IF(OR(U8="",V8=""),"",AVERAGE(U8:V8)) -> 6.4 | Y8: =IF(AND(U8<>"",V8<>""),1,0) -> 1 | Z8: =IF(D8<>D7,"",IF(OR(U8="",U7=""),"",U8-U7)) -> -0.3 | AA8: =IF(D8<>D7,"",IF(OR(V8="",V7=""),"",V8-V7)) -> 0.1 | AB8: =IF(B8<>"r04","",IF(COUNT(INDEX(U:U,ROW()-3):U8)<2,"",MAX(INDEX(U:U,ROW()-3):U8)-MIN(INDEX(U:U,ROW()-3):U8))) | AC8: =IF(B8<>"r04","",IF(COUNT(INDEX(V:V,ROW()-3):V8)<2,"",MAX(INDEX(V:V,ROW()-3):V8)-MIN(INDEX(V:V,ROW()-3):V8))) | AD8: =IF(B8<>"r04","",COUNT(INDEX(U:U,ROW()-3):U8)) | AE8: =IF(B8<>"r04","",COUNT(INDEX(V:V,ROW()-3):V8))
A9: 1516 | B9: r04 | C9: 2026-07-13_19-07-57__validacao_tcc_unifal_r04 | D9: 1100080 | E9: 71 | F9: sucesso | G9: 46216.819 | H9: 66 | I9: sucesso | J9: 46216.819 | K9: 1 | L9: 1 | M9: completo | O9: 46216.818 | P9: 46216.819 | Q9: =D9&"|"&B9 -> 1100080|r04 | R9: =VLOOKUP(D9,Base_Amostral!$A:$G,5,FALSE) -> Costa Marques | S9: =VLOOKUP(D9,Base_Amostral!$A:$G,3,FALSE) -> Rondônia | T9: =VLOOKUP(D9,Base_Amostral!$A:$G,6,FALSE) -> Norte | U9: =IF(E9="","",E9/10) -> 7.1 | V9: =IF(H9="","",H9/10) -> 6.6 | W9: =IF(OR(U9="",V9=""),"",U9-V9) -> 0.5 | X9: =IF(OR(U9="",V9=""),"",AVERAGE(U9:V9)) -> 6.85 | Y9: =IF(AND(U9<>"",V9<>""),1,0) -> 1 | Z9: =IF(D9<>D8,"",IF(OR(U9="",U8=""),"",U9-U8)) -> 0.9 | AA9: =IF(D9<>D8,"",IF(OR(V9="",V8=""),"",V9-V8)) -> 0 | AB9: =IF(B9<>"r04","",IF(COUNT(INDEX(U:U,ROW()-3):U9)<2,"",MAX(INDEX(U:U,ROW()-3):U9)-MIN(INDEX(U:U,ROW()-3):U9))) -> 0.9 | AC9: =IF(B9<>"r04","",IF(COUNT(INDEX(V:V,ROW()-3):V9)<2,"",MAX(INDEX(V:V,ROW()-3):V9)-MIN(INDEX(V:V,ROW()-3):V9))) -> 0.2 | AD9: =IF(B9<>"r04","",COUNT(INDEX(U:U,ROW()-3):U9)) -> 4 | AE9: =IF(B9<>"r04","",COUNT(INDEX(V:V,ROW()-3):V9)) -> 4
A10: 433 | B10: r01 | C10: 2026-06-22_23-12-00__validacao_tcc_unifal_r01 | D10: 1100700 | E10: 92 | F10: sucesso | G10: 46195.996 | H10: 79 | I10: sucesso | J10: 46195.996 | K10: 1 | L10: 1 | M10: completo | O10: 46195.995 | P10: 46195.996 | Q10: =D10&"|"&B10 -> 1100700|r01 | R10: =VLOOKUP(D10,Base_Amostral!$A:$G,5,FALSE) -> Campo Novo de Rondônia | S10: =VLOOKUP(D10,Base_Amostral!$A:$G,3,FALSE) -> Rondônia | T10: =VLOOKUP(D10,Base_Amostral!$A:$G,6,FALSE) -> Norte | U10: =IF(E10="","",E10/10) -> 9.2 | V10: =IF(H10="","",H10/10) -> 7.9 | W10: =IF(OR(U10="",V10=""),"",U10-V10) -> 1.3 | X10: =IF(OR(U10="",V10=""),"",AVERAGE(U10:V10)) -> 8.55 | Y10: =IF(AND(U10<>"",V10<>""),1,0) -> 1 | Z10: =IF(D10<>D9,"",IF(OR(U10="",U9=""),"",U10-U9)) | AA10: =IF(D10<>D9,"",IF(OR(V10="",V9=""),"",V10-V9)) | AB10: =IF(B10<>"r04","",IF(COUNT(INDEX(U:U,ROW()-3):U10)<2,"",MAX(INDEX(U:U,ROW()-3):U10)-MIN(INDEX(U:U,ROW()-3):U10))) | AC10: =IF(B10<>"r04","",IF(COUNT(INDEX(V:V,ROW()-3):V10)<2,"",MAX(INDEX(V:V,ROW()-3):V10)-MIN(INDEX(V:V,ROW()-3):V10))) | AD10: =IF(B10<>"r04","",COUNT(INDEX(U:U,ROW()-3):U10)) | AE10: =IF(B10<>"r04","",COUNT(INDEX(V:V,ROW()-3):V10))
A11: 779 | B11: r02 | C11: 2026-06-30_18-34-12__validacao_tcc_unifal_r02 | D11: 1100700 | E11: 92 | F11: sucesso | G11: 46203.795 | H11: 78 | I11: sucesso | J11: 46203.795 | K11: 1 | L11: 1 | M11: completo | O11: 46203.794 | P11: 46203.795 | Q11: =D11&"|"&B11 -> 1100700|r02 | R11: =VLOOKUP(D11,Base_Amostral!$A:$G,5,FALSE) -> Campo Novo de Rondônia | S11: =VLOOKUP(D11,Base_Amostral!$A:$G,3,FALSE) -> Rondônia | T11: =VLOOKUP(D11,Base_Amostral!$A:$G,6,FALSE) -> Norte | U11: =IF(E11="","",E11/10) -> 9.2 | V11: =IF(H11="","",H11/10) -> 7.8 | W11: =IF(OR(U11="",V11=""),"",U11-V11) -> 1.4 | X11: =IF(OR(U11="",V11=""),"",AVERAGE(U11:V11)) -> 8.5 | Y11: =IF(AND(U11<>"",V11<>""),1,0) -> 1 | Z11: =IF(D11<>D10,"",IF(OR(U11="",U10=""),"",U11-U10)) -> 0 | AA11: =IF(D11<>D10,"",IF(OR(V11="",V10=""),"",V11-V10)) -> -0.1 | AB11: =IF(B11<>"r04","",IF(COUNT(INDEX(U:U,ROW()-3):U11)<2,"",MAX(INDEX(U:U,ROW()-3):U11)-MIN(INDEX(U:U,ROW()-3):U11))) | AC11: =IF(B11<>"r04","",IF(COUNT(INDEX(V:V,ROW()-3):V11)<2,"",MAX(INDEX(V:V,ROW()-3):V11)-MIN(INDEX(V:V,ROW()-3):V11))) | AD11: =IF(B11<>"r04","",COUNT(INDEX(U:U,ROW()-3):U11)) | AE11: =IF(B11<>"r04","",COUNT(INDEX(V:V,ROW()-3):V11))
A12: 1140 | B12: r03 | C12: 2026-07-06_19-27-44__validacao_tcc_unifal_r03 | D12: 1100700 | E12: 92 | F12: sucesso | G12: 46209.838 | H12: 78 | I12: sucesso | J12: 46209.838 | K12: 1 | L12: 1 | M12: completo | O12: 46209.835 | P12: 46209.838 | Q12: =D12&"|"&B12 -> 1100700|r03 | R12: =VLOOKUP(D12,Base_Amostral!$A:$G,5,FALSE) -> Campo Novo de Rondônia | S12: =VLOOKUP(D12,Base_Amostral!$A:$G,3,FALSE) -> Rondônia | T12: =VLOOKUP(D12,Base_Amostral!$A:$G,6,FALSE) -> Norte | U12: =IF(E12="","",E12/10) -> 9.2 | V12: =IF(H12="","",H12/10) -> 7.8 | W12: =IF(OR(U12="",V12=""),"",U12-V12) -> 1.4 | X12: =IF(OR(U12="",V12=""),"",AVERAGE(U12:V12)) -> 8.5 | Y12: =IF(AND(U12<>"",V12<>""),1,0) -> 1 | Z12: =IF(D12<>D11,"",IF(OR(U12="",U11=""),"",U12-U11)) -> 0 | AA12: =IF(D12<>D11,"",IF(OR(V12="",V11=""),"",V12-V11)) -> 0 | AB12: =IF(B12<>"r04","",IF(COUNT(INDEX(U:U,ROW()-3):U12)<2,"",MAX(INDEX(U:U,ROW()-3):U12)-MIN(INDEX(U:U,ROW()-3):U12))) | AC12: =IF(B12<>"r04","",IF(COUNT(INDEX(V:V,ROW()-3):V12)<2,"",MAX(INDEX(V:V,ROW()-3):V12)-MIN(INDEX(V:V,ROW()-3):V12))) | AD12: =IF(B12<>"r04","",COUNT(INDEX(U:U,ROW()-3):U12)) | AE12: =IF(B12<>"r04","",COUNT(INDEX(V:V,ROW()-3):V12))
A13: 1511 | B13: r04 | C13: 2026-07-13_19-07-57__validacao_tcc_unifal_r04 | D13: 1100700 | E13: 96 | F13: sucesso | G13: 46216.817 | H13: 83 | I13: sucesso | J13: 46216.817 | K13: 1 | L13: 1 | M13: completo | O13: 46216.817 | P13: 46216.817 | Q13: =D13&"|"&B13 -> 1100700|r04 | R13: =VLOOKUP(D13,Base_Amostral!$A:$G,5,FALSE) -> Campo Novo de Rondônia | S13: =VLOOKUP(D13,Base_Amostral!$A:$G,3,FALSE) -> Rondônia | T13: =VLOOKUP(D13,Base_Amostral!$A:$G,6,FALSE) -> Norte | U13: =IF(E13="","",E13/10) -> 9.6 | V13: =IF(H13="","",H13/10) -> 8.3 | W13: =IF(OR(U13="",V13=""),"",U13-V13) -> 1.3 | X13: =IF(OR(U13="",V13=""),"",AVERAGE(U13:V13)) -> 8.95 | Y13: =IF(AND(U13<>"",V13<>""),1,0) -> 1 | Z13: =IF(D13<>D12,"",IF(OR(U13="",U12=""),"",U13-U12)) -> 0.4 | AA13: =IF(D13<>D12,"",IF(OR(V13="",V12=""),"",V13-V12)) -> 0.5 | AB13: =IF(B13<>"r04","",IF(COUNT(INDEX(U:U,ROW()-3):U13)<2,"",MAX(INDEX(U:U,ROW()-3):U13)-MIN(INDEX(U:U,ROW()-3):U13))) -> 0.4 | AC13: =IF(B13<>"r04","",IF(COUNT(INDEX(V:V,ROW()-3):V13)<2,"",MAX(INDEX(V:V,ROW()-3):V13)-MIN(INDEX(V:V,ROW()-3):V13))) -> 0.5 | AD13: =IF(B13<>"r04","",COUNT(INDEX(U:U,ROW()-3):U13)) -> 4 | AE13: =IF(B13<>"r04","",COUNT(INDEX(V:V,ROW()-3):V13)) -> 4
... A45: 1477 | B45: r04 | C45: 2026-07-13_19-07-57__validacao_tcc_unifal_r04 | D45: 1301209 | E45: 69 | F45: sucesso | G45: 46216.805 | H45: 66 | I45: sucesso | J45: 46216.805 | K45: 1 | L45: 1 | M45: completo | O45: 46216.804 | P45: 46216.805 | Q45: =D45&"|"&B45 -> 1301209|r04 | R45: =VLOOKUP(D45,Base_Amostral!$A:$G,5,FALSE) -> Coari | S45: =VLOOKUP(D45,Base_Amostral!$A:$G,3,FALSE) -> Amazonas | T45: =VLOOKUP(D45,Base_Amostral!$A:$G,6,FALSE) -> Norte | U45: =IF(E45="","",E45/10) -> 6.9 | V45: =IF(H45="","",H45/10) -> 6.6 | W45: =IF(OR(U45="",V45=""),"",U45-V45) -> 0.3 | X45: =IF(OR(U45="",V45=""),"",AVERAGE(U45:V45)) -> 6.75 | Y45: =IF(AND(U45<>"",V45<>""),1,0) -> 1 | Z45: =IF(D45<>D44,"",IF(OR(U45="",U44=""),"",U45-U44)) -> 0.6 | AA45: =IF(D45<>D44,"",IF(OR(V45="",V44=""),"",V45-V44)) -> 0 | AB45: =IF(B45<>"r04","",IF(COUNT(INDEX(U:U,ROW()-3):U45)<2,"",MAX(INDEX(U:U,ROW()-3):U45)-MIN(INDEX(U:U,ROW()-3):U45))) -> 0.6 | AC45: =IF(B45<>"r04","",IF(COUNT(INDEX(V:V,ROW()-3):V45)<2,"",MAX(INDEX(V:V,ROW()-3):V45)-MIN(INDEX(V:V,ROW()-3):V45))) -> 0 | AD45: =IF(B45<>"r04","",COUNT(INDEX(U:U,ROW()-3):U45)) -> 4 | AE45: =IF(B45<>"r04","",COUNT(INDEX(V:V,ROW()-3):V45)) -> 4
A46: 400 | B46: r01 | C46: 2026-06-22_23-12-00__validacao_tcc_unifal_r01 | D46: 1303403 | E46: 92 | F46: sucesso | G46: 46195.982 | I46: sucesso_sem_nota | J46: 46195.982 | K46: 1 | L46: 0 | M46: parcial | O46: 46195.977 | P46: 46195.982 | Q46: =D46&"|"&B46 -> 1303403|r01 | R46: =VLOOKUP(D46,Base_Amostral!$A:$G,5,FALSE) -> Parintins | S46: =VLOOKUP(D46,Base_Amostral!$A:$G,3,FALSE) -> Amazonas | T46: =VLOOKUP(D46,Base_Amostral!$A:$G,6,FALSE) -> Norte | U46: =IF(E46="","",E46/10) -> 9.2 | V46: =IF(H46="","",H46/10) | W46: =IF(OR(U46="",V46=""),"",U46-V46) | X46: =IF(OR(U46="",V46=""),"",AVERAGE(U46:V46)) | Y46: =IF(AND(U46<>"",V46<>""),1,0) -> 0 | Z46: =IF(D46<>D45,"",IF(OR(U46="",U45=""),"",U46-U45)) | AA46: =IF(D46<>D45,"",IF(OR(V46="",V45=""),"",V46-V45)) | AB46: =IF(B46<>"r04","",IF(COUNT(INDEX(U:U,ROW()-3):U46)<2,"",MAX(INDEX(U:U,ROW()-3):U46)-MIN(INDEX(U:U,ROW()-3):U46))) | AC46: =IF(B46<>"r04","",IF(COUNT(INDEX(V:V,ROW()-3):V46)<2,"",MAX(INDEX(V:V,ROW()-3):V46)-MIN(INDEX(V:V,ROW()-3):V46))) | AD46: =IF(B46<>"r04","",COUNT(INDEX(U:U,ROW()-3):U46)) | AE46: =IF(B46<>"r04","",COUNT(INDEX(V:V,ROW()-3):V46))
A47: 765 | B47: r02 | C47: 2026-06-30_18-34-12__validacao_tcc_unifal_r02 | D47: 1303403 | E47: 92 | F47: sucesso | G47: 46203.787 | I47: sucesso_sem_nota | J47: 46203.788 | K47: 1 | L47: 0 | M47: parcial | O47: 46203.787 | P47: 46203.788 | Q47: =D47&"|"&B47 -> 1303403|r02 | R47: =VLOOKUP(D47,Base_Amostral!$A:$G,5,FALSE) -> Parintins | S47: =VLOOKUP(D47,Base_Amostral!$A:$G,3,FALSE) -> Amazonas | T47: =VLOOKUP(D47,Base_Amostral!$A:$G,6,FALSE) -> Norte | U47: =IF(E47="","",E47/10) -> 9.2 | V47: =IF(H47="","",H47/10) | W47: =IF(OR(U47="",V47=""),"",U47-V47) | X47: =IF(OR(U47="",V47=""),"",AVERAGE(U47:V47)) | Y47: =IF(AND(U47<>"",V47<>""),1,0) -> 0 | Z47: =IF(D47<>D46,"",IF(OR(U47="",U46=""),"",U47-U46)) -> 0 | AA47: =IF(D47<>D46,"",IF(OR(V47="",V46=""),"",V47-V46)) | AB47: =IF(B47<>"r04","",IF(COUNT(INDEX(U:U,ROW()-3):U47)<2,"",MAX(INDEX(U:U,ROW()-3):U47)-MIN(INDEX(U:U,ROW()-3):U47))) | AC47: =IF(B47<>"r04","",IF(COUNT(INDEX(V:V,ROW()-3):V47)<2,"",MAX(INDEX(V:V,ROW()-3):V47)-MIN(INDEX(V:V,ROW()-3):V47))) | AD47: =IF(B47<>"r04","",COUNT(INDEX(U:U,ROW()-3):U47)) | AE47: =IF(B47<>"r04","",COUNT(INDEX(V:V,ROW()-3):V47))
A48: 1127 | B48: r03 | C48: 2026-07-06_19-27-44__validacao_tcc_unifal_r03 | D48: 1303403 | E48: 92 | F48: sucesso | G48: 46209.828 | I48: sucesso_sem_nota | J48: 46209.829 | K48: 1 | L48: 0 | M48: parcial | O48: 46209.828 | P48: 46209.829 | Q48: =D48&"|"&B48 -> 1303403|r03 | R48: =VLOOKUP(D48,Base_Amostral!$A:$G,5,FALSE) -> Parintins | S48: =VLOOKUP(D48,Base_Amostral!$A:$G,3,FALSE) -> Amazonas | T48: =VLOOKUP(D48,Base_Amostral!$A:$G,6,FALSE) -> Norte | U48: =IF(E48="","",E48/10) -> 9.2 | V48: =IF(H48="","",H48/10) | W48: =IF(OR(U48="",V48=""),"",U48-V48) | X48: =IF(OR(U48="",V48=""),"",AVERAGE(U48:V48)) | Y48: =IF(AND(U48<>"",V48<>""),1,0) -> 0 | Z48: =IF(D48<>D47,"",IF(OR(U48="",U47=""),"",U48-U47)) -> 0 | AA48: =IF(D48<>D47,"",IF(OR(V48="",V47=""),"",V48-V47)) | AB48: =IF(B48<>"r04","",IF(COUNT(INDEX(U:U,ROW()-3):U48)<2,"",MAX(INDEX(U:U,ROW()-3):U48)-MIN(INDEX(U:U,ROW()-3):U48))) | AC48: =IF(B48<>"r04","",IF(COUNT(INDEX(V:V,ROW()-3):V48)<2,"",MAX(INDEX(V:V,ROW()-3):V48)-MIN(INDEX(V:V,ROW()-3):V48))) | AD48: =IF(B48<>"r04","",COUNT(INDEX(U:U,ROW()-3):U48)) | AE48: =IF(B48<>"r04","",COUNT(INDEX(V:V,ROW()-3):V48))
A49: 1481 | B49: r04 | C49: 2026-07-13_19-07-57__validacao_tcc_unifal_r04 | D49: 1303403 | E49: 96 | F49: sucesso | G49: 46216.808 | I49: sucesso_sem_nota | J49: 46216.809 | K49: 1 | L49: 0 | M49: parcial | O49: 46216.805 | P49: 46216.809 | Q49: =D49&"|"&B49 -> 1303403|r04 | R49: =VLOOKUP(D49,Base_Amostral!$A:$G,5,FALSE) -> Parintins | S49: =VLOOKUP(D49,Base_Amostral!$A:$G,3,FALSE) -> Amazonas | T49: =VLOOKUP(D49,Base_Amostral!$A:$G,6,FALSE) -> Norte | U49: =IF(E49="","",E49/10) -> 9.6 | V49: =IF(H49="","",H49/10) | W49: =IF(OR(U49="",V49=""),"",U49-V49) | X49: =IF(OR(U49="",V49=""),"",AVERAGE(U49:V49)) | Y49: =IF(AND(U49<>"",V49<>""),1,0) -> 0 | Z49: =IF(D49<>D48,"",IF(OR(U49="",U48=""),"",U49-U48)) -> 0.4 | AA49: =IF(D49<>D48,"",IF(OR(V49="",V48=""),"",V49-V48)) | AB49: =IF(B49<>"r04","",IF(COUNT(INDEX(U:U,ROW()-3):U49)<2,"",MAX(INDEX(U:U,ROW()-3):U49)-MIN(INDEX(U:U,ROW()-3):U49))) -> 0.4 | AC49: =IF(B49<>"r04","",IF(COUNT(INDEX(V:V,ROW()-3):V49)<2,"",MAX(INDEX(V:V,ROW()-3):V49)-MIN(INDEX(V:V,ROW()-3):V49))) | AD49: =IF(B49<>"r04","",COUNT(INDEX(U:U,ROW()-3):U49)) -> 4 | AE49: =IF(B49<>"r04","",COUNT(INDEX(V:V,ROW()-3):V49)) -> 0
A50: 448 | B50: r01 | C50: 2026-06-22_23-12-00__validacao_tcc_unifal_r01 | D50: 1400472 | E50: 58 | F50: sucesso | G50: 46196.001 | H50: 58 | I50: sucesso | J50: 46196.002 | K50: 1 | L50: 1 | M50: completo | O50: 46196 | P50: 46196.002 | Q50: =D50&"|"&B50 -> 1400472|r01 | R50: =VLOOKUP(D50,Base_Amostral!$A:$G,5,FALSE) -> Rorainópolis | S50: =VLOOKUP(D50,Base_Amostral!$A:$G,3,FALSE) -> Roraima | T50: =VLOOKUP(D50,Base_Amostral!$A:$G,6,FALSE) -> Norte | U50: =IF(E50="","",E50/10) -> 5.8 | V50: =IF(H50="","",H50/10) -> 5.8 | W50: =IF(OR(U50="",V50=""),"",U50-V50) -> 0 | X50: =IF(OR(U50="",V50=""),"",AVERAGE(U50:V50)) -> 5.8 | Y50: =IF(AND(U50<>"",V50<>""),1,0) -> 1 | Z50: =IF(D50<>D49,"",IF(OR(U50="",U49=""),"",U50-U49)) | AA50: =IF(D50<>D49,"",IF(OR(V50="",V49=""),"",V50-V49)) | AB50: =IF(B50<>"r04","",IF(COUNT(INDEX(U:U,ROW()-3):U50)<2,"",MAX(INDEX(U:U,ROW()-3):U50)-MIN(INDEX(U:U,ROW()-3):U50))) | AC50: =IF(B50<>"r04","",IF(COUNT(INDEX(V:V,ROW()-3):V50)<2,"",MAX(INDEX(V:V,ROW()-3):V50)-MIN(INDEX(V:V,ROW()-3):V50))) | AD50: =IF(B50<>"r04","",COUNT(INDEX(U:U,ROW()-3):U50)) | AE50: =IF(B50<>"r04","",COUNT(INDEX(V:V,ROW()-3):V50))
A51: 790 | B51: r02 | C51: 2026-06-30_18-34-12__validacao_tcc_unifal_r02 | D51: 1400472 | E51: 59 | F51: sucesso | G51: 46203.802 | H51: 59 | I51: sucesso | J51: 46203.802 | K51: 1 | L51: 1 | M51: completo | O51: 46203.798 | P51: 46203.802 | Q51: =D51&"|"&B51 -> 1400472|r02 | R51: =VLOOKUP(D51,Base_Amostral!$A:$G,5,FALSE) -> Rorainópolis | S51: =VLOOKUP(D51,Base_Amostral!$A:$G,3,FALSE) -> Roraima | T51: =VLOOKUP(D51,Base_Amostral!$A:$G,6,FALSE) -> Norte | U51: =IF(E51="","",E51/10) -> 5.9 | V51: =IF(H51="","",H51/10) -> 5.9 | W51: =IF(OR(U51="",V51=""),"",U51-V51) -> 0 | X51: =IF(OR(U51="",V51=""),"",AVERAGE(U51:V51)) -> 5.9 | Y51: =IF(AND(U51<>"",V51<>""),1,0) -> 1 | Z51: =IF(D51<>D50,"",IF(OR(U51="",U50=""),"",U51-U50)) -> 0.1 | AA51: =IF(D51<>D50,"",IF(OR(V51="",V50=""),"",V51-V50)) -> 0.1 | AB51: =IF(B51<>"r04","",IF(COUNT(INDEX(U:U,ROW()-3):U51)<2,"",MAX(INDEX(U:U,ROW()-3):U51)-MIN(INDEX(U:U,ROW()-3):U51))) | AC51: =IF(B51<>"r04","",IF(COUNT(INDEX(V:V,ROW()-3):V51)<2,"",MAX(INDEX(V:V,ROW()-3):V51)-MIN(INDEX(V:V,ROW()-3):V51))) | AD51: =IF(B51<>"r04","",COUNT(INDEX(U:U,ROW()-3):U51)) | AE51: =IF(B51<>"r04","",COUNT(INDEX(V:V,ROW()-3):V51))
A52: 1156 | B52: r03 | C52: 2026-07-06_19-27-44__validacao_tcc_unifal_r03 | D52: 1400472 | E52: 61 | F52: sucesso | G52: 46209.844 | H52: 60 | I52: sucesso | J52: 46209.844 | K52: 1 | L52: 1 | M52: completo | O52: 46209.843 | P52: 46209.844 | Q52: =D52&"|"&B52 -> 1400472|r03 | R52: =VLOOKUP(D52,Base_Amostral!$A:$G,5,FALSE) -> Rorainópolis | S52: =VLOOKUP(D52,Base_Amostral!$A:$G,3,FALSE) -> Roraima | T52: =VLOOKUP(D52,Base_Amostral!$A:$G,6,FALSE) -> Norte | U52: =IF(E52="","",E52/10) -> 6.1 | V52: =IF(H52="","",H52/10) -> 6 | W52: =IF(OR(U52="",V52=""),"",U52-V52) -> 0.1 | X52: =IF(OR(U52="",V52=""),"",AVERAGE(U52:V52)) -> 6.05 | Y52: =IF(AND(U52<>"",V52<>""),1,0) -> 1 | Z52: =IF(D52<>D51,"",IF(OR(U52="",U51=""),"",U52-U51)) -> 0.2 | AA52: =IF(D52<>D51,"",IF(OR(V52="",V51=""),"",V52-V51)) -> 0.1 | AB52: =IF(B52<>"r04","",IF(COUNT(INDEX(U:U,ROW()-3):U52)<2,"",MAX(INDEX(U:U,ROW()-3):U52)-MIN(INDEX(U:U,ROW()-3):U52))) | AC52: =IF(B52<>"r04","",IF(COUNT(INDEX(V:V,ROW()-3):V52)<2,"",MAX(INDEX(V:V,ROW()-3):V52)-MIN(INDEX(V:V,ROW()-3):V52))) | AD52: =IF(B52<>"r04","",COUNT(INDEX(U:U,ROW()-3):U52)) | AE52: =IF(B52<>"r04","",COUNT(INDEX(V:V,ROW()-3):V52))
A53: 1521 | B53: r04 | C53: 2026-07-13_19-07-57__validacao_tcc_unifal_r04 | D53: 1400472 | E53: 72 | F53: sucesso | G53: 46216.822 | H53: 59 | I53: sucesso | J53: 46216.823 | K53: 1 | L53: 1 | M53: completo | O53: 46216.821 | P53: 46216.823 | Q53: =D53&"|"&B53 -> 1400472|r04 | R53: =VLOOKUP(D53,Base_Amostral!$A:$G,5,FALSE) -> Rorainópolis | S53: =VLOOKUP(D53,Base_Amostral!$A:$G,3,FALSE) -> Roraima | T53: =VLOOKUP(D53,Base_Amostral!$A:$G,6,FALSE) -> Norte | U53: =IF(E53="","",E53/10) -> 7.2 | V53: =IF(H53="","",H53/10) -> 5.9 | W53: =IF(OR(U53="",V53=""),"",U53-V53) -> 1.3 | X53: =IF(OR(U53="",V53=""),"",AVERAGE(U53:V53)) -> 6.55 | Y53: =IF(AND(U53<>"",V53<>""),1,0) -> 1 | Z53: =IF(D53<>D52,"",IF(OR(U53="",U52=""),"",U53-U52)) -> 1.1 | AA53: =IF(D53<>D52,"",IF(OR(V53="",V52=""),"",V53-V52)) -> -0.1 | AB53: =IF(B53<>"r04","",IF(COUNT(INDEX(U:U,ROW()-3):U53)<2,"",MAX(INDEX(U:U,ROW()-3):U53)-MIN(INDEX(U:U,ROW()-3):U53))) -> 1.4 | AC53: =IF(B53<>"r04","",IF(COUNT(INDEX(V:V,ROW()-3):V53)<2,"",MAX(INDEX(V:V,ROW()-3):V53)-MIN(INDEX(V:V,ROW()-3):V53))) -> 0.2 | AD53: =IF(B53<>"r04","",COUNT(INDEX(U:U,ROW()-3):U53)) -> 4 | AE53: =IF(B53<>"r04","",COUNT(INDEX(V:V,ROW()-3):V53)) -> 4
A54: 403 | B54: r01 | C54: 2026-06-22_23-12-00__validacao_tcc_unifal_r01 | D54: 1500107 | F54: falha_de_carregamento | G54: 46195.99 | H54: 60 | I54: sucesso | J54: 46195.99 | K54: 0 | L54: 1 | M54: parcial | O54: 46195.982 | P54: 46195.99 | Q54: =D54&"|"&B54 -> 1500107|r01 | R54: =VLOOKUP(D54,Base_Amostral!$A:$G,5,FALSE) -> Abaetetuba | S54: =VLOOKUP(D54,Base_Amostral!$A:$G,3,FALSE) -> Pará | T54: =VLOOKUP(D54,Base_Amostral!$A:$G,6,FALSE) -> Norte | U54: =IF(E54="","",E54/10) | V54: =IF(H54="","",H54/10) -> 6 | W54: =IF(OR(U54="",V54=""),"",U54-V54) | X54: =IF(OR(U54="",V54=""),"",AVERAGE(U54:V54)) | Y54: =IF(AND(U54<>"",V54<>""),1,0) -> 0 | Z54: =IF(D54<>D53,"",IF(OR(U54="",U53=""),"",U54-U53)) | AA54: =IF(D54<>D53,"",IF(OR(V54="",V53=""),"",V54-V53)) | AB54: =IF(B54<>"r04","",IF(COUNT(INDEX(U:U,ROW()-3):U54)<2,"",MAX(INDEX(U:U,ROW()-3):U54)-MIN(INDEX(U:U,ROW()-3):U54))) | AC54: =IF(B54<>"r04","",IF(COUNT(INDEX(V:V,ROW()-3):V54)<2,"",MAX(INDEX(V:V,ROW()-3):V54)-MIN(INDEX(V:V,ROW()-3):V54))) | AD54: =IF(B54<>"r04","",COUNT(INDEX(U:U,ROW()-3):U54)) | AE54: =IF(B54<>"r04","",COUNT(INDEX(V:V,ROW()-3):V54))
A55: 766 | B55: r02 | C55: 2026-06-30_18-34-12__validacao_tcc_unifal_r02 | D55: 1500107 | E55: 92 | F55: sucesso | G55: 46203.788 | H55: 60 | I55: sucesso | J55: 46203.788 | K55: 1 | L55: 1 | M55: completo | O55: 46203.788 | P55: 46203.788 | Q55: =D55&"|"&B55 -> 1500107|r02 | R55: =VLOOKUP(D55,Base_Amostral!$A:$G,5,FALSE) -> Abaetetuba | S55: =VLOOKUP(D55,Base_Amostral!$A:$G,3,FALSE) -> Pará | T55: =VLOOKUP(D55,Base_Amostral!$A:$G,6,FALSE) -> Norte | U55: =IF(E55="","",E55/10) -> 9.2 | V55: =IF(H55="","",H55/10) -> 6 | W55: =IF(OR(U55="",V55=""),"",U55-V55) -> 3.2 | X55: =IF(OR(U55="",V55=""),"",AVERAGE(U55:V55)) -> 7.6 | Y55: =IF(AND(U55<>"",V55<>""),1,0) -> 1 | Z55: =IF(D55<>D54,"",IF(OR(U55="",U54=""),"",U55-U54)) | AA55: =IF(D55<>D54,"",IF(OR(V55="",V54=""),"",V55-V54)) -> 0 | AB55: =IF(B55<>"r04","",IF(COUNT(INDEX(U:U,ROW()-3):U55)<2,"",MAX(INDEX(U:U,ROW()-3):U55)-MIN(INDEX(U:U,ROW()-3):U55))) | AC55: =IF(B55<>"r04","",IF(COUNT(INDEX(V:V,ROW()-3):V55)<2,"",MAX(INDEX(V:V,ROW()-3):V55)-MIN(INDEX(V:V,ROW()-3):V55))) | AD55: =IF(B55<>"r04","",COUNT(INDEX(U:U,ROW()-3):U55)) | AE55: =IF(B55<>"r04","",COUNT(INDEX(V:V,ROW()-3):V55))
A56: 1128 | B56: r03 | C56: 2026-07-06_19-27-44__validacao_tcc_unifal_r03 | D56: 1500107 | E56: 60 | F56: sucesso | G56: 46209.829 | H56: 60 | I56: sucesso | J56: 46209.829 | K56: 1 | L56: 1 | M56: completo | O56: 46209.829 | P56: 46209.829 | Q56: =D56&"|"&B56 -> 1500107|r03 | R56: =VLOOKUP(D56,Base_Amostral!$A:$G,5,FALSE) -> Abaetetuba | S56: =VLOOKUP(D56,Base_Amostral!$A:$G,3,FALSE) -> Pará | T56: =VLOOKUP(D56,Base_Amostral!$A:$G,6,FALSE) -> Norte | U56: =IF(E56="","",E56/10) -> 6 | V56: =IF(H56="","",H56/10) -> 6 | W56: =IF(OR(U56="",V56=""),"",U56-V56) -> 0 | X56: =IF(OR(U56="",V56=""),"",AVERAGE(U56:V56)) -> 6 | Y56: =IF(AND(U56<>"",V56<>""),1,0) -> 1 | Z56: =IF(D56<>D55,"",IF(OR(U56="",U55=""),"",U56-U55)) -> -3.2 | AA56: =IF(D56<>D55,"",IF(OR(V56="",V55=""),"",V56-V55)) -> 0 | AB56: =IF(B56<>"r04","",IF(COUNT(INDEX(U:U,ROW()-3):U56)<2,"",MAX(INDEX(U:U,ROW()-3):U56)-MIN(INDEX(U:U,ROW()-3):U56))) | AC56: =IF(B56<>"r04","",IF(COUNT(INDEX(V:V,ROW()-3):V56)<2,"",MAX(INDEX(V:V,ROW()-3):V56)-MIN(INDEX(V:V,ROW()-3):V56))) | AD56: =IF(B56<>"r04","",COUNT(INDEX(U:U,ROW()-3):U56)) | AE56: =IF(B56<>"r04","",COUNT(INDEX(V:V,ROW()-3):V56))
A57: 1491 | B57: r04 | C57: 2026-07-13_19-07-57__validacao_tcc_unifal_r04 | D57: 1500107 | E57: 71 | F57: sucesso | G57: 46216.812 | H57: 60 | I57: sucesso | J57: 46216.812 | K57: 1 | L57: 1 | M57: completo | O57: 46216.809 | P57: 46216.812 | Q57: =D57&"|"&B57 -> 1500107|r04 | R57: =VLOOKUP(D57,Base_Amostral!$A:$G,5,FALSE) -> Abaetetuba | S57: =VLOOKUP(D57,Base_Amostral!$A:$G,3,FALSE) -> Pará | T57: =VLOOKUP(D57,Base_Amostral!$A:$G,6,FALSE) -> Norte | U57: =IF(E57="","",E57/10) -> 7.1 | V57: =IF(H57="","",H57/10) -> 6 | W57: =IF(OR(U57="",V57=""),"",U57-V57) -> 1.1 | X57: =IF(OR(U57="",V57=""),"",AVERAGE(U57:V57)) -> 6.55 | Y57: =IF(AND(U57<>"",V57<>""),1,0) -> 1 | Z57: =IF(D57<>D56,"",IF(OR(U57="",U56=""),"",U57-U56)) -> 1.1 | AA57: =IF(D57<>D56,"",IF(OR(V57="",V56=""),"",V57-V56)) -> 0 | AB57: =IF(B57<>"r04","",IF(COUNT(INDEX(U:U,ROW()-3):U57)<2,"",MAX(INDEX(U:U,ROW()-3):U57)-MIN(INDEX(U:U,ROW()-3):U57))) -> 3.2 | AC57: =IF(B57<>"r04","",IF(COUNT(INDEX(V:V,ROW()-3):V57)<2,"",MAX(INDEX(V:V,ROW()-3):V57)-MIN(INDEX(V:V,ROW()-3):V57))) -> 0 | AD57: =IF(B57<>"r04","",COUNT(INDEX(U:U,ROW()-3):U57)) -> 3 | AE57: =IF(B57<>"r04","",COUNT(INDEX(V:V,ROW()-3):V57)) -> 4
A58: 409 | B58: r01 | C58: 2026-06-22_23-12-00__validacao_tcc_unifal_r01 | D58: 1500958 | E58: 62 | F58: sucesso | G58: 46195.992 | H58: 64 | I58: sucesso | J58: 46195.992 | K58: 1 | L58: 1 | M58: completo | O58: 46195.99 | P58: 46195.992 | Q58: =D58&"|"&B58 -> 1500958|r01 | R58: =VLOOKUP(D58,Base_Amostral!$A:$G,5,FALSE) -> Aurora do Pará | S58: =VLOOKUP(D58,Base_Amostral!$A:$G,3,FALSE) -> Pará | T58: =VLOOKUP(D58,Base_Amostral!$A:$G,6,FALSE) -> Norte | U58: =IF(E58="","",E58/10) -> 6.2 | V58: =IF(H58="","",H58/10) -> 6.4 | W58: =IF(OR(U58="",V58=""),"",U58-V58) -> -0.2 | X58: =IF(OR(U58="",V58=""),"",AVERAGE(U58:V58)) -> 6.3 | Y58: =IF(AND(U58<>"",V58<>""),1,0) -> 1 | Z58: =IF(D58<>D57,"",IF(OR(U58="",U57=""),"",U58-U57)) | AA58: =IF(D58<>D57,"",IF(OR(V58="",V57=""),"",V58-V57)) | AB58: =IF(B58<>"r04","",IF(COUNT(INDEX(U:U,ROW()-3):U58)<2,"",MAX(INDEX(U:U,ROW()-3):U58)-MIN(INDEX(U:U,ROW()-3):U58))) | AC58: =IF(B58<>"r04","",IF(COUNT(INDEX(V:V,ROW()-3):V58)<2,"",MAX(INDEX(V:V,ROW()-3):V58)-MIN(INDEX(V:V,ROW()-3):V58))) | AD58: =IF(B58<>"r04","",COUNT(INDEX(U:U,ROW()-3):U58)) | AE58: =IF(B58<>"r04","",COUNT(INDEX(V:V,ROW()-3):V58))
A59: 767 | B59: r02 | C59: 2026-06-30_18-34-12__validacao_tcc_unifal_r02 | D59: 1500958 | E59: 62 | F59: sucesso | G59: 46203.789 | H59: 64 | I59: sucesso | J59: 46203.789 | K59: 1 | L59: 1 | M59: completo | O59: 46203.788 | P59: 46203.789 | Q59: =D59&"|"&B59 -> 1500958|r02 | R59: =VLOOKUP(D59,Base_Amostral!$A:$G,5,FALSE) -> Aurora do Pará | S59: =VLOOKUP(D59,Base_Amostral!$A:$G,3,FALSE) -> Pará | T59: =VLOOKUP(D59,Base_Amostral!$A:$G,6,FALSE) -> Norte | U59: =IF(E59="","",E59/10) -> 6.2 | V59: =IF(H59="","",H59/10) -> 6.4 | W59: =IF(OR(U59="",V59=""),"",U59-V59) -> -0.2 | X59: =IF(OR(U59="",V59=""),"",AVERAGE(U59:V59)) -> 6.3 | Y59: =IF(AND(U59<>"",V59<>""),1,0) -> 1 | Z59: =IF(D59<>D58,"",IF(OR(U59="",U58=""),"",U59-U58)) -> 0 | AA59: =IF(D59<>D58,"",IF(OR(V59="",V58=""),"",V59-V58)) -> 0 | AB59: =IF(B59<>"r04","",IF(COUNT(INDEX(U:U,ROW()-3):U59)<2,"",MAX(INDEX(U:U,ROW()-3):U59)-MIN(INDEX(U:U,ROW()-3):U59))) | AC59: =IF(B59<>"r04","",IF(COUNT(INDEX(V:V,ROW()-3):V59)<2,"",MAX(INDEX(V:V,ROW()-3):V59)-MIN(INDEX(V:V,ROW()-3):V59))) | AD59: =IF(B59<>"r04","",COUNT(INDEX(U:U,ROW()-3):U59)) | AE59: =IF(B59<>"r04","",COUNT(INDEX(V:V,ROW()-3):V59))
A60: 1130 | B60: r03 | C60: 2026-07-06_19-27-44__validacao_tcc_unifal_r03 | D60: 1500958 | E60: 62 | F60: sucesso | G60: 46209.83 | H60: 64 | I60: sucesso | J60: 46209.83 | K60: 1 | L60: 1 | M60: completo | O60: 46209.829 | P60: 46209.83 | Q60: =D60&"|"&B60 -> 1500958|r03 | R60: =VLOOKUP(D60,Base_Amostral!$A:$G,5,FALSE) -> Aurora do Pará | S60: =VLOOKUP(D60,Base_Amostral!$A:$G,3,FALSE) -> Pará | T60: =VLOOKUP(D60,Base_Amostral!$A:$G,6,FALSE) -> Norte | U60: =IF(E60="","",E60/10) -> 6.2 | V60: =IF(H60="","",H60/10) -> 6.4 | W60: =IF(OR(U60="",V60=""),"",U60-V60) -> -0.2 | X60: =IF(OR(U60="",V60=""),"",AVERAGE(U60:V60)) -> 6.3 | Y60: =IF(AND(U60<>"",V60<>""),1,0) -> 1 | Z60: =IF(D60<>D59,"",IF(OR(U60="",U59=""),"",U60-U59)) -> 0 | AA60: =IF(D60<>D59,"",IF(OR(V60="",V59=""),"",V60-V59)) -> 0 | AB60: =IF(B60<>"r04","",IF(COUNT(INDEX(U:U,ROW()-3):U60)<2,"",MAX(INDEX(U:U,ROW()-3):U60)-MIN(INDEX(U:U,ROW()-3):U60))) | AC60: =IF(B60<>"r04","",IF(COUNT(INDEX(V:V,ROW()-3):V60)<2,"",MAX(INDEX(V:V,ROW()-3):V60)-MIN(INDEX(V:V,ROW()-3):V60))) | AD60: =IF(B60<>"r04","",COUNT(INDEX(U:U,ROW()-3):U60)) | AE60: =IF(B60<>"r04","",COUNT(INDEX(V:V,ROW()-3):V60))
A61: 1492 | B61: r04 | C61: 2026-07-13_19-07-57__validacao_tcc_unifal_r04 | D61: 1500958 | E61: 73 | F61: sucesso | G61: 46216.812 | H61: 64 | I61: sucesso | J61: 46216.813 | K61: 1 | L61: 1 | M61: completo | O61: 46216.812 | P61: 46216.813 | Q61: =D61&"|"&B61 -> 1500958|r04 | R61: =VLOOKUP(D61,Base_Amostral!$A:$G,5,FALSE) -> Aurora do Pará | S61: =VLOOKUP(D61,Base_Amostral!$A:$G,3,FALSE) -> Pará | T61: =VLOOKUP(D61,Base_Amostral!$A:$G,6,FALSE) -> Norte | U61: =IF(E61="","",E61/10) -> 7.3 | V61: =IF(H61="","",H61/10) -> 6.4 | W61: =IF(OR(U61="",V61=""),"",U61-V61) -> 0.9 | X61: =IF(OR(U61="",V61=""),"",AVERAGE(U61:V61)) -> 6.85 | Y61: =IF(AND(U61<>"",V61<>""),1,0) -> 1 | Z61: =IF(D61<>D60,"",IF(OR(U61="",U60=""),"",U61-U60)) -> 1.1 | AA61: =IF(D61<>D60,"",IF(OR(V61="",V60=""),"",V61-V60)) -> 0 | AB61: =IF(B61<>"r04","",IF(COUNT(INDEX(U:U,ROW()-3):U61)<2,"",MAX(INDEX(U:U,ROW()-3):U61)-MIN(INDEX(U:U,ROW()-3):U61))) -> 1.1 | AC61: =IF(B61<>"r04","",IF(COUNT(INDEX(V:V,ROW()-3):V61)<2,"",MAX(INDEX(V:V,ROW()-3):V61)-MIN(INDEX(V:V,ROW()-3):V61))) -> 0 | AD61: =IF(B61<>"r04","",COUNT(INDEX(U:U,ROW()-3):U61)) -> 4 | AE61: =IF(B61<>"r04","",COUNT(INDEX(V:V,ROW()-3):V61)) -> 4
A62: 415 | B62: r01 | C62: 2026-06-22_23-12-00__validacao_tcc_unifal_r01 | D62: 1502707 | E62: 92 | F62: sucesso | G62: 46195.992 | H62: 61 | I62: sucesso | J62: 46195.993 | K62: 1 | L62: 1 | M62: completo | O62: 46195.992 | P62: 46195.993 | Q62: =D62&"|"&B62 -> 1502707|r01 | R62: =VLOOKUP(D62,Base_Amostral!$A:$G,5,FALSE) -> Conceição do Araguaia | S62: =VLOOKUP(D62,Base_Amostral!$A:$G,3,FALSE) -> Pará | T62: =VLOOKUP(D62,Base_Amostral!$A:$G,6,FALSE) -> Norte | U62: =IF(E62="","",E62/10) -> 9.2 | V62: =IF(H62="","",H62/10) -> 6.1 | W62: =IF(OR(U62="",V62=""),"",U62-V62) -> 3.1 | X62: =IF(OR(U62="",V62=""),"",AVERAGE(U62:V62)) -> 7.65 | Y62: =IF(AND(U62<>"",V62<>""),1,0) -> 1 | Z62: =IF(D62<>D61,"",IF(OR(U62="",U61=""),"",U62-U61)) | AA62: =IF(D62<>D61,"",IF(OR(V62="",V61=""),"",V62-V61)) | AB62: =IF(B62<>"r04","",IF(COUNT(INDEX(U:U,ROW()-3):U62)<2,"",MAX(INDEX(U:U,ROW()-3):U62)-MIN(INDEX(U:U,ROW()-3):U62))) | AC62: =IF(B62<>"r04","",IF(COUNT(INDEX(V:V,ROW()-3):V62)<2,"",MAX(INDEX(V:V,ROW()-3):V62)-MIN(INDEX(V:V,ROW()-3):V62))) | AD62: =IF(B62<>"r04","",COUNT(INDEX(U:U,ROW()-3):U62)) | AE62: =IF(B62<>"r04","",COUNT(INDEX(V:V,ROW()-3):V62))
A63: 768 | B63: r02 | C63: 2026-06-30_18-34-12__validacao_tcc_unifal_r02 | D63: 1502707 | E63: 92 | F63: sucesso | G63: 46203.789 | H63: 61 | I63: sucesso | J63: 46203.789 | K63: 1 | L63: 1 | M63: completo | O63: 46203.789 | P63: 46203.789 | Q63: =D63&"|"&B63 -> 1502707|r02 | R63: =VLOOKUP(D63,Base_Amostral!$A:$G,5,FALSE) -> Conceição do Araguaia | S63: =VLOOKUP(D63,Base_Amostral!$A:$G,3,FALSE) -> Pará | T63: =VLOOKUP(D63,Base_Amostral!$A:$G,6,FALSE) -> Norte | U63: =IF(E63="","",E63/10) -> 9.2 | V63: =IF(H63="","",H63/10) -> 6.1 | W63: =IF(OR(U63="",V63=""),"",U63-V63) -> 3.1 | X63: =IF(OR(U63="",V63=""),"",AVERAGE(U63:V63)) -> 7.65 | Y63: =IF(AND(U63<>"",V63<>""),1,0) -> 1 | Z63: =IF(D63<>D62,"",IF(OR(U63="",U62=""),"",U63-U62)) -> 0 | AA63: =IF(D63<>D62,"",IF(OR(V63="",V62=""),"",V63-V62)) -> 0 | AB63: =IF(B63<>"r04","",IF(COUNT(INDEX(U:U,ROW()-3):U63)<2,"",MAX(INDEX(U:U,ROW()-3):U63)-MIN(INDEX(U:U,ROW()-3):U63))) | AC63: =IF(B63<>"r04","",IF(COUNT(INDEX(V:V,ROW()-3):V63)<2,"",MAX(INDEX(V:V,ROW()-3):V63)-MIN(INDEX(V:V,ROW()-3):V63))) | AD63: =IF(B63<>"r04","",COUNT(INDEX(U:U,ROW()-3):U63)) | AE63: =IF(B63<>"r04","",COUNT(INDEX(V:V,ROW()-3):V63))
A64: 1132 | B64: r03 | C64: 2026-07-06_19-27-44__validacao_tcc_unifal_r03 | D64: 1502707 | E64: 61 | F64: sucesso | G64: 46209.831 | H64: 61 | I64: sucesso | J64: 46209.831 | K64: 1 | L64: 1 | M64: completo | O64: 46209.83 | P64: 46209.831 | Q64: =D64&"|"&B64 -> 1502707|r03 | R64: =VLOOKUP(D64,Base_Amostral!$A:$G,5,FALSE) -> Conceição do Araguaia | S64: =VLOOKUP(D64,Base_Amostral!$A:$G,3,FALSE) -> Pará | T64: =VLOOKUP(D64,Base_Amostral!$A:$G,6,FALSE) -> Norte | U64: =IF(E64="","",E64/10) -> 6.1 | V64: =IF(H64="","",H64/10) -> 6.1 | W64: =IF(OR(U64="",V64=""),"",U64-V64) -> 0 | X64: =IF(OR(U64="",V64=""),"",AVERAGE(U64:V64)) -> 6.1 | Y64: =IF(AND(U64<>"",V64<>""),1,0) -> 1 | Z64: =IF(D64<>D63,"",IF(OR(U64="",U63=""),"",U64-U63)) -> -3.1 | AA64: =IF(D64<>D63,"",IF(OR(V64="",V63=""),"",V64-V63)) -> 0 | AB64: =IF(B64<>"r04","",IF(COUNT(INDEX(U:U,ROW()-3):U64)<2,"",MAX(INDEX(U:U,ROW()-3):U64)-MIN(INDEX(U:U,ROW()-3):U64))) | AC64: =IF(B64<>"r04","",IF(COUNT(INDEX(V:V,ROW()-3):V64)<2,"",MAX(INDEX(V:V,ROW()-3):V64)-MIN(INDEX(V:V,ROW()-3):V64))) | AD64: =IF(B64<>"r04","",COUNT(INDEX(U:U,ROW()-3):U64)) | AE64: =IF(B64<>"r04","",COUNT(INDEX(V:V,ROW()-3):V64))
A65: 1493 | B65: r04 | C65: 2026-07-13_19-07-57__validacao_tcc_unifal_r04 | D65: 1502707 | E65: 72 | F65: sucesso | G65: 46216.813 | H65: 62 | I65: sucesso | J65: 46216.813 | K65: 1 | L65: 1 | M65: completo | O65: 46216.813 | P65: 46216.813 | Q65: =D65&"|"&B65 -> 1502707|r04 | R65: =VLOOKUP(D65,Base_Amostral!$A:$G,5,FALSE) -> Conceição do Araguaia | S65: =VLOOKUP(D65,Base_Amostral!$A:$G,3,FALSE) -> Pará | T65: =VLOOKUP(D65,Base_Amostral!$A:$G,6,FALSE) -> Norte | U65: =IF(E65="","",E65/10) -> 7.2 | V65: =IF(H65="","",H65/10) -> 6.2 | W65: =IF(OR(U65="",V65=""),"",U65-V65) -> 1 | X65: =IF(OR(U65="",V65=""),"",AVERAGE(U65:V65)) -> 6.7 | Y65: =IF(AND(U65<>"",V65<>""),1,0) -> 1 | Z65: =IF(D65<>D64,"",IF(OR(U65="",U64=""),"",U65-U64)) -> 1.1 | AA65: =IF(D65<>D64,"",IF(OR(V65="",V64=""),"",V65-V64)) -> 0.1 | AB65: =IF(B65<>"r04","",IF(COUNT(INDEX(U:U,ROW()-3):U65)<2,"",MAX(INDEX(U:U,ROW()-3):U65)-MIN(INDEX(U:U,ROW()-3):U65))) -> 3.1 | AC65: =IF(B65<>"r04","",IF(COUNT(INDEX(V:V,ROW()-3):V65)<2,"",MAX(INDEX(V:V,ROW()-3):V65)-MIN(INDEX(V:V,ROW()-3):V65))) -> 0.1 | AD65: =IF(B65<>"r04","",COUNT(INDEX(U:U,ROW()-3):U65)) -> 4 | AE65: =IF(B65<>"r04","",COUNT(INDEX(V:V,ROW()-3):V65)) -> 4
A66: 418 | B66: r01 | C66: 2026-06-22_23-12-00__validacao_tcc_unifal_r01 | D66: 1502939 | E66: 62 | F66: sucesso | G66: 46195.993 | H66: 62 | I66: sucesso | J66: 46195.993 | K66: 1 | L66: 1 | M66: completo | O66: 46195.993 | P66: 46195.993 | Q66: =D66&"|"&B66 -> 1502939|r01 | R66: =VLOOKUP(D66,Base_Amostral!$A:$G,5,FALSE) -> Dom Eliseu | S66: =VLOOKUP(D66,Base_Amostral!$A:$G,3,FALSE) -> Pará | T66: =VLOOKUP(D66,Base_Amostral!$A:$G,6,FALSE) -> Norte | U66: =IF(E66="","",E66/10) -> 6.2 | V66: =IF(H66="","",H66/10) -> 6.2 | W66: =IF(OR(U66="",V66=""),"",U66-V66) -> 0 | X66: =IF(OR(U66="",V66=""),"",AVERAGE(U66:V66)) -> 6.2 | Y66: =IF(AND(U66<>"",V66<>""),1,0) -> 1 | Z66: =IF(D66<>D65,"",IF(OR(U66="",U65=""),"",U66-U65)) | AA66: =IF(D66<>D65,"",IF(OR(V66="",V65=""),"",V66-V65)) | AB66: =IF(B66<>"r04","",IF(COUNT(INDEX(U:U,ROW()-3):U66)<2,"",MAX(INDEX(U:U,ROW()-3):U66)-MIN(INDEX(U:U,ROW()-3):U66))) | AC66: =IF(B66<>"r04","",IF(COUNT(INDEX(V:V,ROW()-3):V66)<2,"",MAX(INDEX(V:V,ROW()-3):V66)-MIN(INDEX(V:V,ROW()-3):V66))) | AD66: =IF(B66<>"r04","",COUNT(INDEX(U:U,ROW()-3):U66)) | AE66: =IF(B66<>"r04","",COUNT(INDEX(V:V,ROW()-3):V66))
... A77: 1503 | B77: r04 | C77: 2026-07-13_19-07-57__validacao_tcc_unifal_r04 | D77: 1505494 | E77: 76 | F77: sucesso | G77: 46216.816 | H77: 66 | I77: sucesso | J77: 46216.816 | K77: 1 | L77: 1 | M77: completo | O77: 46216.815 | P77: 46216.816 | Q77: =D77&"|"&B77 -> 1505494|r04 | R77: =VLOOKUP(D77,Base_Amostral!$A:$G,5,FALSE) -> Palestina do Pará | S77: =VLOOKUP(D77,Base_Amostral!$A:$G,3,FALSE) -> Pará | T77: =VLOOKUP(D77,Base_Amostral!$A:$G,6,FALSE) -> Norte | U77: =IF(E77="","",E77/10) -> 7.6 | V77: =IF(H77="","",H77/10) -> 6.6 | W77: =IF(OR(U77="",V77=""),"",U77-V77) -> 1 | X77: =IF(OR(U77="",V77=""),"",AVERAGE(U77:V77)) -> 7.1 | Y77: =IF(AND(U77<>"",V77<>""),1,0) -> 1 | Z77: =IF(D77<>D76,"",IF(OR(U77="",U76=""),"",U77-U76)) -> 1.1 | AA77: =IF(D77<>D76,"",IF(OR(V77="",V76=""),"",V77-V76)) -> 0 | AB77: =IF(B77<>"r04","",IF(COUNT(INDEX(U:U,ROW()-3):U77)<2,"",MAX(INDEX(U:U,ROW()-3):U77)-MIN(INDEX(U:U,ROW()-3):U77))) -> 1.1 | AC77: =IF(B77<>"r04","",IF(COUNT(INDEX(V:V,ROW()-3):V77)<2,"",MAX(INDEX(V:V,ROW()-3):V77)-MIN(INDEX(V:V,ROW()-3):V77))) -> 0 | AD77: =IF(B77<>"r04","",COUNT(INDEX(U:U,ROW()-3):U77)) -> 4 | AE77: =IF(B77<>"r04","",COUNT(INDEX(V:V,ROW()-3):V77)) -> 4
A78: 370 | B78: r01 | C78: 2026-06-22_23-12-00__validacao_tcc_unifal_r01 | D78: 1600303 | E78: 92 | F78: sucesso | G78: 46195.969 | I78: sucesso_sem_nota | J78: 46195.97 | K78: 1 | L78: 0 | M78: parcial | O78: 46195.969 | P78: 46195.97 | Q78: =D78&"|"&B78 -> 1600303|r01 | R78: =VLOOKUP(D78,Base_Amostral!$A:$G,5,FALSE) -> Macapá | S78: =VLOOKUP(D78,Base_Amostral!$A:$G,3,FALSE) -> Amapá | T78: =VLOOKUP(D78,Base_Amostral!$A:$G,6,FALSE) -> Norte | U78: =IF(E78="","",E78/10) -> 9.2 | V78: =IF(H78="","",H78/10) | W78: =IF(OR(U78="",V78=""),"",U78-V78) | X78: =IF(OR(U78="",V78=""),"",AVERAGE(U78:V78)) | Y78: =IF(AND(U78<>"",V78<>""),1,0) -> 0 | Z78: =IF(D78<>D77,"",IF(OR(U78="",U77=""),"",U78-U77)) | AA78: =IF(D78<>D77,"",IF(OR(V78="",V77=""),"",V78-V77)) | AB78: =IF(B78<>"r04","",IF(COUNT(INDEX(U:U,ROW()-3):U78)<2,"",MAX(INDEX(U:U,ROW()-3):U78)-MIN(INDEX(U:U,ROW()-3):U78))) | AC78: =IF(B78<>"r04","",IF(COUNT(INDEX(V:V,ROW()-3):V78)<2,"",MAX(INDEX(V:V,ROW()-3):V78)-MIN(INDEX(V:V,ROW()-3):V78))) | AD78: =IF(B78<>"r04","",COUNT(INDEX(U:U,ROW()-3):U78)) | AE78: =IF(B78<>"r04","",COUNT(INDEX(V:V,ROW()-3):V78))
A79: 739 | B79: r02 | C79: 2026-06-30_18-34-12__validacao_tcc_unifal_r02 | D79: 1600303 | E79: 92 | F79: sucesso | G79: 46203.779 | I79: sucesso_sem_nota | J79: 46203.78 | K79: 1 | L79: 0 | M79: parcial | O79: 46203.779 | P79: 46203.78 | Q79: =D79&"|"&B79 -> 1600303|r02 | R79: =VLOOKUP(D79,Base_Amostral!$A:$G,5,FALSE) -> Macapá | S79: =VLOOKUP(D79,Base_Amostral!$A:$G,3,FALSE) -> Amapá | T79: =VLOOKUP(D79,Base_Amostral!$A:$G,6,FALSE) -> Norte | U79: =IF(E79="","",E79/10) -> 9.2 | V79: =IF(H79="","",H79/10) | W79: =IF(OR(U79="",V79=""),"",U79-V79) | X79: =IF(OR(U79="",V79=""),"",AVERAGE(U79:V79)) | Y79: =IF(AND(U79<>"",V79<>""),1,0) -> 0 | Z79: =IF(D79<>D78,"",IF(OR(U79="",U78=""),"",U79-U78)) -> 0 | AA79: =IF(D79<>D78,"",IF(OR(V79="",V78=""),"",V79-V78)) | AB79: =IF(B79<>"r04","",IF(COUNT(INDEX(U:U,ROW()-3):U79)<2,"",MAX(INDEX(U:U,ROW()-3):U79)-MIN(INDEX(U:U,ROW()-3):U79))) | AC79: =IF(B79<>"r04","",IF(COUNT(INDEX(V:V,ROW()-3):V79)<2,"",MAX(INDEX(V:V,ROW()-3):V79)-MIN(INDEX(V:V,ROW()-3):V79))) | AD79: =IF(B79<>"r04","",COUNT(INDEX(U:U,ROW()-3):U79)) | AE79: =IF(B79<>"r04","",COUNT(INDEX(V:V,ROW()-3):V79))
A80: 1097 | B80: r03 | C80: 2026-07-06_19-27-44__validacao_tcc_unifal_r03 | D80: 1600303 | F80: falha_de_carregamento | G80: 46209.822 | I80: sucesso_sem_nota | J80: 46209.823 | K80: 0 | L80: 0 | M80: falha_total | O80: 46209.815 | P80: 46209.823 | Q80: =D80&"|"&B80 -> 1600303|r03 | R80: =VLOOKUP(D80,Base_Amostral!$A:$G,5,FALSE) -> Macapá | S80: =VLOOKUP(D80,Base_Amostral!$A:$G,3,FALSE) -> Amapá | T80: =VLOOKUP(D80,Base_Amostral!$A:$G,6,FALSE) -> Norte | U80: =IF(E80="","",E80/10) | V80: =IF(H80="","",H80/10) | W80: =IF(OR(U80="",V80=""),"",U80-V80) | X80: =IF(OR(U80="",V80=""),"",AVERAGE(U80:V80)) | Y80: =IF(AND(U80<>"",V80<>""),1,0) -> 0 | Z80: =IF(D80<>D79,"",IF(OR(U80="",U79=""),"",U80-U79)) | AA80: =IF(D80<>D79,"",IF(OR(V80="",V79=""),"",V80-V79)) | AB80: =IF(B80<>"r04","",IF(COUNT(INDEX(U:U,ROW()-3):U80)<2,"",MAX(INDEX(U:U,ROW()-3):U80)-MIN(INDEX(U:U,ROW()-3):U80))) | AC80: =IF(B80<>"r04","",IF(COUNT(INDEX(V:V,ROW()-3):V80)<2,"",MAX(INDEX(V:V,ROW()-3):V80)-MIN(INDEX(V:V,ROW()-3):V80))) | AD80: =IF(B80<>"r04","",COUNT(INDEX(U:U,ROW()-3):U80)) | AE80: =IF(B80<>"r04","",COUNT(INDEX(V:V,ROW()-3):V80))
A81: 1457 | B81: r04 | C81: 2026-07-13_19-07-57__validacao_tcc_unifal_r04 | D81: 1600303 | E81: 82 | F81: sucesso | G81: 46216.8 | I81: sucesso_sem_nota | J81: 46216.801 | K81: 1 | L81: 0 | M81: parcial | O81: 46216.799 | P81: 46216.801 | Q81: =D81&"|"&B81 -> 1600303|r04 | R81: =VLOOKUP(D81,Base_Amostral!$A:$G,5,FALSE) -> Macapá | S81: =VLOOKUP(D81,Base_Amostral!$A:$G,3,FALSE) -> Amapá | T81: =VLOOKUP(D81,Base_Amostral!$A:$G,6,FALSE) -> Norte | U81: =IF(E81="","",E81/10) -> 8.2 | V81: =IF(H81="","",H81/10) | W81: =IF(OR(U81="",V81=""),"",U81-V81) | X81: =IF(OR(U81="",V81=""),"",AVERAGE(U81:V81)) | Y81: =IF(AND(U81<>"",V81<>""),1,0) -> 0 | Z81: =IF(D81<>D80,"",IF(OR(U81="",U80=""),"",U81-U80)) | AA81: =IF(D81<>D80,"",IF(OR(V81="",V80=""),"",V81-V80)) | AB81: =IF(B81<>"r04","",IF(COUNT(INDEX(U:U,ROW()-3):U81)<2,"",MAX(INDEX(U:U,ROW()-3):U81)-MIN(INDEX(U:U,ROW()-3):U81))) -> 1 | AC81: =IF(B81<>"r04","",IF(COUNT(INDEX(V:V,ROW()-3):V81)<2,"",MAX(INDEX(V:V,ROW()-3):V81)-MIN(INDEX(V:V,ROW()-3):V81))) | AD81: =IF(B81<>"r04","",COUNT(INDEX(U:U,ROW()-3):U81)) -> 3 | AE81: =IF(B81<>"r04","",COUNT(INDEX(V:V,ROW()-3):V81)) -> 0
A82: 374 | B82: r01 | C82: 2026-06-22_23-12-00__validacao_tcc_unifal_r01 | D82: 1600550 | E82: 65 | F82: sucesso | G82: 46195.97 | H82: 68 | I82: sucesso | J82: 46195.97 | K82: 1 | L82: 1 | M82: completo | O82: 46195.97 | P82: 46195.97 | Q82: =D82&"|"&B82 -> 1600550|r01 | R82: =VLOOKUP(D82,Base_Amostral!$A:$G,5,FALSE) -> Pracuúba | S82: =VLOOKUP(D82,Base_Amostral!$A:$G,3,FALSE) -> Amapá | T82: =VLOOKUP(D82,Base_Amostral!$A:$G,6,FALSE) -> Norte | U82: =IF(E82="","",E82/10) -> 6.5 | V82: =IF(H82="","",H82/10) -> 6.8 | W82: =IF(OR(U82="",V82=""),"",U82-V82) -> -0.3 | X82: =IF(OR(U82="",V82=""),"",AVERAGE(U82:V82)) -> 6.65 | Y82: =IF(AND(U82<>"",V82<>""),1,0) -> 1 | Z82: =IF(D82<>D81,"",IF(OR(U82="",U81=""),"",U82-U81)) | AA82: =IF(D82<>D81,"",IF(OR(V82="",V81=""),"",V82-V81)) | AB82: =IF(B82<>"r04","",IF(COUNT(INDEX(U:U,ROW()-3):U82)<2,"",MAX(INDEX(U:U,ROW()-3):U82)-MIN(INDEX(U:U,ROW()-3):U82))) | AC82: =IF(B82<>"r04","",IF(COUNT(INDEX(V:V,ROW()-3):V82)<2,"",MAX(INDEX(V:V,ROW()-3):V82)-MIN(INDEX(V:V,ROW()-3):V82))) | AD82: =IF(B82<>"r04","",COUNT(INDEX(U:U,ROW()-3):U82)) | AE82: =IF(B82<>"r04","",COUNT(INDEX(V:V,ROW()-3):V82))
A83: 744 | B83: r02 | C83: 2026-06-30_18-34-12__validacao_tcc_unifal_r02 | D83: 1600550 | E83: 65 | F83: sucesso | G83: 46203.78 | H83: 68 | I83: sucesso | J83: 46203.781 | K83: 1 | L83: 1 | M83: completo | O83: 46203.78 | P83: 46203.781 | Q83: =D83&"|"&B83 -> 1600550|r02 | R83: =VLOOKUP(D83,Base_Amostral!$A:$G,5,FALSE) -> Pracuúba | S83: =VLOOKUP(D83,Base_Amostral!$A:$G,3,FALSE) -> Amapá | T83: =VLOOKUP(D83,Base_Amostral!$A:$G,6,FALSE) -> Norte | U83: =IF(E83="","",E83/10) -> 6.5 | V83: =IF(H83="","",H83/10) -> 6.8 | W83: =IF(OR(U83="",V83=""),"",U83-V83) -> -0.3 | X83: =IF(OR(U83="",V83=""),"",AVERAGE(U83:V83)) -> 6.65 | Y83: =IF(AND(U83<>"",V83<>""),1,0) -> 1 | Z83: =IF(D83<>D82,"",IF(OR(U83="",U82=""),"",U83-U82)) -> 0 | AA83: =IF(D83<>D82,"",IF(OR(V83="",V82=""),"",V83-V82)) -> 0 | AB83: =IF(B83<>"r04","",IF(COUNT(INDEX(U:U,ROW()-3):U83)<2,"",MAX(INDEX(U:U,ROW()-3):U83)-MIN(INDEX(U:U,ROW()-3):U83))) | AC83: =IF(B83<>"r04","",IF(COUNT(INDEX(V:V,ROW()-3):V83)<2,"",MAX(INDEX(V:V,ROW()-3):V83)-MIN(INDEX(V:V,ROW()-3):V83))) | AD83: =IF(B83<>"r04","",COUNT(INDEX(U:U,ROW()-3):U83)) | AE83: =IF(B83<>"r04","",COUNT(INDEX(V:V,ROW()-3):V83))
A84: 1117 | B84: r03 | C84: 2026-07-06_19-27-44__validacao_tcc_unifal_r03 | D84: 1600550 | E84: 65 | F84: sucesso | G84: 46209.824 | H84: 68 | I84: sucesso | J84: 46209.824 | K84: 1 | L84: 1 | M84: completo | O84: 46209.823 | P84: 46209.824 | Q84: =D84&"|"&B84 -> 1600550|r03 | R84: =VLOOKUP(D84,Base_Amostral!$A:$G,5,FALSE) -> Pracuúba | S84: =VLOOKUP(D84,Base_Amostral!$A:$G,3,FALSE) -> Amapá | T84: =VLOOKUP(D84,Base_Amostral!$A:$G,6,FALSE) -> Norte | U84: =IF(E84="","",E84/10) -> 6.5 | V84: =IF(H84="","",H84/10) -> 6.8 | W84: =IF(OR(U84="",V84=""),"",U84-V84) -> -0.3 | X84: =IF(OR(U84="",V84=""),"",AVERAGE(U84:V84)) -> 6.65 | Y84: =IF(AND(U84<>"",V84<>""),1,0) -> 1 | Z84: =IF(D84<>D83,"",IF(OR(U84="",U83=""),"",U84-U83)) -> 0 | AA84: =IF(D84<>D83,"",IF(OR(V84="",V83=""),"",V84-V83)) -> 0 | AB84: =IF(B84<>"r04","",IF(COUNT(INDEX(U:U,ROW()-3):U84)<2,"",MAX(INDEX(U:U,ROW()-3):U84)-MIN(INDEX(U:U,ROW()-3):U84))) | AC84: =IF(B84<>"r04","",IF(COUNT(INDEX(V:V,ROW()-3):V84)<2,"",MAX(INDEX(V:V,ROW()-3):V84)-MIN(INDEX(V:V,ROW()-3):V84))) | AD84: =IF(B84<>"r04","",COUNT(INDEX(U:U,ROW()-3):U84)) | AE84: =IF(B84<>"r04","",COUNT(INDEX(V:V,ROW()-3):V84))
A85: 1461 | B85: r04 | C85: 2026-07-13_19-07-57__validacao_tcc_unifal_r04 | D85: 1600550 | E85: 77 | F85: sucesso | G85: 46216.801 | H85: 68 | I85: sucesso | J85: 46216.802 | K85: 1 | L85: 1 | M85: completo | O85: 46216.801 | P85: 46216.802 | Q85: =D85&"|"&B85 -> 1600550|r04 | R85: =VLOOKUP(D85,Base_Amostral!$A:$G,5,FALSE) -> Pracuúba | S85: =VLOOKUP(D85,Base_Amostral!$A:$G,3,FALSE) -> Amapá | T85: =VLOOKUP(D85,Base_Amostral!$A:$G,6,FALSE) -> Norte | U85: =IF(E85="","",E85/10) -> 7.7 | V85: =IF(H85="","",H85/10) -> 6.8 | W85: =IF(OR(U85="",V85=""),"",U85-V85) -> 0.9 | X85: =IF(OR(U85="",V85=""),"",AVERAGE(U85:V85)) -> 7.25 | Y85: =IF(AND(U85<>"",V85<>""),1,0) -> 1 | Z85: =IF(D85<>D84,"",IF(OR(U85="",U84=""),"",U85-U84)) -> 1.2 | AA85: =IF(D85<>D84,"",IF(OR(V85="",V84=""),"",V85-V84)) -> 0 | AB85: =IF(B85<>"r04","",IF(COUNT(INDEX(U:U,ROW()-3):U85)<2,"",MAX(INDEX(U:U,ROW()-3):U85)-MIN(INDEX(U:U,ROW()-3):U85))) -> 1.2 | AC85: =IF(B85<>"r04","",IF(COUNT(INDEX(V:V,ROW()-3):V85)<2,"",MAX(INDEX(V:V,ROW()-3):V85)-MIN(INDEX(V:V,ROW()-3):V85))) -> 0 | AD85: =IF(B85<>"r04","",COUNT(INDEX(U:U,ROW()-3):U85)) -> 4 | AE85: =IF(B85<>"r04","",COUNT(INDEX(V:V,ROW()-3):V85)) -> 4
A86: 377 | B86: r01 | C86: 2026-06-22_23-12-00__validacao_tcc_unifal_r01 | D86: 1600709 | E86: 59 | F86: sucesso | G86: 46195.971 | H86: 66 | I86: sucesso | J86: 46195.971 | K86: 1 | L86: 1 | M86: completo | O86: 46195.97 | P86: 46195.971 | Q86: =D86&"|"&B86 -> 1600709|r01 | R86: =VLOOKUP(D86,Base_Amostral!$A:$G,5,FALSE) -> Tartarugalzinho | S86: =VLOOKUP(D86,Base_Amostral!$A:$G,3,FALSE) -> Amapá | T86: =VLOOKUP(D86,Base_Amostral!$A:$G,6,FALSE) -> Norte | U86: =IF(E86="","",E86/10) -> 5.9 | V86: =IF(H86="","",H86/10) -> 6.6 | W86: =IF(OR(U86="",V86=""),"",U86-V86) -> -0.7 | X86: =IF(OR(U86="",V86=""),"",AVERAGE(U86:V86)) -> 6.25 | Y86: =IF(AND(U86<>"",V86<>""),1,0) -> 1 | Z86: =IF(D86<>D85,"",IF(OR(U86="",U85=""),"",U86-U85)) | AA86: =IF(D86<>D85,"",IF(OR(V86="",V85=""),"",V86-V85)) | AB86: =IF(B86<>"r04","",IF(COUNT(INDEX(U:U,ROW()-3):U86)<2,"",MAX(INDEX(U:U,ROW()-3):U86)-MIN(INDEX(U:U,ROW()-3):U86))) | AC86: =IF(B86<>"r04","",IF(COUNT(INDEX(V:V,ROW()-3):V86)<2,"",MAX(INDEX(V:V,ROW()-3):V86)-MIN(INDEX(V:V,ROW()-3):V86))) | AD86: =IF(B86<>"r04","",COUNT(INDEX(U:U,ROW()-3):U86)) | AE86: =IF(B86<>"r04","",COUNT(INDEX(V:V,ROW()-3):V86))
A87: 747 | B87: r02 | C87: 2026-06-30_18-34-12__validacao_tcc_unifal_r02 | D87: 1600709 | E87: 59 | F87: sucesso | G87: 46203.781 | H87: 66 | I87: sucesso | J87: 46203.781 | K87: 1 | L87: 1 | M87: completo | O87: 46203.781 | P87: 46203.781 | Q87: =D87&"|"&B87 -> 1600709|r02 | R87: =VLOOKUP(D87,Base_Amostral!$A:$G,5,FALSE) -> Tartarugalzinho | S87: =VLOOKUP(D87,Base_Amostral!$A:$G,3,FALSE) -> Amapá | T87: =VLOOKUP(D87,Base_Amostral!$A:$G,6,FALSE) -> Norte | U87: =IF(E87="","",E87/10) -> 5.9 | V87: =IF(H87="","",H87/10) -> 6.6 | W87: =IF(OR(U87="",V87=""),"",U87-V87) -> -0.7 | X87: =IF(OR(U87="",V87=""),"",AVERAGE(U87:V87)) -> 6.25 | Y87: =IF(AND(U87<>"",V87<>""),1,0) -> 1 | Z87: =IF(D87<>D86,"",IF(OR(U87="",U86=""),"",U87-U86)) -> 0 | AA87: =IF(D87<>D86,"",IF(OR(V87="",V86=""),"",V87-V86)) -> 0 | AB87: =IF(B87<>"r04","",IF(COUNT(INDEX(U:U,ROW()-3):U87)<2,"",MAX(INDEX(U:U,ROW()-3):U87)-MIN(INDEX(U:U,ROW()-3):U87))) | AC87: =IF(B87<>"r04","",IF(COUNT(INDEX(V:V,ROW()-3):V87)<2,"",MAX(INDEX(V:V,ROW()-3):V87)-MIN(INDEX(V:V,ROW()-3):V87))) | AD87: =IF(B87<>"r04","",COUNT(INDEX(U:U,ROW()-3):U87)) | AE87: =IF(B87<>"r04","",COUNT(INDEX(V:V,ROW()-3):V87))
A88: 1119 | B88: r03 | C88: 2026-07-06_19-27-44__validacao_tcc_unifal_r03 | D88: 1600709 | E88: 59 | F88: sucesso | G88: 46209.825 | H88: 66 | I88: sucesso | J88: 46209.825 | K88: 1 | L88: 1 | M88: completo | O88: 46209.825 | P88: 46209.825 | Q88: =D88&"|"&B88 -> 1600709|r03 | R88: =VLOOKUP(D88,Base_Amostral!$A:$G,5,FALSE) -> Tartarugalzinho | S88: =VLOOKUP(D88,Base_Amostral!$A:$G,3,FALSE) -> Amapá | T88: =VLOOKUP(D88,Base_Amostral!$A:$G,6,FALSE) -> Norte | U88: =IF(E88="","",E88/10) -> 5.9 | V88: =IF(H88="","",H88/10) -> 6.6 | W88: =IF(OR(U88="",V88=""),"",U88-V88) -> -0.7 | X88: =IF(OR(U88="",V88=""),"",AVERAGE(U88:V88)) -> 6.25 | Y88: =IF(AND(U88<>"",V88<>""),1,0) -> 1 | Z88: =IF(D88<>D87,"",IF(OR(U88="",U87=""),"",U88-U87)) -> 0 | AA88: =IF(D88<>D87,"",IF(OR(V88="",V87=""),"",V88-V87)) -> 0 | AB88: =IF(B88<>"r04","",IF(COUNT(INDEX(U:U,ROW()-3):U88)<2,"",MAX(INDEX(U:U,ROW()-3):U88)-MIN(INDEX(U:U,ROW()-3):U88))) | AC88: =IF(B88<>"r04","",IF(COUNT(INDEX(V:V,ROW()-3):V88)<2,"",MAX(INDEX(V:V,ROW()-3):V88)-MIN(INDEX(V:V,ROW()-3):V88))) | AD88: =IF(B88<>"r04","",COUNT(INDEX(U:U,ROW()-3):U88)) | AE88: =IF(B88<>"r04","",COUNT(INDEX(V:V,ROW()-3):V88))
A89: 1466 | B89: r04 | C89: 2026-07-13_19-07-57__validacao_tcc_unifal_r04 | D89: 1600709 | E89: 72 | F89: sucesso | G89: 46216.802 | H89: 66 | I89: sucesso | J89: 46216.803 | K89: 1 | L89: 1 | M89: completo | O89: 46216.802 | P89: 46216.803 | Q89: =D89&"|"&B89 -> 1600709|r04 | R89: =VLOOKUP(D89,Base_Amostral!$A:$G,5,FALSE) -> Tartarugalzinho | S89: =VLOOKUP(D89,Base_Amostral!$A:$G,3,FALSE) -> Amapá | T89: =VLOOKUP(D89,Base_Amostral!$A:$G,6,FALSE) -> Norte | U89: =IF(E89="","",E89/10) -> 7.2 | V89: =IF(H89="","",H89/10) -> 6.6 | W89: =IF(OR(U89="",V89=""),"",U89-V89) -> 0.6 | X89: =IF(OR(U89="",V89=""),"",AVERAGE(U89:V89)) -> 6.9 | Y89: =IF(AND(U89<>"",V89<>""),1,0) -> 1 | Z89: =IF(D89<>D88,"",IF(OR(U89="",U88=""),"",U89-U88)) -> 1.3 | AA89: =IF(D89<>D88,"",IF(OR(V89="",V88=""),"",V89-V88)) -> 0 | AB89: =IF(B89<>"r04","",IF(COUNT(INDEX(U:U,ROW()-3):U89)<2,"",MAX(INDEX(U:U,ROW()-3):U89)-MIN(INDEX(U:U,ROW()-3):U89))) -> 1.3 | AC89: =IF(B89<>"r04","",IF(COUNT(INDEX(V:V,ROW()-3):V89)<2,"",MAX(INDEX(V:V,ROW()-3):V89)-MIN(INDEX(V:V,ROW()-3):V89))) -> 0 | AD89: =IF(B89<>"r04","",COUNT(INDEX(U:U,ROW()-3):U89)) -> 4 | AE89: =IF(B89<>"r04","",COUNT(INDEX(V:V,ROW()-3):V89)) -> 4
A90: 451 | B90: r01 | C90: 2026-06-22_23-12-00__validacao_tcc_unifal_r01 | D90: 1702208 | E90: 56 | F90: sucesso | G90: 46196.002 | H90: 61 | I90: sucesso | J90: 46196.003 | K90: 1 | L90: 1 | M90: completo | O90: 46196.002 | P90: 46196.003 | Q90: =D90&"|"&B90 -> 1702208|r01 | R90: =VLOOKUP(D90,Base_Amostral!$A:$G,5,FALSE) -> Araguatins | S90: =VLOOKUP(D90,Base_Amostral!$A:$G,3,FALSE) -> Tocantins | T90: =VLOOKUP(D90,Base_Amostral!$A:$G,6,FALSE) -> Norte | U90: =IF(E90="","",E90/10) -> 5.6 | V90: =IF(H90="","",H90/10) -> 6.1 | W90: =IF(OR(U90="",V90=""),"",U90-V90) -> -0.5 | X90: =IF(OR(U90="",V90=""),"",AVERAGE(U90:V90)) -> 5.85 | Y90: =IF(AND(U90<>"",V90<>""),1,0) -> 1 | Z90: =IF(D90<>D89,"",IF(OR(U90="",U89=""),"",U90-U89)) | AA90: =IF(D90<>D89,"",IF(OR(V90="",V89=""),"",V90-V89)) | AB90: =IF(B90<>"r04","",IF(COUNT(INDEX(U:U,ROW()-3):U90)<2,"",MAX(INDEX(U:U,ROW()-3):U90)-MIN(INDEX(U:U,ROW()-3):U90))) | AC90: =IF(B90<>"r04","",IF(COUNT(INDEX(V:V,ROW()-3):V90)<2,"",MAX(INDEX(V:V,ROW()-3):V90)-MIN(INDEX(V:V,ROW()-3):V90))) | AD90: =IF(B90<>"r04","",COUNT(INDEX(U:U,ROW()-3):U90)) | AE90: =IF(B90<>"r04","",COUNT(INDEX(V:V,ROW()-3):V90))
A91: 802 | B91: r02 | C91: 2026-06-30_18-34-12__validacao_tcc_unifal_r02 | D91: 1702208 | E91: 56 | F91: sucesso | G91: 46203.803 | H91: 61 | I91: sucesso | J91: 46203.804 | K91: 1 | L91: 1 | M91: completo | O91: 46203.802 | P91: 46203.804 | Q91: =D91&"|"&B91 -> 1702208|r02 | R91: =VLOOKUP(D91,Base_Amostral!$A:$G,5,FALSE) -> Araguatins | S91: =VLOOKUP(D91,Base_Amostral!$A:$G,3,FALSE) -> Tocantins | T91: =VLOOKUP(D91,Base_Amostral!$A:$G,6,FALSE) -> Norte | U91: =IF(E91="","",E91/10) -> 5.6 | V91: =IF(H91="","",H91/10) -> 6.1 | W91: =IF(OR(U91="",V91=""),"",U91-V91) -> -0.5 | X91: =IF(OR(U91="",V91=""),"",AVERAGE(U91:V91)) -> 5.85 | Y91: =IF(AND(U91<>"",V91<>""),1,0) -> 1 | Z91: =IF(D91<>D90,"",IF(OR(U91="",U90=""),"",U91-U90)) -> 0 | AA91: =IF(D91<>D90,"",IF(OR(V91="",V90=""),"",V91-V90)) -> 0 | AB91: =IF(B91<>"r04","",IF(COUNT(INDEX(U:U,ROW()-3):U91)<2,"",MAX(INDEX(U:U,ROW()-3):U91)-MIN(INDEX(U:U,ROW()-3):U91))) | AC91: =IF(B91<>"r04","",IF(COUNT(INDEX(V:V,ROW()-3):V91)<2,"",MAX(INDEX(V:V,ROW()-3):V91)-MIN(INDEX(V:V,ROW()-3):V91))) | AD91: =IF(B91<>"r04","",COUNT(INDEX(U:U,ROW()-3):U91)) | AE91: =IF(B91<>"r04","",COUNT(INDEX(V:V,ROW()-3):V91))
A92: 1160 | B92: r03 | C92: 2026-07-06_19-27-44__validacao_tcc_unifal_r03 | D92: 1702208 | E92: 56 | F92: sucesso | G92: 46209.845 | H92: 61 | I92: sucesso | J92: 46209.845 | K92: 1 | L92: 1 | M92: completo | O92: 46209.844 | P92: 46209.845 | Q92: =D92&"|"&B92 -> 1702208|r03 | R92: =VLOOKUP(D92,Base_Amostral!$A:$G,5,FALSE) -> Araguatins | S92: =VLOOKUP(D92,Base_Amostral!$A:$G,3,FALSE) -> Tocantins | T92: =VLOOKUP(D92,Base_Amostral!$A:$G,6,FALSE) -> Norte | U92: =IF(E92="","",E92/10) -> 5.6 | V92: =IF(H92="","",H92/10) -> 6.1 | W92: =IF(OR(U92="",V92=""),"",U92-V92) -> -0.5 | X92: =IF(OR(U92="",V92=""),"",AVERAGE(U92:V92)) -> 5.85 | Y92: =IF(AND(U92<>"",V92<>""),1,0) -> 1 | Z92: =IF(D92<>D91,"",IF(OR(U92="",U91=""),"",U92-U91)) -> 0 | AA92: =IF(D92<>D91,"",IF(OR(V92="",V91=""),"",V92-V91)) -> 0 | AB92: =IF(B92<>"r04","",IF(COUNT(INDEX(U:U,ROW()-3):U92)<2,"",MAX(INDEX(U:U,ROW()-3):U92)-MIN(INDEX(U:U,ROW()-3):U92))) | AC92: =IF(B92<>"r04","",IF(COUNT(INDEX(V:V,ROW()-3):V92)<2,"",MAX(INDEX(V:V,ROW()-3):V92)-MIN(INDEX(V:V,ROW()-3):V92))) | AD92: =IF(B92<>"r04","",COUNT(INDEX(U:U,ROW()-3):U92)) | AE92: =IF(B92<>"r04","",COUNT(INDEX(V:V,ROW()-3):V92))
A93: 1525 | B93: r04 | C93: 2026-07-13_19-07-57__validacao_tcc_unifal_r04 | D93: 1702208 | E93: 96 | F93: sucesso | G93: 46216.823 | H93: 61 | I93: sucesso | J93: 46216.823 | K93: 1 | L93: 1 | M93: completo | O93: 46216.823 | P93: 46216.823 | Q93: =D93&"|"&B93 -> 1702208|r04 | R93: =VLOOKUP(D93,Base_Amostral!$A:$G,5,FALSE) -> Araguatins | S93: =VLOOKUP(D93,Base_Amostral!$A:$G,3,FALSE) -> Tocantins | T93: =VLOOKUP(D93,Base_Amostral!$A:$G,6,FALSE) -> Norte | U93: =IF(E93="","",E93/10) -> 9.6 | V93: =IF(H93="","",H93/10) -> 6.1 | W93: =IF(OR(U93="",V93=""),"",U93-V93) -> 3.5 | X93: =IF(OR(U93="",V93=""),"",AVERAGE(U93:V93)) -> 7.85 | Y93: =IF(AND(U93<>"",V93<>""),1,0) -> 1 | Z93: =IF(D93<>D92,"",IF(OR(U93="",U92=""),"",U93-U92)) -> 4 | AA93: =IF(D93<>D92,"",IF(OR(V93="",V92=""),"",V93-V92)) -> 0 | AB93: =IF(B93<>"r04","",IF(COUNT(INDEX(U:U,ROW()-3):U93)<2,"",MAX(INDEX(U:U,ROW()-3):U93)-MIN(INDEX(U:U,ROW()-3):U93))) -> 4 | AC93: =IF(B93<>"r04","",IF(COUNT(INDEX(V:V,ROW()-3):V93)<2,"",MAX(INDEX(V:V,ROW()-3):V93)-MIN(INDEX(V:V,ROW()-3):V93))) -> 0 | AD93: =IF(B93<>"r04","",COUNT(INDEX(U:U,ROW()-3):U93)) -> 4 | AE93: =IF(B93<>"r04","",COUNT(INDEX(V:V,ROW()-3):V93)) -> 4
... A113: 1537 | B113: r04 | C113: 2026-07-13_19-07-57__validacao_tcc_unifal_r04 | D113: 1718808 | E113: 77 | F113: sucesso | G113: 46216.827 | H113: 69 | I113: sucesso | J113: 46216.827 | K113: 1 | L113: 1 | M113: completo | O113: 46216.827 | P113: 46216.827 | Q113: =D113&"|"&B113 -> 1718808|r04 | R113: =VLOOKUP(D113,Base_Amostral!$A:$G,5,FALSE) -> Sampaio | S113: =VLOOKUP(D113,Base_Amostral!$A:$G,3,FALSE) -> Tocantins | T113: =VLOOKUP(D113,Base_Amostral!$A:$G,6,FALSE) -> Norte | U113: =IF(E113="","",E113/10) -> 7.7 | V113: =IF(H113="","",H113/10) -> 6.9 | W113: =IF(OR(U113="",V113=""),"",U113-V113) -> 0.8 | X113: =IF(OR(U113="",V113=""),"",AVERAGE(U113:V113)) -> 7.3 | Y113: =IF(AND(U113<>"",V113<>""),1,0) -> 1 | Z113: =IF(D113<>D112,"",IF(OR(U113="",U112=""),"",U113-U112)) -> 0.8 | AA113: =IF(D113<>D112,"",IF(OR(V113="",V112=""),"",V113-V112)) -> 0 | AB113: =IF(B113<>"r04","",IF(COUNT(INDEX(U:U,ROW()-3):U113)<2,"",MAX(INDEX(U:U,ROW()-3):U113)-MIN(INDEX(U:U,ROW()-3):U113))) -> 0.8 | AC113: =IF(B113<>"r04","",IF(COUNT(INDEX(V:V,ROW()-3):V113)<2,"",MAX(INDEX(V:V,ROW()-3):V113)-MIN(INDEX(V:V,ROW()-3):V113))) -> 0 | AD113: =IF(B113<>"r04","",COUNT(INDEX(U:U,ROW()-3):U113)) -> 4 | AE113: =IF(B113<>"r04","",COUNT(INDEX(V:V,ROW()-3):V113)) -> 4
A114: 474 | B114: r01 | C114: 2026-06-22_23-12-00__validacao_tcc_unifal_r01 | D114: 1718881 | E114: 92 | F114: sucesso | G114: 46196.013 | I114: sucesso_sem_nota | J114: 46196.014 | K114: 1 | L114: 0 | M114: parcial | O114: 46196.013 | P114: 46196.014 | Q114: =D114&"|"&B114 -> 1718881|r01 | R114: =VLOOKUP(D114,Base_Amostral!$A:$G,5,FALSE) -> Santa Maria do Tocantins | S114: =VLOOKUP(D114,Base_Amostral!$A:$G,3,FALSE) -> Tocantins | T114: =VLOOKUP(D114,Base_Amostral!$A:$G,6,FALSE) -> Norte | U114: =IF(E114="","",E114/10) -> 9.2 | V114: =IF(H114="","",H114/10) | W114: =IF(OR(U114="",V114=""),"",U114-V114) | X114: =IF(OR(U114="",V114=""),"",AVERAGE(U114:V114)) | Y114: =IF(AND(U114<>"",V114<>""),1,0) -> 0 | Z114: =IF(D114<>D113,"",IF(OR(U114="",U113=""),"",U114-U113)) | AA114: =IF(D114<>D113,"",IF(OR(V114="",V113=""),"",V114-V113)) | AB114: =IF(B114<>"r04","",IF(COUNT(INDEX(U:U,ROW()-3):U114)<2,"",MAX(INDEX(U:U,ROW()-3):U114)-MIN(INDEX(U:U,ROW()-3):U114))) | AC114: =IF(B114<>"r04","",IF(COUNT(INDEX(V:V,ROW()-3):V114)<2,"",MAX(INDEX(V:V,ROW()-3):V114)-MIN(INDEX(V:V,ROW()-3):V114))) | AD114: =IF(B114<>"r04","",COUNT(INDEX(U:U,ROW()-3):U114)) | AE114: =IF(B114<>"r04","",COUNT(INDEX(V:V,ROW()-3):V114))
A115: 821 | B115: r02 | C115: 2026-06-30_18-34-12__validacao_tcc_unifal_r02 | D115: 1718881 | E115: 92 | F115: sucesso | G115: 46203.81 | I115: sucesso_sem_nota | J115: 46203.811 | K115: 1 | L115: 0 | M115: parcial | O115: 46203.81 | P115: 46203.811 | Q115: =D115&"|"&B115 -> 1718881|r02 | R115: =VLOOKUP(D115,Base_Amostral!$A:$G,5,FALSE) -> Santa Maria do Tocantins | S115: =VLOOKUP(D115,Base_Amostral!$A:$G,3,FALSE) -> Tocantins | T115: =VLOOKUP(D115,Base_Amostral!$A:$G,6,FALSE) -> Norte | U115: =IF(E115="","",E115/10) -> 9.2 | V115: =IF(H115="","",H115/10) | W115: =IF(OR(U115="",V115=""),"",U115-V115) | X115: =IF(OR(U115="",V115=""),"",AVERAGE(U115:V115)) | Y115: =IF(AND(U115<>"",V115<>""),1,0) -> 0 | Z115: =IF(D115<>D114,"",IF(OR(U115="",U114=""),"",U115-U114)) -> 0 | AA115: =IF(D115<>D114,"",IF(OR(V115="",V114=""),"",V115-V114)) | AB115: =IF(B115<>"r04","",IF(COUNT(INDEX(U:U,ROW()-3):U115)<2,"",MAX(INDEX(U:U,ROW()-3):U115)-MIN(INDEX(U:U,ROW()-3):U115))) | AC115: =IF(B115<>"r04","",IF(COUNT(INDEX(V:V,ROW()-3):V115)<2,"",MAX(INDEX(V:V,ROW()-3):V115)-MIN(INDEX(V:V,ROW()-3):V115))) | AD115: =IF(B115<>"r04","",COUNT(INDEX(U:U,ROW()-3):U115)) | AE115: =IF(B115<>"r04","",COUNT(INDEX(V:V,ROW()-3):V115))
A116: 1176 | B116: r03 | C116: 2026-07-06_19-27-44__validacao_tcc_unifal_r03 | D116: 1718881 | E116: 92 | F116: sucesso | G116: 46209.853 | I116: sucesso_sem_nota | J116: 46209.854 | K116: 1 | L116: 0 | M116: parcial | O116: 46209.85 | P116: 46209.854 | Q116: =D116&"|"&B116 -> 1718881|r03 | R116: =VLOOKUP(D116,Base_Amostral!$A:$G,5,FALSE) -> Santa Maria do Tocantins | S116: =VLOOKUP(D116,Base_Amostral!$A:$G,3,FALSE) -> Tocantins | T116: =VLOOKUP(D116,Base_Amostral!$A:$G,6,FALSE) -> Norte | U116: =IF(E116="","",E116/10) -> 9.2 | V116: =IF(H116="","",H116/10) | W116: =IF(OR(U116="",V116=""),"",U116-V116) | X116: =IF(OR(U116="",V116=""),"",AVERAGE(U116:V116)) | Y116: =IF(AND(U116<>"",V116<>""),1,0) -> 0 | Z116: =IF(D116<>D115,"",IF(OR(U116="",U115=""),"",U116-U115)) -> 0 | AA116: =IF(D116<>D115,"",IF(OR(V116="",V115=""),"",V116-V115)) | AB116: =IF(B116<>"r04","",IF(COUNT(INDEX(U:U,ROW()-3):U116)<2,"",MAX(INDEX(U:U,ROW()-3):U116)-MIN(INDEX(U:U,ROW()-3):U116))) | AC116: =IF(B116<>"r04","",IF(COUNT(INDEX(V:V,ROW()-3):V116)<2,"",MAX(INDEX(V:V,ROW()-3):V116)-MIN(INDEX(V:V,ROW()-3):V116))) | AD116: =IF(B116<>"r04","",COUNT(INDEX(U:U,ROW()-3):U116)) | AE116: =IF(B116<>"r04","",COUNT(INDEX(V:V,ROW()-3):V116))
A117: 1538 | B117: r04 | C117: 2026-07-13_19-07-57__validacao_tcc_unifal_r04 | D117: 1718881 | E117: 96 | F117: sucesso | G117: 46216.828 | I117: sucesso_sem_nota | J117: 46216.829 | K117: 1 | L117: 0 | M117: parcial | O117: 46216.828 | P117: 46216.829 | Q117: =D117&"|"&B117 -> 1718881|r04 | R117: =VLOOKUP(D117,Base_Amostral!$A:$G,5,FALSE) -> Santa Maria do Tocantins | S117: =VLOOKUP(D117,Base_Amostral!$A:$G,3,FALSE) -> Tocantins | T117: =VLOOKUP(D117,Base_Amostral!$A:$G,6,FALSE) -> Norte | U117: =IF(E117="","",E117/10) -> 9.6 | V117: =IF(H117="","",H117/10) | W117: =IF(OR(U117="",V117=""),"",U117-V117) | X117: =IF(OR(U117="",V117=""),"",AVERAGE(U117:V117)) | Y117: =IF(AND(U117<>"",V117<>""),1,0) -> 0 | Z117: =IF(D117<>D116,"",IF(OR(U117="",U116=""),"",U117-U116)) -> 0.4 | AA117: =IF(D117<>D116,"",IF(OR(V117="",V116=""),"",V117-V116)) | AB117: =IF(B117<>"r04","",IF(COUNT(INDEX(U:U,ROW()-3):U117)<2,"",MAX(INDEX(U:U,ROW()-3):U117)-MIN(INDEX(U:U,ROW()-3):U117))) -> 0.4 | AC117: =IF(B117<>"r04","",IF(COUNT(INDEX(V:V,ROW()-3):V117)<2,"",MAX(INDEX(V:V,ROW()-3):V117)-MIN(INDEX(V:V,ROW()-3):V117))) | AD117: =IF(B117<>"r04","",COUNT(INDEX(U:U,ROW()-3):U117)) -> 4 | AE117: =IF(B117<>"r04","",COUNT(INDEX(V:V,ROW()-3):V117)) -> 0
A118: 478 | B118: r01 | C118: 2026-06-22_23-12-00__validacao_tcc_unifal_r01 | D118: 1722107 | E118: 92 | F118: sucesso | G118: 46196.014 | H118: 71 | I118: sucesso | J118: 46196.014 | K118: 1 | L118: 1 | M118: completo | O118: 46196.014 | P118: 46196.014 | Q118: =D118&"|"&B118 -> 1722107|r01 | R118: =VLOOKUP(D118,Base_Amostral!$A:$G,5,FALSE) -> Xambioá | S118: =VLOOKUP(D118,Base_Amostral!$A:$G,3,FALSE) -> Tocantins | T118: =VLOOKUP(D118,Base_Amostral!$A:$G,6,FALSE) -> Norte | U118: =IF(E118="","",E118/10) -> 9.2 | V118: =IF(H118="","",H118/10) -> 7.1 | W118: =IF(OR(U118="",V118=""),"",U118-V118) -> 2.1 | X118: =IF(OR(U118="",V118=""),"",AVERAGE(U118:V118)) -> 8.15 | Y118: =IF(AND(U118<>"",V118<>""),1,0) -> 1 | Z118: =IF(D118<>D117,"",IF(OR(U118="",U117=""),"",U118-U117)) | AA118: =IF(D118<>D117,"",IF(OR(V118="",V117=""),"",V118-V117)) | AB118: =IF(B118<>"r04","",IF(COUNT(INDEX(U:U,ROW()-3):U118)<2,"",MAX(INDEX(U:U,ROW()-3):U118)-MIN(INDEX(U:U,ROW()-3):U118))) | AC118: =IF(B118<>"r04","",IF(COUNT(INDEX(V:V,ROW()-3):V118)<2,"",MAX(INDEX(V:V,ROW()-3):V118)-MIN(INDEX(V:V,ROW()-3):V118))) | AD118: =IF(B118<>"r04","",COUNT(INDEX(U:U,ROW()-3):U118)) | AE118: =IF(B118<>"r04","",COUNT(INDEX(V:V,ROW()-3):V118))
A119: 825 | B119: r02 | C119: 2026-06-30_18-34-12__validacao_tcc_unifal_r02 | D119: 1722107 | E119: 92 | F119: sucesso | G119: 46203.814 | H119: 71 | I119: sucesso | J119: 46203.814 | K119: 1 | L119: 1 | M119: completo | O119: 46203.811 | P119: 46203.814 | Q119: =D119&"|"&B119 -> 1722107|r02 | R119: =VLOOKUP(D119,Base_Amostral!$A:$G,5,FALSE) -> Xambioá | S119: =VLOOKUP(D119,Base_Amostral!$A:$G,3,FALSE) -> Tocantins | T119: =VLOOKUP(D119,Base_Amostral!$A:$G,6,FALSE) -> Norte | U119: =IF(E119="","",E119/10) -> 9.2 | V119: =IF(H119="","",H119/10) -> 7.1 | W119: =IF(OR(U119="",V119=""),"",U119-V119) -> 2.1 | X119: =IF(OR(U119="",V119=""),"",AVERAGE(U119:V119)) -> 8.15 | Y119: =IF(AND(U119<>"",V119<>""),1,0) -> 1 | Z119: =IF(D119<>D118,"",IF(OR(U119="",U118=""),"",U119-U118)) -> 0 | AA119: =IF(D119<>D118,"",IF(OR(V119="",V118=""),"",V119-V118)) -> 0 | AB119: =IF(B119<>"r04","",IF(COUNT(INDEX(U:U,ROW()-3):U119)<2,"",MAX(INDEX(U:U,ROW()-3):U119)-MIN(INDEX(U:U,ROW()-3):U119))) | AC119: =IF(B119<>"r04","",IF(COUNT(INDEX(V:V,ROW()-3):V119)<2,"",MAX(INDEX(V:V,ROW()-3):V119)-MIN(INDEX(V:V,ROW()-3):V119))) | AD119: =IF(B119<>"r04","",COUNT(INDEX(U:U,ROW()-3):U119)) | AE119: =IF(B119<>"r04","",COUNT(INDEX(V:V,ROW()-3):V119))
A120: 1182 | B120: r03 | C120: 2026-07-06_19-27-44__validacao_tcc_unifal_r03 | D120: 1722107 | E120: 92 | F120: sucesso | G120: 46209.854 | H120: 71 | I120: sucesso | J120: 46209.854 | K120: 1 | L120: 1 | M120: completo | O120: 46209.854 | P120: 46209.854 | Q120: =D120&"|"&B120 -> 1722107|r03 | R120: =VLOOKUP(D120,Base_Amostral!$A:$G,5,FALSE) -> Xambioá | S120: =VLOOKUP(D120,Base_Amostral!$A:$G,3,FALSE) -> Tocantins | T120: =VLOOKUP(D120,Base_Amostral!$A:$G,6,FALSE) -> Norte | U120: =IF(E120="","",E120/10) -> 9.2 | V120: =IF(H120="","",H120/10) -> 7.1 | W120: =IF(OR(U120="",V120=""),"",U120-V120) -> 2.1 | X120: =IF(OR(U120="",V120=""),"",AVERAGE(U120:V120)) -> 8.15 | Y120: =IF(AND(U120<>"",V120<>""),1,0) -> 1 | Z120: =IF(D120<>D119,"",IF(OR(U120="",U119=""),"",U120-U119)) -> 0 | AA120: =IF(D120<>D119,"",IF(OR(V120="",V119=""),"",V120-V119)) -> 0 | AB120: =IF(B120<>"r04","",IF(COUNT(INDEX(U:U,ROW()-3):U120)<2,"",MAX(INDEX(U:U,ROW()-3):U120)-MIN(INDEX(U:U,ROW()-3):U120))) | AC120: =IF(B120<>"r04","",IF(COUNT(INDEX(V:V,ROW()-3):V120)<2,"",MAX(INDEX(V:V,ROW()-3):V120)-MIN(INDEX(V:V,ROW()-3):V120))) | AD120: =IF(B120<>"r04","",COUNT(INDEX(U:U,ROW()-3):U120)) | AE120: =IF(B120<>"r04","",COUNT(INDEX(V:V,ROW()-3):V120))
A121: 1540 | B121: r04 | C121: 2026-07-13_19-07-57__validacao_tcc_unifal_r04 | D121: 1722107 | E121: 96 | F121: sucesso | G121: 46216.83 | H121: 71 | I121: sucesso | J121: 46216.831 | K121: 1 | L121: 1 | M121: completo | O121: 46216.829 | P121: 46216.831 | Q121: =D121&"|"&B121 -> 1722107|r04 | R121: =VLOOKUP(D121,Base_Amostral!$A:$G,5,FALSE) -> Xambioá | S121: =VLOOKUP(D121,Base_Amostral!$A:$G,3,FALSE) -> Tocantins | T121: =VLOOKUP(D121,Base_Amostral!$A:$G,6,FALSE) -> Norte | U121: =IF(E121="","",E121/10) -> 9.6 | V121: =IF(H121="","",H121/10) -> 7.1 | W121: =IF(OR(U121="",V121=""),"",U121-V121) -> 2.5 | X121: =IF(OR(U121="",V121=""),"",AVERAGE(U121:V121)) -> 8.35 | Y121: =IF(AND(U121<>"",V121<>""),1,0) -> 1 | Z121: =IF(D121<>D120,"",IF(OR(U121="",U120=""),"",U121-U120)) -> 0.4 | AA121: =IF(D121<>D120,"",IF(OR(V121="",V120=""),"",V121-V120)) -> 0 | AB121: =IF(B121<>"r04","",IF(COUNT(INDEX(U:U,ROW()-3):U121)<2,"",MAX(INDEX(U:U,ROW()-3):U121)-MIN(INDEX(U:U,ROW()-3):U121))) -> 0.4 | AC121: =IF(B121<>"r04","",IF(COUNT(INDEX(V:V,ROW()-3):V121)<2,"",MAX(INDEX(V:V,ROW()-3):V121)-MIN(INDEX(V:V,ROW()-3):V121))) -> 0 | AD121: =IF(B121<>"r04","",COUNT(INDEX(U:U,ROW()-3):U121)) -> 4 | AE121: =IF(B121<>"r04","",COUNT(INDEX(V:V,ROW()-3):V121)) -> 4
A122: 495 | B122: r01 | C122: 2026-06-22_23-12-00__validacao_tcc_unifal_r01 | D122: 2100436 | E122: 69 | F122: sucesso | G122: 46196.022 | H122: 65 | I122: sucesso | J122: 46196.022 | K122: 1 | L122: 1 | M122: completo | O122: 46196.02 | P122: 46196.022 | Q122: =D122&"|"&B122 -> 2100436|r01 | R122: =VLOOKUP(D122,Base_Amostral!$A:$G,5,FALSE) -> Alto Alegre do Maranhão | S122: =VLOOKUP(D122,Base_Amostral!$A:$G,3,FALSE) -> Maranhão | T122: =VLOOKUP(D122,Base_Amostral!$A:$G,6,FALSE) -> Nordeste | U122: =IF(E122="","",E122/10) -> 6.9 | V122: =IF(H122="","",H122/10) -> 6.5 | W122: =IF(OR(U122="",V122=""),"",U122-V122) -> 0.4 | X122: =IF(OR(U122="",V122=""),"",AVERAGE(U122:V122)) -> 6.7 | Y122: =IF(AND(U122<>"",V122<>""),1,0) -> 1 | Z122: =IF(D122<>D121,"",IF(OR(U122="",U121=""),"",U122-U121)) | AA122: =IF(D122<>D121,"",IF(OR(V122="",V121=""),"",V122-V121)) | AB122: =IF(B122<>"r04","",IF(COUNT(INDEX(U:U,ROW()-3):U122)<2,"",MAX(INDEX(U:U,ROW()-3):U122)-MIN(INDEX(U:U,ROW()-3):U122))) | AC122: =IF(B122<>"r04","",IF(COUNT(INDEX(V:V,ROW()-3):V122)<2,"",MAX(INDEX(V:V,ROW()-3):V122)-MIN(INDEX(V:V,ROW()-3):V122))) | AD122: =IF(B122<>"r04","",COUNT(INDEX(U:U,ROW()-3):U122)) | AE122: =IF(B122<>"r04","",COUNT(INDEX(V:V,ROW()-3):V122))
A123: 844 | B123: r02 | C123: 2026-06-30_18-34-12__validacao_tcc_unifal_r02 | D123: 2100436 | E123: 69 | F123: sucesso | G123: 46203.818 | H123: 65 | I123: sucesso | J123: 46203.818 | K123: 1 | L123: 1 | M123: completo | O123: 46203.817 | P123: 46203.818 | Q123: =D123&"|"&B123 -> 2100436|r02 | R123: =VLOOKUP(D123,Base_Amostral!$A:$G,5,FALSE) -> Alto Alegre do Maranhão | S123: =VLOOKUP(D123,Base_Amostral!$A:$G,3,FALSE) -> Maranhão | T123: =VLOOKUP(D123,Base_Amostral!$A:$G,6,FALSE) -> Nordeste | U123: =IF(E123="","",E123/10) -> 6.9 | V123: =IF(H123="","",H123/10) -> 6.5 | W123: =IF(OR(U123="",V123=""),"",U123-V123) -> 0.4 | X123: =IF(OR(U123="",V123=""),"",AVERAGE(U123:V123)) -> 6.7 | Y123: =IF(AND(U123<>"",V123<>""),1,0) -> 1 | Z123: =IF(D123<>D122,"",IF(OR(U123="",U122=""),"",U123-U122)) -> 0 | AA123: =IF(D123<>D122,"",IF(OR(V123="",V122=""),"",V123-V122)) -> 0 | AB123: =IF(B123<>"r04","",IF(COUNT(INDEX(U:U,ROW()-3):U123)<2,"",MAX(INDEX(U:U,ROW()-3):U123)-MIN(INDEX(U:U,ROW()-3):U123))) | AC123: =IF(B123<>"r04","",IF(COUNT(INDEX(V:V,ROW()-3):V123)<2,"",MAX(INDEX(V:V,ROW()-3):V123)-MIN(INDEX(V:V,ROW()-3):V123))) | AD123: =IF(B123<>"r04","",COUNT(INDEX(U:U,ROW()-3):U123)) | AE123: =IF(B123<>"r04","",COUNT(INDEX(V:V,ROW()-3):V123))
A124: 1220 | B124: r03 | C124: 2026-07-06_19-27-44__validacao_tcc_unifal_r03 | D124: 2100436 | E124: 69 | F124: sucesso | G124: 46209.869 | H124: 65 | I124: sucesso | J124: 46209.869 | K124: 1 | L124: 1 | M124: completo | O124: 46209.868 | P124: 46209.869 | Q124: =D124&"|"&B124 -> 2100436|r03 | R124: =VLOOKUP(D124,Base_Amostral!$A:$G,5,FALSE) -> Alto Alegre do Maranhão | S124: =VLOOKUP(D124,Base_Amostral!$A:$G,3,FALSE) -> Maranhão | T124: =VLOOKUP(D124,Base_Amostral!$A:$G,6,FALSE) -> Nordeste | U124: =IF(E124="","",E124/10) -> 6.9 | V124: =IF(H124="","",H124/10) -> 6.5 | W124: =IF(OR(U124="",V124=""),"",U124-V124) -> 0.4 | X124: =IF(OR(U124="",V124=""),"",AVERAGE(U124:V124)) -> 6.7 | Y124: =IF(AND(U124<>"",V124<>""),1,0) -> 1 | Z124: =IF(D124<>D123,"",IF(OR(U124="",U123=""),"",U124-U123)) -> 0 | AA124: =IF(D124<>D123,"",IF(OR(V124="",V123=""),"",V124-V123)) -> 0 | AB124: =IF(B124<>"r04","",IF(COUNT(INDEX(U:U,ROW()-3):U124)<2,"",MAX(INDEX(U:U,ROW()-3):U124)-MIN(INDEX(U:U,ROW()-3):U124))) | AC124: =IF(B124<>"r04","",IF(COUNT(INDEX(V:V,ROW()-3):V124)<2,"",MAX(INDEX(V:V,ROW()-3):V124)-MIN(INDEX(V:V,ROW()-3):V124))) | AD124: =IF(B124<>"r04","",COUNT(INDEX(U:U,ROW()-3):U124)) | AE124: =IF(B124<>"r04","",COUNT(INDEX(V:V,ROW()-3):V124))
A125: 1585 | B125: r04 | C125: 2026-07-13_19-07-57__validacao_tcc_unifal_r04 | D125: 2100436 | E125: 79 | F125: sucesso | G125: 46216.847 | H125: 65 | I125: sucesso | J125: 46216.847 | K125: 1 | L125: 1 | M125: completo | O125: 46216.847 | P125: 46216.847 | Q125: =D125&"|"&B125 -> 2100436|r04 | R125: =VLOOKUP(D125,Base_Amostral!$A:$G,5,FALSE) -> Alto Alegre do Maranhão | S125: =VLOOKUP(D125,Base_Amostral!$A:$G,3,FALSE) -> Maranhão | T125: =VLOOKUP(D125,Base_Amostral!$A:$G,6,FALSE) -> Nordeste | U125: =IF(E125="","",E125/10) -> 7.9 | V125: =IF(H125="","",H125/10) -> 6.5 | W125: =IF(OR(U125="",V125=""),"",U125-V125) -> 1.4 | X125: =IF(OR(U125="",V125=""),"",AVERAGE(U125:V125)) -> 7.2 | Y125: =IF(AND(U125<>"",V125<>""),1,0) -> 1 | Z125: =IF(D125<>D124,"",IF(OR(U125="",U124=""),"",U125-U124)) -> 1 | AA125: =IF(D125<>D124,"",IF(OR(V125="",V124=""),"",V125-V124)) -> 0 | AB125: =IF(B125<>"r04","",IF(COUNT(INDEX(U:U,ROW()-3):U125)<2,"",MAX(INDEX(U:U,ROW()-3):U125)-MIN(INDEX(U:U,ROW()-3):U125))) -> 1 | AC125: =IF(B125<>"r04","",IF(COUNT(INDEX(V:V,ROW()-3):V125)<2,"",MAX(INDEX(V:V,ROW()-3):V125)-MIN(INDEX(V:V,ROW()-3):V125))) -> 0 | AD125: =IF(B125<>"r04","",COUNT(INDEX(U:U,ROW()-3):U125)) -> 4 | AE125: =IF(B125<>"r04","",COUNT(INDEX(V:V,ROW()-3):V125)) -> 4
A126: 501 | B126: r01 | C126: 2026-06-22_23-12-00__validacao_tcc_unifal_r01 | D126: 2100501 | E126: 73 | F126: sucesso | G126: 46196.022 | H126: 63 | I126: sucesso | J126: 46196.023 | K126: 1 | L126: 1 | M126: completo | O126: 46196.022 | P126: 46196.023 | Q126: =D126&"|"&B126 -> 2100501|r01 | R126: =VLOOKUP(D126,Base_Amostral!$A:$G,5,FALSE) -> Alto Parnaíba | S126: =VLOOKUP(D126,Base_Amostral!$A:$G,3,FALSE) -> Maranhão | T126: =VLOOKUP(D126,Base_Amostral!$A:$G,6,FALSE) -> Nordeste | U126: =IF(E126="","",E126/10) -> 7.3 | V126: =IF(H126="","",H126/10) -> 6.3 | W126: =IF(OR(U126="",V126=""),"",U126-V126) -> 1 | X126: =IF(OR(U126="",V126=""),"",AVERAGE(U126:V126)) -> 6.8 | Y126: =IF(AND(U126<>"",V126<>""),1,0) -> 1 | Z126: =IF(D126<>D125,"",IF(OR(U126="",U125=""),"",U126-U125)) | AA126: =IF(D126<>D125,"",IF(OR(V126="",V125=""),"",V126-V125)) | AB126: =IF(B126<>"r04","",IF(COUNT(INDEX(U:U,ROW()-3):U126)<2,"",MAX(INDEX(U:U,ROW()-3):U126)-MIN(INDEX(U:U,ROW()-3):U126))) | AC126: =IF(B126<>"r04","",IF(COUNT(INDEX(V:V,ROW()-3):V126)<2,"",MAX(INDEX(V:V,ROW()-3):V126)-MIN(INDEX(V:V,ROW()-3):V126))) | AD126: =IF(B126<>"r04","",COUNT(INDEX(U:U,ROW()-3):U126)) | AE126: =IF(B126<>"r04","",COUNT(INDEX(V:V,ROW()-3):V126))
A127: 848 | B127: r02 | C127: 2026-06-30_18-34-12__validacao_tcc_unifal_r02 | D127: 2100501 | E127: 68 | F127: sucesso | G127: 46203.818 | H127: 63 | I127: sucesso | J127: 46203.819 | K127: 1 | L127: 1 | M127: completo | O127: 46203.818 | P127: 46203.819 | Q127: =D127&"|"&B127 -> 2100501|r02 | R127: =VLOOKUP(D127,Base_Amostral!$A:$G,5,FALSE) -> Alto Parnaíba | S127: =VLOOKUP(D127,Base_Amostral!$A:$G,3,FALSE) -> Maranhão | T127: =VLOOKUP(D127,Base_Amostral!$A:$G,6,FALSE) -> Nordeste | U127: =IF(E127="","",E127/10) -> 6.8 | V127: =IF(H127="","",H127/10) -> 6.3 | W127: =IF(OR(U127="",V127=""),"",U127-V127) -> 0.5 | X127: =IF(OR(U127="",V127=""),"",AVERAGE(U127:V127)) -> 6.55 | Y127: =IF(AND(U127<>"",V127<>""),1,0) -> 1 | Z127: =IF(D127<>D126,"",IF(OR(U127="",U126=""),"",U127-U126)) -> -0.5 | AA127: =IF(D127<>D126,"",IF(OR(V127="",V126=""),"",V127-V126)) -> 0 | AB127: =IF(B127<>"r04","",IF(COUNT(INDEX(U:U,ROW()-3):U127)<2,"",MAX(INDEX(U:U,ROW()-3):U127)-MIN(INDEX(U:U,ROW()-3):U127))) | AC127: =IF(B127<>"r04","",IF(COUNT(INDEX(V:V,ROW()-3):V127)<2,"",MAX(INDEX(V:V,ROW()-3):V127)-MIN(INDEX(V:V,ROW()-3):V127))) | AD127: =IF(B127<>"r04","",COUNT(INDEX(U:U,ROW()-3):U127)) | AE127: =IF(B127<>"r04","",COUNT(INDEX(V:V,ROW()-3):V127))
A128: 1222 | B128: r03 | C128: 2026-07-06_19-27-44__validacao_tcc_unifal_r03 | D128: 2100501 | E128: 73 | F128: sucesso | G128: 46209.871 | H128: 68 | I128: sucesso | J128: 46209.872 | K128: 1 | L128: 1 | M128: completo | O128: 46209.869 | P128: 46209.872 | Q128: =D128&"|"&B128 -> 2100501|r03 | R128: =VLOOKUP(D128,Base_Amostral!$A:$G,5,FALSE) -> Alto Parnaíba | S128: =VLOOKUP(D128,Base_Amostral!$A:$G,3,FALSE) -> Maranhão | T128: =VLOOKUP(D128,Base_Amostral!$A:$G,6,FALSE) -> Nordeste | U128: =IF(E128="","",E128/10) -> 7.3 | V128: =IF(H128="","",H128/10) -> 6.8 | W128: =IF(OR(U128="",V128=""),"",U128-V128) -> 0.5 | X128: =IF(OR(U128="",V128=""),"",AVERAGE(U128:V128)) -> 7.05 | Y128: =IF(AND(U128<>"",V128<>""),1,0) -> 1 | Z128: =IF(D128<>D127,"",IF(OR(U128="",U127=""),"",U128-U127)) -> 0.5 | AA128: =IF(D128<>D127,"",IF(OR(V128="",V127=""),"",V128-V127)) -> 0.5 | AB128: =IF(B128<>"r04","",IF(COUNT(INDEX(U:U,ROW()-3):U128)<2,"",MAX(INDEX(U:U,ROW()-3):U128)-MIN(INDEX(U:U,ROW()-3):U128))) | AC128: =IF(B128<>"r04","",IF(COUNT(INDEX(V:V,ROW()-3):V128)<2,"",MAX(INDEX(V:V,ROW()-3):V128)-MIN(INDEX(V:V,ROW()-3):V128))) | AD128: =IF(B128<>"r04","",COUNT(INDEX(U:U,ROW()-3):U128)) | AE128: =IF(B128<>"r04","",COUNT(INDEX(V:V,ROW()-3):V128))
A129: 1587 | B129: r04 | C129: 2026-07-13_19-07-57__validacao_tcc_unifal_r04 | D129: 2100501 | E129: 80 | F129: sucesso | G129: 46216.848 | H129: 63 | I129: sucesso | J129: 46216.848 | K129: 1 | L129: 1 | M129: completo | O129: 46216.847 | P129: 46216.848 | Q129: =D129&"|"&B129 -> 2100501|r04 | R129: =VLOOKUP(D129,Base_Amostral!$A:$G,5,FALSE) -> Alto Parnaíba | S129: =VLOOKUP(D129,Base_Amostral!$A:$G,3,FALSE) -> Maranhão | T129: =VLOOKUP(D129,Base_Amostral!$A:$G,6,FALSE) -> Nordeste | U129: =IF(E129="","",E129/10) -> 8 | V129: =IF(H129="","",H129/10) -> 6.3 | W129: =IF(OR(U129="",V129=""),"",U129-V129) -> 1.7 | X129: =IF(OR(U129="",V129=""),"",AVERAGE(U129:V129)) -> 7.15 | Y129: =IF(AND(U129<>"",V129<>""),1,0) -> 1 | Z129: =IF(D129<>D128,"",IF(OR(U129="",U128=""),"",U129-U128)) -> 0.7 | AA129: =IF(D129<>D128,"",IF(OR(V129="",V128=""),"",V129-V128)) -> -0.5 | AB129: =IF(B129<>"r04","",IF(COUNT(INDEX(U:U,ROW()-3):U129)<2,"",MAX(INDEX(U:U,ROW()-3):U129)-MIN(INDEX(U:U,ROW()-3):U129))) -> 1.2 | AC129: =IF(B129<>"r04","",IF(COUNT(INDEX(V:V,ROW()-3):V129)<2,"",MAX(INDEX(V:V,ROW()-3):V129)-MIN(INDEX(V:V,ROW()-3):V129))) -> 0.5 | AD129: =IF(B129<>"r04","",COUNT(INDEX(U:U,ROW()-3):U129)) -> 4 | AE129: =IF(B129<>"r04","",COUNT(INDEX(V:V,ROW()-3):V129)) -> 4
... A196: 1337 | B196: r03 | C196: 2026-07-06_19-27-44__validacao_tcc_unifal_r03 | D196: 2202901 | E196: 66 | F196: sucesso | G196: 46209.909 | H196: 65 | I196: sucesso | J196: 46209.91 | K196: 1 | L196: 1 | M196: completo | O196: 46209.909 | P196: 46209.91 | Q196: =D196&"|"&B196 -> 2202901|r03 | R196: =VLOOKUP(D196,Base_Amostral!$A:$G,5,FALSE) -> Corrente | S196: =VLOOKUP(D196,Base_Amostral!$A:$G,3,FALSE) -> Piauí | T196: =VLOOKUP(D196,Base_Amostral!$A:$G,6,FALSE) -> Nordeste | U196: =IF(E196="","",E196/10) -> 6.6 | V196: =IF(H196="","",H196/10) -> 6.5 | W196: =IF(OR(U196="",V196=""),"",U196-V196) -> 0.1 | X196: =IF(OR(U196="",V196=""),"",AVERAGE(U196:V196)) -> 6.55 | Y196: =IF(AND(U196<>"",V196<>""),1,0) -> 1 | Z196: =IF(D196<>D195,"",IF(OR(U196="",U195=""),"",U196-U195)) -> 0 | AA196: =IF(D196<>D195,"",IF(OR(V196="",V195=""),"",V196-V195)) -> 0 | AB196: =IF(B196<>"r04","",IF(COUNT(INDEX(U:U,ROW()-3):U196)<2,"",MAX(INDEX(U:U,ROW()-3):U196)-MIN(INDEX(U:U,ROW()-3):U196))) | AC196: =IF(B196<>"r04","",IF(COUNT(INDEX(V:V,ROW()-3):V196)<2,"",MAX(INDEX(V:V,ROW()-3):V196)-MIN(INDEX(V:V,ROW()-3):V196))) | AD196: =IF(B196<>"r04","",COUNT(INDEX(U:U,ROW()-3):U196)) | AE196: =IF(B196<>"r04","",COUNT(INDEX(V:V,ROW()-3):V196))
A197: 1714 | B197: r04 | C197: 2026-07-13_19-07-57__validacao_tcc_unifal_r04 | D197: 2202901 | F197: falha_de_carregamento | G197: 46216.901 | I197: erro | J197: 46216.902 | K197: 0 | L197: 0 | M197: falha_total | O197: 46216.895 | P197: 46216.902 | Q197: =D197&"|"&B197 -> 2202901|r04 | R197: =VLOOKUP(D197,Base_Amostral!$A:$G,5,FALSE) -> Corrente | S197: =VLOOKUP(D197,Base_Amostral!$A:$G,3,FALSE) -> Piauí | T197: =VLOOKUP(D197,Base_Amostral!$A:$G,6,FALSE) -> Nordeste | U197: =IF(E197="","",E197/10) | V197: =IF(H197="","",H197/10) | W197: =IF(OR(U197="",V197=""),"",U197-V197) | X197: =IF(OR(U197="",V197=""),"",AVERAGE(U197:V197)) | Y197: =IF(AND(U197<>"",V197<>""),1,0) -> 0 | Z197: =IF(D197<>D196,"",IF(OR(U197="",U196=""),"",U197-U196)) | AA197: =IF(D197<>D196,"",IF(OR(V197="",V196=""),"",V197-V196)) | AB197: =IF(B197<>"r04","",IF(COUNT(INDEX(U:U,ROW()-3):U197)<2,"",MAX(INDEX(U:U,ROW()-3):U197)-MIN(INDEX(U:U,ROW()-3):U197))) -> 0 | AC197: =IF(B197<>"r04","",IF(COUNT(INDEX(V:V,ROW()-3):V197)<2,"",MAX(INDEX(V:V,ROW()-3):V197)-MIN(INDEX(V:V,ROW()-3):V197))) -> 0 | AD197: =IF(B197<>"r04","",COUNT(INDEX(U:U,ROW()-3):U197)) -> 3 | AE197: =IF(B197<>"r04","",COUNT(INDEX(V:V,ROW()-3):V197)) -> 3
A198: 654 | B198: r01 | C198: 2026-06-22_23-12-00__validacao_tcc_unifal_r01 | D198: 2203305 | E198: 73 | F198: sucesso | G198: 46196.077 | H198: 71 | I198: sucesso | J198: 46196.077 | K198: 1 | L198: 1 | M198: completo | O198: 46196.076 | P198: 46196.077 | Q198: =D198&"|"&B198 -> 2203305|r01 | R198: =VLOOKUP(D198,Base_Amostral!$A:$G,5,FALSE) -> Demerval Lobão | S198: =VLOOKUP(D198,Base_Amostral!$A:$G,3,FALSE) -> Piauí | T198: =VLOOKUP(D198,Base_Amostral!$A:$G,6,FALSE) -> Nordeste | U198: =IF(E198="","",E198/10) -> 7.3 | V198: =IF(H198="","",H198/10) -> 7.1 | W198: =IF(OR(U198="",V198=""),"",U198-V198) -> 0.2 | X198: =IF(OR(U198="",V198=""),"",AVERAGE(U198:V198)) -> 7.2 | Y198: =IF(AND(U198<>"",V198<>""),1,0) -> 1 | Z198: =IF(D198<>D197,"",IF(OR(U198="",U197=""),"",U198-U197)) | AA198: =IF(D198<>D197,"",IF(OR(V198="",V197=""),"",V198-V197)) | AB198: =IF(B198<>"r04","",IF(COUNT(INDEX(U:U,ROW()-3):U198)<2,"",MAX(INDEX(U:U,ROW()-3):U198)-MIN(INDEX(U:U,ROW()-3):U198))) | AC198: =IF(B198<>"r04","",IF(COUNT(INDEX(V:V,ROW()-3):V198)<2,"",MAX(INDEX(V:V,ROW()-3):V198)-MIN(INDEX(V:V,ROW()-3):V198))) | AD198: =IF(B198<>"r04","",COUNT(INDEX(U:U,ROW()-3):U198)) | AE198: =IF(B198<>"r04","",COUNT(INDEX(V:V,ROW()-3):V198))
A199: 983 | B199: r02 | C199: 2026-06-30_18-34-12__validacao_tcc_unifal_r02 | D199: 2203305 | E199: 73 | F199: sucesso | G199: 46203.871 | H199: 71 | I199: sucesso | J199: 46203.872 | K199: 1 | L199: 1 | M199: completo | O199: 46203.871 | P199: 46203.872 | Q199: =D199&"|"&B199 -> 2203305|r02 | R199: =VLOOKUP(D199,Base_Amostral!$A:$G,5,FALSE) -> Demerval Lobão | S199: =VLOOKUP(D199,Base_Amostral!$A:$G,3,FALSE) -> Piauí | T199: =VLOOKUP(D199,Base_Amostral!$A:$G,6,FALSE) -> Nordeste | U199: =IF(E199="","",E199/10) -> 7.3 | V199: =IF(H199="","",H199/10) -> 7.1 | W199: =IF(OR(U199="",V199=""),"",U199-V199) -> 0.2 | X199: =IF(OR(U199="",V199=""),"",AVERAGE(U199:V199)) -> 7.2 | Y199: =IF(AND(U199<>"",V199<>""),1,0) -> 1 | Z199: =IF(D199<>D198,"",IF(OR(U199="",U198=""),"",U199-U198)) -> 0 | AA199: =IF(D199<>D198,"",IF(OR(V199="",V198=""),"",V199-V198)) -> 0 | AB199: =IF(B199<>"r04","",IF(COUNT(INDEX(U:U,ROW()-3):U199)<2,"",MAX(INDEX(U:U,ROW()-3):U199)-MIN(INDEX(U:U,ROW()-3):U199))) | AC199: =IF(B199<>"r04","",IF(COUNT(INDEX(V:V,ROW()-3):V199)<2,"",MAX(INDEX(V:V,ROW()-3):V199)-MIN(INDEX(V:V,ROW()-3):V199))) | AD199: =IF(B199<>"r04","",COUNT(INDEX(U:U,ROW()-3):U199)) | AE199: =IF(B199<>"r04","",COUNT(INDEX(V:V,ROW()-3):V199))
A200: 1341 | B200: r03 | C200: 2026-07-06_19-27-44__validacao_tcc_unifal_r03 | D200: 2203305 | E200: 73 | F200: sucesso | G200: 46209.91 | H200: 71 | I200: sucesso | J200: 46209.91 | K200: 1 | L200: 1 | M200: completo | O200: 46209.91 | P200: 46209.91 | Q200: =D200&"|"&B200 -> 2203305|r03 | R200: =VLOOKUP(D200,Base_Amostral!$A:$G,5,FALSE) -> Demerval Lobão | S200: =VLOOKUP(D200,Base_Amostral!$A:$G,3,FALSE) -> Piauí | T200: =VLOOKUP(D200,Base_Amostral!$A:$G,6,FALSE) -> Nordeste | U200: =IF(E200="","",E200/10) -> 7.3 | V200: =IF(H200="","",H200/10) -> 7.1 | W200: =IF(OR(U200="",V200=""),"",U200-V200) -> 0.2 | X200: =IF(OR(U200="",V200=""),"",AVERAGE(U200:V200)) -> 7.2 | Y200: =IF(AND(U200<>"",V200<>""),1,0) -> 1 | Z200: =IF(D200<>D199,"",IF(OR(U200="",U199=""),"",U200-U199)) -> 0 | AA200: =IF(D200<>D199,"",IF(OR(V200="",V199=""),"",V200-V199)) -> 0 | AB200: =IF(B200<>"r04","",IF(COUNT(INDEX(U:U,ROW()-3):U200)<2,"",MAX(INDEX(U:U,ROW()-3):U200)-MIN(INDEX(U:U,ROW()-3):U200))) | AC200: =IF(B200<>"r04","",IF(COUNT(INDEX(V:V,ROW()-3):V200)<2,"",MAX(INDEX(V:V,ROW()-3):V200)-MIN(INDEX(V:V,ROW()-3):V200))) | AD200: =IF(B200<>"r04","",COUNT(INDEX(U:U,ROW()-3):U200)) | AE200: =IF(B200<>"r04","",COUNT(INDEX(V:V,ROW()-3):V200))
A201: 1724 | B201: r04 | C201: 2026-07-13_19-07-57__validacao_tcc_unifal_r04 | D201: 2203305 | E201: 78 | F201: sucesso | G201: 46216.903 | H201: 71 | I201: sucesso | J201: 46216.903 | K201: 1 | L201: 1 | M201: completo | O201: 46216.902 | P201: 46216.903 | Q201: =D201&"|"&B201 -> 2203305|r04 | R201: =VLOOKUP(D201,Base_Amostral!$A:$G,5,FALSE) -> Demerval Lobão | S201: =VLOOKUP(D201,Base_Amostral!$A:$G,3,FALSE) -> Piauí | T201: =VLOOKUP(D201,Base_Amostral!$A:$G,6,FALSE) -> Nordeste | U201: =IF(E201="","",E201/10) -> 7.8 | V201: =IF(H201="","",H201/10) -> 7.1 | W201: =IF(OR(U201="",V201=""),"",U201-V201) -> 0.7 | X201: =IF(OR(U201="",V201=""),"",AVERAGE(U201:V201)) -> 7.45 | Y201: =IF(AND(U201<>"",V201<>""),1,0) -> 1 | Z201: =IF(D201<>D200,"",IF(OR(U201="",U200=""),"",U201-U200)) -> 0.5 | AA201: =IF(D201<>D200,"",IF(OR(V201="",V200=""),"",V201-V200)) -> 0 | AB201: =IF(B201<>"r04","",IF(COUNT(INDEX(U:U,ROW()-3):U201)<2,"",MAX(INDEX(U:U,ROW()-3):U201)-MIN(INDEX(U:U,ROW()-3):U201))) -> 0.5 | AC201: =IF(B201<>"r04","",IF(COUNT(INDEX(V:V,ROW()-3):V201)<2,"",MAX(INDEX(V:V,ROW()-3):V201)-MIN(INDEX(V:V,ROW()-3):V201))) -> 0 | AD201: =IF(B201<>"r04","",COUNT(INDEX(U:U,ROW()-3):U201)) -> 4 | AE201: =IF(B201<>"r04","",COUNT(INDEX(V:V,ROW()-3):V201)) -> 4
